Workbook

Sheet README
A1: Merchant statement parse: sample Fiserv / CardPointe statement
A3: Source | B3: Sample Fiserv Statement.pdf (16 pages), card processing statement, period 07/01/2026 to 07/31/2026, corporate number 496115385882.
A4: Method | B4: Text was extracted from the PDF text layer and parsed with Python (regular expressions, decimal arithmetic). The parsed data was compared with the PDF text (every dollar amount on pages 2-16 matches in order, plus the page 1 values), then every table was validated in this workbook with live Excel formulas (see Checks).
A5: Result | B5: 77 of 78 checks pass: every parsed control total ties to the statement to the cent. The one REVIEW is a variance inside the source statement (3 interchange lines whose printed charge differs from rate x sales + transactions x fee). See Checks and Findings.
A6: Sign convention | B6: As printed on the statement: submitted sales and positive adjustments are positive; refunds, Paid by Others, disputes and fees are negative.
A7: Not parsed | B7: The compliance notice after page 16 (boilerplate, no data).
A8: Header | B8: Company and address on the Summary sheet are what page 1 visibly shows (ABC Company, DOWNINGTOWN PA 19335). The text layer holds different, more detailed text behind the overlay; it is not copied here (see Findings).
A10: Sheet | B10: Content
A11: Summary | B11: Statement header and account summary, with the summary equation recomputed.
A12: Cost Summary | B12: Effective rate (total and excluding AMEX), pass-through vs processor fees, effective rate by card brand and the 10 largest fee lines, all as live formulas.
A13: Trend | B13: 13-month sales trend from the page 1 chart, with YoY and MoM recomputed.
A14: Daily | B14: Summary By Day (31 dated rows incl. 06/30, the month-end charge and the total), row checks and tie-out to Funded.
A15: CardType | B15: Summary by Card Type with gross, refunds, net and average ticket recomputed.
... A24: Findings | B24: Parsing hazards found in this statement layout and source-statement variances to review.

Sheet Summary
A1: Statement header and account summary
A3: Statement
A4: Statement type | B4: CardConnect (Fiserv) card processing statement | C4: Logo reads cardconnect; contact site cardpointe.com
A5: Source file | B5: Sample Fiserv Statement.pdf | C5: 16 pages
A6: Corporate number | B6: 496115385882 | C6: Page 1 and the page headers show it truncated (4961); the full number is visible as the first Location ID in Summary By Location (page 3)
A7: Period start | B7: 46204
A8: Period end | B8: 46234
A9: Locations included | B9: 23 | C9: Printed on page 1; recounted in Checks
A10: Company (as displayed) | B10: ABC Company | C10: Exactly as printed on page 1
A11: City / state / ZIP (as displayed) | B11: DOWNINGTOWN PA 19335 | C11: No street address or contact name is visible on page 1
A12: Hidden text behind the header | B12: Yes | C12: The page 1 text layer holds a different company name, a contact name and a street address behind the overlay. Deliberately not copied here.
A13: Processor customer service | B13: 1-877-828-0720 / cardpointe.com
A15: Account Summary (page 1)
A16: Amount Submitted | B16: 8980209.2
A17: Paid by Others | B17: -1678631.3
A18: Disputes | B18: -1213.82
A19: Adjustments | B19: 0
A20: Fees | B20: -170258.04
A21: Amount Processed (statement) | B21: 7130106 | C21: Page 1 boxes are positioned out of label order in the text layer; mapped by equation and by the Total rows
A22: Amount Processed (computed) | B22: =SUM(B16:B20) -> 7130106
A23: Difference | B23: =B22-B21 -> 0
A25: New Customers | B25: 3481
A26: Repeat Customers | B26: 1548
A27: Avg. Ticket Size (statement) | B27: 808.08
A28: Avg. Ticket Size (computed) | B28: =ROUND(B16/CardType!G10,2) -> 808.08 | C28: Net submitted / net items (CardType total)
A29: Sales change Jul 25 vs Jul 26 | B29: 1.7827 | C29: Printed as "178.27% year over year"
A30: Sales change Jun 26 vs Jul 26 | B30: 0.0182 | C30: Printed as "1.82% month over month"

Sheet Cost Summary
A1: Cost summary: effective rate, pass-through and processor fees
A2: Fees are shown here as positive costs. Every value is a live formula on the Summary, CardType, FeeSummary and FeeDetail sheets.
A4: Volume
A5: Gross sales | B5: =CardType!D9 -> 9228078.2
A6: Refunds | B6: =CardType!F9 -> -247869
A7: Amount submitted (net) | B7: =Summary!B16 -> 8980209.2
A8: Transactions (sales + refunds) | B8: =CardType!G9 -> 11113
A9: Average ticket | B9: =Summary!B27 -> 808.08
A10: Refund rate (refunds / gross sales) | B10: =-CardType!F9/CardType!D9 -> 0.026860306
A12: Cost
A13: Total fees | B13: =-Summary!B20 -> 170258.04
A14: Effective rate (total fees / amount submitted) | B14: =B13/B7 -> 0.018959251
A15: Amount submitted excluding AMEX | B15: =B7-CardType!H7 -> 7301577.9 | C15: AMEX is funded and priced directly by American Express (Paid by Others)
A16: Fees excluding AMEX | B16: =B13+FeeSummary!D8 -> 170088.04 | C16: Only $170.00 of AMEX-related processor fees appear on this statement
A17: Effective rate excluding AMEX | B17: =B16/B15 -> 0.023294696
A18: Pass-through: interchange + card-brand assessments (IC/PF) | B18: =-FeeSummary!H6 -> 146436.8 | C18: Includes $9,965.45 of assessments/network fees and $3,863.23 of debit interchange (see FeeSummary)
A19: Pass-through share of total fees | B19: =B18/B13 -> 0.86008743
A20: Processor fees + service charges (markup) | B20: =-(FeeSummary!H5+FeeSummary!H7) -> 23821.24
A21: Markup share of total fees | B21: =B20/B13 -> 0.13991257
A22: Markup as % of volume excluding AMEX | B22: =B20/B15 -> 0.0032624784
A24: Effective rate by card brand
A25: Card brand | B25: Fees | C25: Net volume | D25: Effective rate | E25: Note
A26: Visa | B26: =-FeeSummary!B8 -> 86045.46 | C26: =CardType!H5 -> 4176165.4 | D26: =B26/C26 -> 0.02060394
A27: Mastercard | B27: =-FeeSummary!C8 -> 66487.73 | C27: =CardType!H4 -> 2580894 | D27: =B27/C27 -> 0.025761511
A28: Discover | B28: =-FeeSummary!E8 -> 3608.57 | C28: =CardType!H6 -> 151718.17 | D28: =B28/C28 -> 0.023784692
A29: Debit (PIN networks) | B29: =-FeeSummary!F8 -> 3898.1 | C29: =CardType!H8 -> 392800.35 | D29: =B29/C29 -> 0.009923871 | E29: Visa / Mastercard / Discover debit cards sit in their brand rows
A30: American Express | B30: =-FeeSummary!D8 -> 170 | C30: =CardType!H7 -> 1678631.3 | D30: =B30/C30 -> 0.00010127298 | E30: AMEX discount is billed by American Express, not on this statement
A31: Others (account-level, no brand) | B31: =-FeeSummary!G8 -> 10048.18 | E31: e.g. ANNUAL COMPLIANCE SVC FEE; counted in the total rate, not in any brand rate
A32: Total | B32: =SUM(B26:B31) -> 170258.04 | C32: =SUM(C26:C30) -> 8980209.2 | D32: =B32/C32 -> 0.018959251
A34: Largest individual fee lines (excluding IC/PF)
A35: Description (FeeDetail) | B35: Amount | C35: Product | D35: Type | E35: FeeDetail row
A36: =FeeDetail!D10 -> ANNUAL COMPLIANCE SVC FEE | B36: =-FeeDetail!F10 -> 6899.77 | C36: =FeeDetail!C10 -> Miscellaneous | D36: =FeeDetail!E10 -> Fees | E36: 10
A37: =FeeDetail!D195 -> VISA SALES DISCOUNT 0.0015 DISC RATE TIMES $2482035.50 | B37: =-FeeDetail!F195 -> 3723.04 | C37: =FeeDetail!C195 -> Visa | D37: =FeeDetail!E195 -> Service Charges | E37: 195
A38: =FeeDetail!D138 -> MASTERCARD SALES DISCOUNT 0.0015 DISC RATE TIMES $2051547.43 | B38: =-FeeDetail!F138 -> 3077.31 | C38: =FeeDetail!C138 -> Mastercard | D38: =FeeDetail!E138 -> Service Charges | E38: 138
A39: =FeeDetail!D190 -> VISA DEBIT SALES DISCOUNT 0.0015 DISC RATE TIMES $1826627.84 | B39: =-FeeDetail!F190 -> 2739.93 | C39: =FeeDetail!C190 -> Visa | D39: =FeeDetail!E190 -> Service Charges | E39: 190
A40: =FeeDetail!D21 -> VISA NETWORK FEE CNP 2-09 | B40: =-FeeDetail!F21 -> 1000.01 | C40: =FeeDetail!C21 -> Miscellaneous | D40: =FeeDetail!E21 -> Fees | E40: 21
A41: =FeeDetail!D146 -> MASTERCARD DEBIT SALES DISC 0.0015 DISC RATE TIMES $612749.80 | B41: =-FeeDetail!F146 -> 919.11 | C41: =FeeDetail!C146 -> Mastercard | D41: =FeeDetail!E146 -> Service Charges | E41: 146
A42: =FeeDetail!D122 -> CARDPOINTE PLATFORM FEE | B42: =-FeeDetail!F122 -> 803.85 | C42: =FeeDetail!C122 -> Miscellaneous | D42: =FeeDetail!E122 -> Service Charges | E42: 122
A43: =FeeDetail!D251 -> VISA AUTH FEE 5581 TRANSACTIONS AT 0.1 | B43: =-FeeDetail!F251 -> 558.1 | C43: =FeeDetail!C251 -> Visa | D43: =FeeDetail!E251 -> Fees | E43: 251
A44: =FeeDetail!D125 -> AVS WATS AUTHORIZATION FEE 10826 TRANSACTIONS AT 0.05 | B44: =-FeeDetail!F125 -> 541.3 | C44: =FeeDetail!C125 -> Miscellaneous | D44: =FeeDetail!E125 -> Fees | E44: 125
A45: =FeeDetail!D140 -> MASTERCARD AUTH FEE 3559 TRANSACTIONS AT 0.1 | B45: =-FeeDetail!F140 -> 355.9 | C45: =FeeDetail!C140 -> Mastercard | D45: =FeeDetail!E140 -> Fees | E45: 140

Sheet Trend
A1: 13 months sales trend (page 1 chart)
A2: Chart labels from the text layer; amounts are Amount Submitted per month.
A3: Month | B3: Amount Submitted | C3: Change vs previous month
A4: 45839 | B4: 3227208.9
A5: 45870 | B5: 3782196.9 | C5: =B5/B4-1 -> 0.17197151
A6: 45901 | B6: 4833175.6 | C6: =B6/B5-1 -> 0.2778752
A7: 45931 | B7: 6227957.9 | C7: =B7/B6-1 -> 0.28858505
A8: 45962 | B8: 5402522.7 | C8: =B8/B7-1 -> -0.13253705
A9: 45992 | B9: 5629409.6 | C9: =B9/B8-1 -> 0.041996477
A10: 46023 | B10: 4872899.1 | C10: =B10/B9-1 -> -0.13438541
A11: 46054 | B11: 4255217.5 | C11: =B11/B10-1 -> -0.12675855
A12: 46082 | B12: 4135241.7 | C12: =B12/B11-1 -> -0.02819498
A13: 46113 | B13: 5744885.9 | C13: =B13/B12-1 -> 0.38925034
A14: 46143 | B14: 7293127.3 | C14: =B14/B13-1 -> 0.26949906
A15: 46174 | B15: 8819730.6 | C15: =B15/B14-1 -> 0.20932081
A16: 46204 | B16: 8980209.2 | C16: =B16/B15-1 -> 0.018195405
A18: Jul 26 vs Jul 25 (year over year), computed | B18: =B16/B4-1 -> 1.782655
A19: Printed on page 1 | B19: =Summary!B29 -> 1.7827
A20: Jul 26 vs Jun 26 (month over month), computed | B20: =B16/B15-1 -> 0.018195405
A21: Printed on page 1 | B21: =Summary!B30 -> 0.0182

Sheet Checks
A1: Validation checks
A2: PASS = computed value equals the statement to the cent. REVIEW = differs (either a parse problem or a variance inside the source statement; see Findings).
A3: # | B3: Area | C3: Check | D3: Statement / expected | E3: Computed | F3: Difference | G3: Result
A4: 1 | B4: Summary | C4: Account summary: submitted + paid by others + disputes + adjustments + fees = amount processed | D4: =Summary!B21 -> 7130106 | E4: =Summary!B22 -> 7130106 | F4: =ROUND(E4-D4,2) -> 0 | G4: =IF(ABS(F4)<0.005,"PASS","REVIEW") -> PASS
A5: 2 | B5: Summary | C5: Average ticket = net submitted / net items | D5: =Summary!B27 -> 808.08 | E5: =Summary!B28 -> 808.08 | F5: =ROUND(E5-D5,2) -> 0 | G5: =IF(ABS(F5)<0.005,"PASS","REVIEW") -> PASS
A6: 3 | B6: Summary | C6: Locations included (page 1) = number of location rows | D6: =Summary!B9 -> 23 | E6: =COUNTA(Locations!A4:A26) -> 23 | F6: =ROUND(E6-D6,2) -> 0 | G6: =IF(ABS(F6)<0.005,"PASS","REVIEW") -> PASS
A7: 4 | B7: Trend | C7: Trend chart: Jul 26 value = Account Summary (Amount Submitted) | D7: =Summary!B16 -> 8980209.2 | E7: =Trend!B16 -> 8980209.2 | F7: =ROUND(E7-D7,2) -> 0 | G7: =IF(ABS(F7)<0.005,"PASS","REVIEW") -> PASS
A8: 5 | B8: Trend | C8: Trend chart: year over year (Jul 26 vs Jul 25), percent, printed vs recomputed | D8: =Summary!B29*100 -> 178.27 | E8: =ROUND(Trend!B18*100,2) -> 178.27 | F8: =ROUND(E8-D8,2) -> 0 | G8: =IF(ABS(F8)<0.005,"PASS","REVIEW") -> PASS
A9: 6 | B9: Trend | C9: Trend chart: month over month (Jun 26 vs Jul 26), percent, printed vs recomputed | D9: =Summary!B30*100 -> 1.82 | E9: =ROUND(Trend!B20*100,2) -> 1.82 | F9: =ROUND(E9-D9,2) -> 0 | G9: =IF(ABS(F9)<0.005,"PASS","REVIEW") -> PASS
A10: 7 | B10: Daily | C10: Summary By Day: sum of all rows incl. 06/30 and month-end = statement total (Amount Submitted) | D10: =Daily!B36 -> 8980209.2 | E10: =Daily!B37 -> 8980209.2 | F10: =ROUND(E10-D10,2) -> 0 | G10: =IF(ABS(F10)<0.005,"PASS","REVIEW") -> PASS
A11: 8 | B11: Daily | C11: Summary By Day: sum of all rows incl. 06/30 and month-end = statement total (Paid by Others) | D11: =Daily!C36 -> -1678631.3 | E11: =Daily!C37 -> -1678631.3 | F11: =ROUND(E11-D11,2) -> 0 | G11: =IF(ABS(F11)<0.005,"PASS","REVIEW") -> PASS
A12: 9 | B12: Daily | C12: Summary By Day: sum of all rows incl. 06/30 and month-end = statement total (Disputes) | D12: =Daily!D36 -> -1213.82 | E12: =Daily!D37 -> -1213.82 | F12: =ROUND(E12-D12,2) -> 0 | G12: =IF(ABS(F12)<0.005,"PASS","REVIEW") -> PASS
A13: 10 | B13: Daily | C13: Summary By Day: sum of all rows incl. 06/30 and month-end = statement total (Adjustments) | D13: =Daily!E36 -> 0 | E13: =Daily!E37 -> 0 | F13: =ROUND(E13-D13,2) -> 0 | G13: =IF(ABS(F13)<0.005,"PASS","REVIEW") -> PASS
A14: 11 | B14: Daily | C14: Summary By Day: sum of all rows incl. 06/30 and month-end = statement total (Fees) | D14: =Daily!F36 -> -170258.04 | E14: =Daily!F37 -> -170258.04 | F14: =ROUND(E14-D14,2) -> 0 | G14: =IF(ABS(F14)<0.005,"PASS","REVIEW") -> PASS
A15: 12 | B15: Daily | C15: Summary By Day: sum of all rows incl. 06/30 and month-end = statement total (Amount Processed) | D15: =Daily!G36 -> 7130106 | E15: =Daily!G37 -> 7130106 | F15: =ROUND(E15-D15,2) -> 0 | G15: =IF(ABS(F15)<0.005,"PASS","REVIEW") -> PASS
A16: 13 | B16: Daily | C16: Summary By Day total = Account Summary (Amount Submitted) | D16: =Summary!B16 -> 8980209.2 | E16: =Daily!B37 -> 8980209.2 | F16: =ROUND(E16-D16,2) -> 0 | G16: =IF(ABS(F16)<0.005,"PASS","REVIEW") -> PASS
A17: 14 | B17: Daily | C17: Summary By Day total = Account Summary (Amount Processed) | D17: =Summary!B21 -> 7130106 | E17: =Daily!G37 -> 7130106 | F17: =ROUND(E17-D17,2) -> 0 | G17: =IF(ABS(F17)<0.005,"PASS","REVIEW") -> PASS
A18: 15 | B18: Daily | C18: Each daily row: submitted + paid by others + disputes + adjustments + fees = processed (sum of absolute row errors) | D18: 0 | E18: =SUMPRODUCT(ABS(Daily!H4:H35)) -> 0 | F18: =ROUND(E18-D18,2) -> 0 | G18: =IF(ABS(F18)<0.005,"PASS","REVIEW") -> PASS
A19: 16 | B19: Daily | C19: Each date: Summary By Day amounts = sum of Amounts Funded rows for that submit date (sum of absolute differences) | D19: 0 | E19: =SUMPRODUCT(ABS(Daily!I4:I34)) -> 0 | F19: =ROUND(E19-D19,2) -> 0 | G19: =IF(ABS(F19)<0.005,"PASS","REVIEW") -> PASS
A20: 17 | B20: Daily | C20: Month End Charge = Account Summary fees | D20: =Summary!B20 -> -170258.04 | E20: =Daily!F35 -> -170258.04 | F20: =ROUND(E20-D20,2) -> 0 | G20: =IF(ABS(F20)<0.005,"PASS","REVIEW") -> PASS
A21: 18 | B21: Locations | C21: Summary By Location: sum of 23 rows = statement total (Amount Submitted) | D21: =Locations!B27 -> 8980209.2 | E21: =Locations!B28 -> 8980209.2 | F21: =ROUND(E21-D21,2) -> 0 | G21: =IF(ABS(F21)<0.005,"PASS","REVIEW") -> PASS
A22: 19 | B22: Locations | C22: Summary By Location: sum of 23 rows = statement total (Paid by Others) | D22: =Locations!C27 -> -1678631.3 | E22: =Locations!C28 -> -1678631.3 | F22: =ROUND(E22-D22,2) -> 0 | G22: =IF(ABS(F22)<0.005,"PASS","REVIEW") -> PASS
A23: 20 | B23: Locations | C23: Summary By Location: sum of 23 rows = statement total (Disputes) | D23: =Locations!D27 -> -1213.82 | E23: =Locations!D28 -> -1213.82 | F23: =ROUND(E23-D23,2) -> 0 | G23: =IF(ABS(F23)<0.005,"PASS","REVIEW") -> PASS
A24: 21 | B24: Locations | C24: Summary By Location: sum of 23 rows = statement total (Adjustments) | D24: =Locations!E27 -> 0 | E24: =Locations!E28 -> 0 | F24: =ROUND(E24-D24,2) -> 0 | G24: =IF(ABS(F24)<0.005,"PASS","REVIEW") -> PASS
A25: 22 | B25: Locations | C25: Summary By Location: sum of 23 rows = statement total (Fees) | D25: =Locations!F27 -> -170258.04 | E25: =Locations!F28 -> -170258.04 | F25: =ROUND(E25-D25,2) -> 0 | G25: =IF(ABS(F25)<0.005,"PASS","REVIEW") -> PASS
A26: 23 | B26: Locations | C26: Summary By Location: sum of 23 rows = statement total (Amount Processed) | D26: =Locations!G27 -> 7130106 | E26: =Locations!G28 -> 7130106 | F26: =ROUND(E26-D26,2) -> 0 | G26: =IF(ABS(F26)<0.005,"PASS","REVIEW") -> PASS
A27: 24 | B27: Locations | C27: Each location row: components add up to Processed Amount (sum of absolute row errors) | D27: 0 | E27: =SUMPRODUCT(ABS(Locations!H4:H26)) -> 0 | F27: =ROUND(E27-D27,2) -> 0 | G27: =IF(ABS(F27)<0.005,"PASS","REVIEW") -> PASS
A28: 25 | B28: Locations | C28: Location totals = Account Summary (Amount Processed) | D28: =Summary!B21 -> 7130106 | E28: =Locations!G28 -> 7130106 | F28: =ROUND(E28-D28,2) -> 0 | G28: =IF(ABS(F28)<0.005,"PASS","REVIEW") -> PASS
A29: 26 | B29: Paid by Others | C29: Paid by Others list: sum = statement total | D29: =PaidByOthers!C26 -> -1678631.3 | E29: =PaidByOthers!C27 -> -1678631.3 | F29: =ROUND(E29-D29,2) -> 0 | G29: =IF(ABS(F29)<0.005,"PASS","REVIEW") -> PASS
A30: 27 | B30: Paid by Others | C30: Paid by Others list per location = Summary By Location (sum of absolute differences) | D30: 0 | E30: =SUMPRODUCT(ABS(Locations!J4:J26)) -> 0 | F30: =ROUND(E30-D30,2) -> 0 | G30: =IF(ABS(F30)<0.005,"PASS","REVIEW") -> PASS
A31: 28 | B31: Paid by Others | C31: Paid by Others total = Account Summary | D31: =Summary!B17 -> -1678631.3 | E31: =PaidByOthers!C27 -> -1678631.3 | F31: =ROUND(E31-D31,2) -> 0 | G31: =IF(ABS(F31)<0.005,"PASS","REVIEW") -> PASS
A32: 29 | B32: Card type | C32: Each card row: gross + refunds = net amount (sum of absolute row errors) | D32: 0 | E32: =SUMPRODUCT(ABS(CardType!I4:I8)) -> 0 | F32: =ROUND(E32-D32,2) -> 0 | G32: =IF(ABS(F32)<0.005,"PASS","REVIEW") -> PASS
A33: 30 | B33: Card type | C33: Each card row: gross items + refund items = total items (sum of absolute row errors) | D33: 0 | E33: =SUMPRODUCT(ABS(CardType!J4:J8)) -> 0 | F33: =ROUND(E33-D33,2) -> 0 | G33: =IF(ABS(F33)<0.005,"PASS","REVIEW") -> PASS
A34: 31 | B34: Card type | C34: Card type totals: sum of rows = statement total (gross items) | D34: =CardType!C9 -> 10571 | E34: =CardType!C10 -> 10571 | F34: =ROUND(E34-D34,2) -> 0 | G34: =IF(ABS(F34)<0.005,"PASS","REVIEW") -> PASS
A35: 32 | B35: Card type | C35: Card type totals: sum of rows = statement total (gross sales) | D35: =CardType!D9 -> 9228078.2 | E35: =CardType!D10 -> 9228078.2 | F35: =ROUND(E35-D35,2) -> 0 | G35: =IF(ABS(F35)<0.005,"PASS","REVIEW") -> PASS
A36: 33 | B36: Card type | C36: Card type totals: sum of rows = statement total (refund items) | D36: =CardType!E9 -> 542 | E36: =CardType!E10 -> 542 | F36: =ROUND(E36-D36,2) -> 0 | G36: =IF(ABS(F36)<0.005,"PASS","REVIEW") -> PASS
A37: 34 | B37: Card type | C37: Card type totals: sum of rows = statement total (refunds) | D37: =CardType!F9 -> -247869 | E37: =CardType!F10 -> -247869 | F37: =ROUND(E37-D37,2) -> 0 | G37: =IF(ABS(F37)<0.005,"PASS","REVIEW") -> PASS
A38: 35 | B38: Card type | C38: Card type totals: sum of rows = statement total (total items) | D38: =CardType!G9 -> 11113 | E38: =CardType!G10 -> 11113 | F38: =ROUND(E38-D38,2) -> 0 | G38: =IF(ABS(F38)<0.005,"PASS","REVIEW") -> PASS
A39: 36 | B39: Card type | C39: Card type totals: sum of rows = statement total (net amount) | D39: =CardType!H9 -> 8980209.2 | E39: =CardType!H10 -> 8980209.2 | F39: =ROUND(E39-D39,2) -> 0 | G39: =IF(ABS(F39)<0.005,"PASS","REVIEW") -> PASS
A40: 37 | B40: Card type | C40: Card type net total = Account Summary (Amount Submitted) | D40: =Summary!B16 -> 8980209.2 | E40: =CardType!H10 -> 8980209.2 | F40: =ROUND(E40-D40,2) -> 0 | G40: =IF(ABS(F40)<0.005,"PASS","REVIEW") -> PASS
A41: 38 | B41: Card type | C41: Average ticket per card type recomputed (sum of absolute differences) | D41: 0 | E41: =SUMPRODUCT(ABS(CardType!L4:L8)) -> 0 | F41: =ROUND(E41-D41,2) -> 0 | G41: =IF(ABS(F41)<0.005,"PASS","REVIEW") -> PASS
A42: 39 | B42: Disputes | C42: Disputes detail = Account Summary disputes | D42: =Summary!B18 -> -1213.82 | E42: =Disputes!F7 -> -1213.82 | F42: =ROUND(E42-D42,2) -> 0 | G42: =IF(ABS(F42)<0.005,"PASS","REVIEW") -> PASS
A43: 40 | B43: Disputes | C43: Disputes detail = Summary By Location disputes total | D43: =Locations!D27 -> -1213.82 | E43: =Disputes!F7 -> -1213.82 | F43: =ROUND(E43-D43,2) -> 0 | G43: =IF(ABS(F43)<0.005,"PASS","REVIEW") -> PASS
A44: 41 | B44: Fees | C44: Fee Summary: fees + IC/PF + service charges = total fees | D44: =FeeSummary!B36 -> -170258.04 | E44: =SUM(FeeSummary!B33:B35) -> -170258.04 | F44: =ROUND(E44-D44,2) -> 0 | G44: =IF(ABS(F44)<0.005,"PASS","REVIEW") -> PASS
A45: 42 | B45: Fees | C45: Fee Summary total = Account Summary fees | D45: =Summary!B20 -> -170258.04 | E45: =FeeSummary!B36 -> -170258.04 | F45: =ROUND(E45-D45,2) -> 0 | G45: =IF(ABS(F45)<0.005,"PASS","REVIEW") -> PASS
A46: 43 | B46: Fees | C46: Sum of all 357 fee lines = Account Summary fees | D46: =Summary!B20 -> -170258.04 | E46: =FeeDetail!F361 -> -170258.04 | F46: =ROUND(E46-D46,2) -> 0 | G46: =IF(ABS(F46)<0.005,"PASS","REVIEW") -> PASS
A47: 44 | B47: Fees | C47: Fee lines by type = Fee Summary (Fees) | D47: =FeeSummary!B33 -> -12133.63 | E47: =FeeSummary!C33 -> -12133.63 | F47: =ROUND(E47-D47,2) -> 0 | G47: =IF(ABS(F47)<0.005,"PASS","REVIEW") -> PASS
A48: 45 | B48: Fees | C48: Fee lines by type = Fee Summary (IC/PF) | D48: =FeeSummary!B34 -> -146436.8 | E48: =FeeSummary!C34 -> -146436.8 | F48: =ROUND(E48-D48,2) -> 0 | G48: =IF(ABS(F48)<0.005,"PASS","REVIEW") -> PASS
A49: 46 | B49: Fees | C49: Fee lines by type = Fee Summary (Service Charges) | D49: =FeeSummary!B35 -> -11687.61 | E49: =FeeSummary!C35 -> -11687.61 | F49: =ROUND(E49-D49,2) -> 0 | G49: =IF(ABS(F49)<0.005,"PASS","REVIEW") -> PASS
A50: 47 | B50: Fees | C50: Fee lines by category = printed group subtotal (Account Fees) | D50: =FeeSummary!B25 -> -9375.7 | E50: =FeeSummary!C25 -> -9375.7 | F50: =ROUND(E50-D50,2) -> 0 | G50: =IF(ABS(F50)<0.005,"PASS","REVIEW") -> PASS
A51: 48 | B51: Fees | C51: Fee lines by category = printed group subtotal (Debit Fees) | D51: =FeeSummary!B26 -> -3863.23 | E51: =FeeSummary!C26 -> -3863.23 | F51: =ROUND(E51-D51,2) -> 0 | G51: =IF(ABS(F51)<0.005,"PASS","REVIEW") -> PASS
A52: 49 | B52: Fees | C52: Fee lines by category = printed group subtotal (Debit Network Fees) | D52: =FeeSummary!B27 -> -4.9 | E52: =FeeSummary!C27 -> -4.9 | F52: =ROUND(E52-D52,2) -> 0 | G52: =IF(ABS(F52)<0.005,"PASS","REVIEW") -> PASS
A53: 50 | B53: Fees | C53: Fee lines by category = printed group subtotal (Transaction Fees) | D53: =FeeSummary!B28 -> -157014.21 | E53: =FeeSummary!C28 -> -157014.21 | F53: =ROUND(E53-D53,2) -> 0 | G53: =IF(ABS(F53)<0.005,"PASS","REVIEW") -> PASS
A54: 51 | B54: Fees | C54: Fee matrix (type by brand): recomputed from FeeDetail = printed matrix (sum of absolute differences, 28 cells) | D54: 0 | E54: =SUMPRODUCT(ABS(FeeSummary!B18:H21)) -> 0 | F54: =ROUND(E54-D54,2) -> 0 | G54: =IF(ABS(F54)<0.005,"PASS","REVIEW") -> PASS
A55: 52 | B55: Fees | C55: Fee lines total = sum of Summary By Location fees | D55: =Locations!F27 -> -170258.04 | E55: =FeeDetail!F361 -> -170258.04 | F55: =ROUND(E55-D55,2) -> 0 | G55: =IF(ABS(F55)<0.005,"PASS","REVIEW") -> PASS
A56: 53 | B56: Interchange | C56: Interchange table: brand sales = printed brand totals (sum of absolute differences) | D56: 0 | E56: =SUMPRODUCT(ABS(Interchange!H147:H151)) -> 0 | F56: =ROUND(E56-D56,2) -> 0 | G56: =IF(ABS(F56)<0.005,"PASS","REVIEW") -> PASS
A57: 54 | B57: Interchange | C57: Interchange table: brand transactions = printed brand totals (sum of absolute differences) | D57: 0 | E57: =SUMPRODUCT(ABS(Interchange!I147:I151)) -> 0 | F57: =ROUND(E57-D57,2) -> 0 | G57: =IF(ABS(F57)<0.005,"PASS","REVIEW") -> PASS
A58: 55 | B58: Interchange | C58: Interchange table: brand charges = printed brand totals (sum of absolute differences) | D58: 0 | E58: =SUMPRODUCT(ABS(Interchange!J147:J151)) -> 0 | F58: =ROUND(E58-D58,2) -> 0 | G58: =IF(ABS(F58)<0.005,"PASS","REVIEW") -> PASS
A59: 56 | B59: Interchange | C59: Interchange table grand total charges = printed grand total | D59: =Interchange!D152 -> -132608.12 | E59: =Interchange!G152 -> -132608.12 | F59: =ROUND(E59-D59,2) -> 0 | G59: =IF(ABS(F59)<0.005,"PASS","REVIEW") -> PASS
A60: 57 | B60: Interchange | C60: Interchange table grand total sales = Account Summary (Amount Submitted) | D60: =Summary!B16 -> 8980209.2 | E60: =Interchange!E152 -> 8980209.2 | F60: =ROUND(E60-D60,2) -> 0 | G60: =IF(ABS(F60)<0.005,"PASS","REVIEW") -> PASS
A61: 58 | B61: Interchange | C61: IC/PF on Fee Summary = interchange table + assessments/network fees + debit interchange | D61: =FeeSummary!B43 -> -146436.8 | E61: =FeeSummary!B42 -> -146436.8 | F61: =ROUND(E61-D61,2) -> 0 | G61: =IF(ABS(F61)<0.005,"PASS","REVIEW") -> PASS
A62: 59 | B62: Interchange | C62: Mastercard: interchange table + assessments = interchange row of the fee matrix | D62: =FeeSummary!E48 -> -61395.78 | E62: =FeeSummary!D48 -> -61395.78 | F62: =ROUND(E62-D62,2) -> 0 | G62: =IF(ABS(F62)<0.005,"PASS","REVIEW") -> PASS
A63: 60 | B63: Interchange | C63: Visa: interchange table + assessments = interchange row of the fee matrix | D63: =FeeSummary!E49 -> -77822.77 | E63: =FeeSummary!D49 -> -77822.77 | F63: =ROUND(E63-D63,2) -> 0 | G63: =IF(ABS(F63)<0.005,"PASS","REVIEW") -> PASS
A64: 61 | B64: Interchange | C64: Discover: interchange table + assessments = interchange row of the fee matrix | D64: =FeeSummary!E50 -> -3351.3 | E64: =FeeSummary!D50 -> -3351.3 | F64: =ROUND(E64-D64,2) -> 0 | G64: =IF(ABS(F64)<0.005,"PASS","REVIEW") -> PASS
A65: 62 | B65: Fees | C65: Mastercard: sales-discount bases (credit + debit) = gross sales on Card Type | D65: =CardType!D4 -> 2664297.2 | E65: =SUMIFS(FeeDetail!$H$4:$H$360,FeeDetail!$C$4:$C$360,"Mastercard",FeeDetail!$D$4:$D$360,"*SALES DISC*") -> 2664297.2 | F65: =ROUND(E65-D65,2) -> 0 | G65: =IF(ABS(F65)<0.005,"PASS","REVIEW") -> PASS
A66: 63 | B66: Fees | C66: Visa: sales-discount bases (credit + debit) = gross sales on Card Type | D66: =CardType!D5 -> 4308663.3 | E66: =SUMIFS(FeeDetail!$H$4:$H$360,FeeDetail!$C$4:$C$360,"Visa",FeeDetail!$D$4:$D$360,"*SALES DISC*") -> 4308663.3 | F66: =ROUND(E66-D66,2) -> 0 | G66: =IF(ABS(F66)<0.005,"PASS","REVIEW") -> PASS
A67: 64 | B67: Fees | C67: Discover: sales-discount bases (credit + debit) = gross sales on Card Type | D67: =CardType!D6 -> 154076.77 | E67: =SUMIFS(FeeDetail!$H$4:$H$360,FeeDetail!$C$4:$C$360,"Discover",FeeDetail!$D$4:$D$360,"*SALES DISC*") -> 154076.77 | F67: =ROUND(E67-D67,2) -> 0 | G67: =IF(ABS(F67)<0.005,"PASS","REVIEW") -> PASS
A68: 65 | B68: Interchange | C68: Interchange lines where stated charge differs from rate x sales + txns x fee by more than $0.05 (count) | D68: 0 | E68: =COUNTIF(Interchange!L4:L143,"REVIEW") -> 3 | F68: =ROUND(E68-D68,2) -> 3 | G68: =IF(ABS(F68)<0.005,"PASS","REVIEW") -> REVIEW
A69: 66 | B69: Interchange | C69: Printed % of sales and % of transactions recompute on every interchange line (count of lines that do not) | D69: 0 | E69: =COUNTIF(Interchange!O4:O143,"REVIEW") -> 0 | F69: =ROUND(E69-D69,2) -> 0 | G69: =IF(ABS(F69)<0.005,"PASS","REVIEW") -> PASS
A70: 67 | B70: Card type | C70: Printed card mix (pie chart) = net amount share per card type (sum of absolute differences, percentage points) | D70: 0 | E70: =SUMPRODUCT(ABS(CardType!O4:O8))*100 -> 0 | F70: =ROUND(E70-D70,2) -> 0 | G70: =IF(ABS(F70)<0.005,"PASS","REVIEW") -> PASS
A71: 68 | B71: Fees | C71: Printed fee mix (pie chart) = fee type share of total fees (sum of absolute differences, percentage points) | D71: 0 | E71: =SUMPRODUCT(ABS(FeeSummary!D54:D56))*100 -> 0 | F71: =ROUND(E71-D71,2) -> 0 | G71: =IF(ABS(F71)<0.005,"PASS","REVIEW") -> PASS
A72: 69 | B72: Fees | C72: Fee lines where stated amount differs from basis x rate by more than $0.11 (count) | D72: 0 | E72: =COUNTIF(FeeDetail!L4:L360,"REVIEW") -> 0 | F72: =ROUND(E72-D72,2) -> 0 | G72: =IF(ABS(F72)<0.005,"PASS","REVIEW") -> PASS
A73: 70 | B73: Funded | C73: Amounts Funded: sum of rows = statement total (Amount Submitted) | D73: =Funded!B58 -> 8980209.2 | E73: =Funded!B59 -> 8980209.2 | F73: =ROUND(E73-D73,2) -> 0 | G73: =IF(ABS(F73)<0.005,"PASS","REVIEW") -> PASS
A74: 71 | B74: Funded | C74: Amounts Funded: sum of rows = statement total (Paid by Others) | D74: =Funded!C58 -> -1678631.3 | E74: =Funded!C59 -> -1678631.3 | F74: =ROUND(E74-D74,2) -> 0 | G74: =IF(ABS(F74)<0.005,"PASS","REVIEW") -> PASS
A75: 72 | B75: Funded | C75: Amounts Funded: sum of rows = statement total (Disputes) | D75: =Funded!D58 -> -1213.82 | E75: =Funded!D59 -> -1213.82 | F75: =ROUND(E75-D75,2) -> 0 | G75: =IF(ABS(F75)<0.005,"PASS","REVIEW") -> PASS
A76: 73 | B76: Funded | C76: Amounts Funded: sum of rows = statement total (Adjustments) | D76: =Funded!E58 -> 0 | E76: =Funded!E59 -> 0 | F76: =ROUND(E76-D76,2) -> 0 | G76: =IF(ABS(F76)<0.005,"PASS","REVIEW") -> PASS
A77: 74 | B77: Funded | C77: Amounts Funded: sum of rows = statement total (Fees) | D77: =Funded!F58 -> -163012.13 | E77: =Funded!F59 -> -163012.13 | F77: =ROUND(E77-D77,2) -> 0 | G77: =IF(ABS(F77)<0.005,"PASS","REVIEW") -> PASS
A78: 75 | B78: Funded | C78: Amounts Funded: sum of rows = statement total (Amount Funded) | D78: =Funded!H58 -> 7137351.9 | E78: =Funded!H59 -> 7137351.9 | F78: =ROUND(E78-D78,2) -> 0 | G78: =IF(ABS(F78)<0.005,"PASS","REVIEW") -> PASS
A79: 76 | B79: Funded | C79: Each funded row: components add up to Amount Funded (sum of absolute row errors) | D79: 0 | E79: =SUMPRODUCT(ABS(Funded!I4:I57)) -> 0 | F79: =ROUND(E79-D79,2) -> 0 | G79: =IF(ABS(F79)<0.005,"PASS","REVIEW") -> PASS
A80: 77 | B80: Funded | C80: Submitted, paid by others, disputes: Funded totals = Account Summary (sum of absolute differences) | D80: 0 | E80: =ABS(Funded!B59-Summary!B16)+ABS(Funded!C59-Summary!B17)+ABS(Funded!D59-Summary!B18) -> 0 | F80: =ROUND(E80-D80,2) -> 0 | G80: =IF(ABS(F80)<0.005,"PASS","REVIEW") -> PASS
A81: 78 | B81: Funded | C81: Amount Processed - Amount Funded = Month End Charge fees - Funded fees (fees funded belong to prior statements) | D81: =Daily!F35-Funded!F59 -> -7245.91 | E81: =Summary!B21-Funded!H59 -> -7245.91 | F81: =ROUND(E81-D81,2) -> 0 | G81: =IF(ABS(F81)<0.005,"PASS","REVIEW") -> PASS
C83: Checks passed | E83: =COUNTIF(G4:G81,"PASS") -> 77
C84: Checks needing review | E84: =COUNTIF(G4:G81,"REVIEW") -> 1

Sheet Findings
A1: Findings: parsing hazards and source-statement variances
A3: # | B3: Type | C3: Area | D3: Finding | E3: Why it matters for parsing | F3: Suggested handling
A4: 1 | B4: Parse hazard | C4: Summary By Day | D4: The July statement includes a 06/30/2026 row ($509,561.75 submitted) and its amounts are inside the statement totals. There is also an undated "Month End Charge" row and a "Total" row. | E4: A filter on the statement period drops 06/30 and the daily table then no longer sums to the printed total. | F4: Do not filter by period; treat Month End Charge and Total as separate row types.
A5: 2 | B5: Parse hazard | C5: Summary By Day | D5: No row for 07/26/2026 (Sunday): days without activity are omitted, not shown as zero. | E5: A date-indexed load will have a gap; the day is only visible in Amounts Funded (funded 07/26). | F5: Reindex to the full calendar and fill zeros if a continuous series is needed.
A6: 3 | B6: Parse hazard | C6: Fee lines | D6: Category and Product are printed only on the first row of each group and change mid-list (Miscellaneous, Mastercard, Visa, Discover, Amex, Debit); headers repeat after every page break. | E6: Rows after the first in a group have no category/product in the text. | F6: Forward-fill Category and Product; drop repeated header lines.
A7: 4 | B7: Parse hazard | C7: Fee lines / Interchange | D7: Duplicate key: "VI-US BUS TIER 5 PRD 1 CEDP" appears twice in the Visa interchange table ($22,095.20 at 2.25% and $228,931.31 at 3.00%) and twice in the fee list. | E7: Keying or joining on description alone merges two different rows. | F7: Use brand + description + rate (or row order) as the key.
A8: 5 | B8: Parse hazard | C8: Fee lines | D8: The Type column labels assessment fees (Mastercard, Visa credit/debit, Discover) and one Mastercard network settlement fee as "Interchange Charges" (total $9,965.45). | E8: Type-based totals will not match the interchange table. | F8: Keep the printed Type, add a derived class if a true interchange split is needed.
A9: 6 | B9: Parse hazard | C9: Fee Summary vs Interchange table | D9: IC/PF on the Fee Summary is $146,436.80 but the interchange table totals $132,608.12. Difference $13,828.68 = assessments/network fees $9,965.45 + debit interchange $3,863.23. | E9: The interchange table shows $0.00 for every debit network while the fee list charges $3,863.23 of debit interchange. | F9: Reconcile with the bridge on the FeeSummary sheet; the parse itself is complete.
A10: 7 | B10: Parse hazard | C10: Amounts Funded | D10: Funded fees are -$163,012.13 versus a Month End Charge of -$170,258.04; Amount Funded total $7,137,351.92 versus Amount Processed $7,130,106.01 (difference $7,245.91). | E10: Funding does not reconcile to Amount Processed by design (funded fees come from the prior statement). | F10: Reconcile with the check on the Checks sheet.
A11: 8 | B11: Parse hazard | C11: Page 1 header | D11: Page 1 visibly shows "ABC Company" and "DOWNINGTOWN PA 19335" with the corporate number cut to "4961". The text layer contains extra text behind the overlay: a different company name, a contact name and a street address (a redaction done by covering text, not removing it). The six summary amounts and the 13 monthly values also come out of label order, and each month label is split over several lines ("Jul / 25 / - / $3,227,208.93"). | E11: A text-based parser returns the hidden values, an OCR or visual parser returns the visible ones, so the same statement gives two different merchants. The sample also exposes identifying data of what looks like a real merchant. | F11: Decide which layer is authoritative; map summary amounts by the equation and by the Total rows; take the corporate number from the first Location ID in Summary By Location on page 3 (the page headers visibly show only 4961; the full number there sits in the text layer). Consider telling the sender that the PDF still carries the underlying text.
A12: 9 | B12: Parse hazard | C12: Interchange table | D12: The printed "% of Sales" uses the sum of absolute sales of the brand as denominator (refund lines count as positive), not the net Sales Total shown in the brand total. Example: VI-US REGULATED COMM (DB) prints 24% although $1,085,708.06 / $4,176,165.36 = 26%; refund lines print positive percentages. % of Transactions uses the brand transaction total. | E12: Recomputing percentages from the net brand total gives values that do not match the printed ones. | F12: Recompute with the absolute basis (columns M-O of the Interchange sheet: all 140 lines tie).
A13: 10 | B13: Parse hazard | C13: Sign and formatting | D13: Negative values are printed "-$1,234.56"; refunds, Paid by Others, disputes and fees are negative; one positive Paid by Others value (+$20.34) appears on 07/15 in Amounts Funded; percentages are rounded and the % columns are not exact. | E13: Stripping "$" and "," without handling the leading minus, or taking absolute values, changes totals. | F13: Parse sign explicitly; recompute percentages instead of storing the printed ones.
A14: 11 | B14: Parse hazard | C14: Card Type | D14: The Debit row (653 items, $392,800.35) covers PIN-debit networks only; Visa, Mastercard and Discover rows already include their own debit cards. The five rows add up to the net total, but the fee list splits debit differently (e.g. VISA DEBIT SALES DISCOUNT sits under Visa; the Debit product carries network and ILK fees). | E14: Mapping fee lines to card-type rows by the word "debit" gives wrong brand attribution. | F14: Attribute fee lines by the Product printed in the fee list, not by description keywords.
A15: 12 | B15: Source variance | C15: Interchange | D15: VI-US BUS TR4 PRD 3: printed charge -$358.79 vs $330.37 from 2.70% x $12,191.53 + 12 x $0.10 (difference $28.42). It matches the fee list, so the parse is faithful. | E15: Effective rate implied by the charge is about 2.93% versus the printed 2.70%. | F15: Ask the processor or confirm the rate table; flag rather than correct.
... A18: 15 | B18: Info | C18: Rounding | D18: 62 interchange lines differ from rate x sales + txns x fee by $0.01 to $0.04 (printed rates are rounded to 4 decimals). 26 fee lines differ from basis x rate by $0.01 to $0.10; the largest are two "VI DIGTL COM US CNP SVC FEE MN" lines (5 and 10 transactions) charged $0.05 and $0.10 more than transactions x rate. The statement does not state the reason. | E18: Do not treat differences of a few cents per line as parse errors. | F18: Tolerances used: $0.05 on the Interchange sheet and $0.11 on FeeDetail.
A19: 16 | B19: Info | C19: Not parsed | D19: The compliance notice after page 16 is boilerplate with no data. The printed YoY (178.27%) and MoM (1.82%) are rounded and are recomputed on the Trend sheet. | F19: None needed.

Sheet Daily
A1: Summary By Day
A2: Note: the table includes a 06/30/2026 row (previous month) and its amounts are inside the statement totals. No row exists for 07/26/2026.
A3: Date | B3: Amount Submitted | C3: Paid by Others | D3: Disputes | E3: Adjustments | F3: Fees | G3: Amount Processed | H3: Row check (should be 0) | I3: Funded tie-out (should be 0)
A4: 46203 | B4: 509561.75 | C4: -118230.89 | D4: 0 | E4: 0 | F4: 0 | G4: 391330.86 | H4: =ROUND(SUM(B4:F4)-G4,2) -> 0 | I4: =ROUND(ABS(SUMIFS(Funded!$B$4:$B$57,Funded!$A$4:$A$57,$A4)-B4)+ABS(SUMIFS(Funded!$C$4:$C$57,Funded!$A$4:$A$57,$A4)-C4)+ABS(SUMIFS(Funded!$D$4:$D$57,Funded!$A$4:$A$57,$A4)-D4)+ABS(SUMIFS(Funded!$E$4:$E$57,Funded!$A$4:$A$57,$A4)-E4),2) -> 0
A5: 46204 | B5: 420610.31 | C5: -55478.76 | D5: -1213.82 | E5: 0 | F5: 0 | G5: 363917.73 | H5: =ROUND(SUM(B5:F5)-G5,2) -> 0 | I5: =ROUND(ABS(SUMIFS(Funded!$B$4:$B$57,Funded!$A$4:$A$57,$A5)-B5)+ABS(SUMIFS(Funded!$C$4:$C$57,Funded!$A$4:$A$57,$A5)-C5)+ABS(SUMIFS(Funded!$D$4:$D$57,Funded!$A$4:$A$57,$A5)-D5)+ABS(SUMIFS(Funded!$E$4:$E$57,Funded!$A$4:$A$57,$A5)-E5),2) -> 0
A6: 46205 | B6: 475682.04 | C6: -97077.08 | D6: 0 | E6: 0 | F6: 0 | G6: 378604.96 | H6: =ROUND(SUM(B6:F6)-G6,2) -> 0 | I6: =ROUND(ABS(SUMIFS(Funded!$B$4:$B$57,Funded!$A$4:$A$57,$A6)-B6)+ABS(SUMIFS(Funded!$C$4:$C$57,Funded!$A$4:$A$57,$A6)-C6)+ABS(SUMIFS(Funded!$D$4:$D$57,Funded!$A$4:$A$57,$A6)-D6)+ABS(SUMIFS(Funded!$E$4:$E$57,Funded!$A$4:$A$57,$A6)-E6),2) -> 0
A7: 46206 | B7: 136800.78 | C7: -21544.12 | D7: 0 | E7: 0 | F7: 0 | G7: 115256.66 | H7: =ROUND(SUM(B7:F7)-G7,2) -> 0 | I7: =ROUND(ABS(SUMIFS(Funded!$B$4:$B$57,Funded!$A$4:$A$57,$A7)-B7)+ABS(SUMIFS(Funded!$C$4:$C$57,Funded!$A$4:$A$57,$A7)-C7)+ABS(SUMIFS(Funded!$D$4:$D$57,Funded!$A$4:$A$57,$A7)-D7)+ABS(SUMIFS(Funded!$E$4:$E$57,Funded!$A$4:$A$57,$A7)-E7),2) -> 0
A8: 46207 | B8: -395.25 | C8: -1965.52 | D8: 0 | E8: 0 | F8: 0 | G8: -2360.77 | H8: =ROUND(SUM(B8:F8)-G8,2) -> 0 | I8: =ROUND(ABS(SUMIFS(Funded!$B$4:$B$57,Funded!$A$4:$A$57,$A8)-B8)+ABS(SUMIFS(Funded!$C$4:$C$57,Funded!$A$4:$A$57,$A8)-C8)+ABS(SUMIFS(Funded!$D$4:$D$57,Funded!$A$4:$A$57,$A8)-D8)+ABS(SUMIFS(Funded!$E$4:$E$57,Funded!$A$4:$A$57,$A8)-E8),2) -> 0
A9: 46208 | B9: 1818.92 | C9: 0 | D9: 0 | E9: 0 | F9: 0 | G9: 1818.92 | H9: =ROUND(SUM(B9:F9)-G9,2) -> 0 | I9: =ROUND(ABS(SUMIFS(Funded!$B$4:$B$57,Funded!$A$4:$A$57,$A9)-B9)+ABS(SUMIFS(Funded!$C$4:$C$57,Funded!$A$4:$A$57,$A9)-C9)+ABS(SUMIFS(Funded!$D$4:$D$57,Funded!$A$4:$A$57,$A9)-D9)+ABS(SUMIFS(Funded!$E$4:$E$57,Funded!$A$4:$A$57,$A9)-E9),2) -> 0
A10: 46209 | B10: 368117.09 | C10: -63882.42 | D10: 0 | E10: 0 | F10: 0 | G10: 304234.67 | H10: =ROUND(SUM(B10:F10)-G10,2) -> 0 | I10: =ROUND(ABS(SUMIFS(Funded!$B$4:$B$57,Funded!$A$4:$A$57,$A10)-B10)+ABS(SUMIFS(Funded!$C$4:$C$57,Funded!$A$4:$A$57,$A10)-C10)+ABS(SUMIFS(Funded!$D$4:$D$57,Funded!$A$4:$A$57,$A10)-D10)+ABS(SUMIFS(Funded!$E$4:$E$57,Funded!$A$4:$A$57,$A10)-E10),2) -> 0
A11: 46210 | B11: 428727.25 | C11: -89809.19 | D11: 0 | E11: 0 | F11: 0 | G11: 338918.06 | H11: =ROUND(SUM(B11:F11)-G11,2) -> 0 | I11: =ROUND(ABS(SUMIFS(Funded!$B$4:$B$57,Funded!$A$4:$A$57,$A11)-B11)+ABS(SUMIFS(Funded!$C$4:$C$57,Funded!$A$4:$A$57,$A11)-C11)+ABS(SUMIFS(Funded!$D$4:$D$57,Funded!$A$4:$A$57,$A11)-D11)+ABS(SUMIFS(Funded!$E$4:$E$57,Funded!$A$4:$A$57,$A11)-E11),2) -> 0
A12: 46211 | B12: 452197.88 | C12: -76864.6 | D12: 0 | E12: 0 | F12: 0 | G12: 375333.28 | H12: =ROUND(SUM(B12:F12)-G12,2) -> 0 | I12: =ROUND(ABS(SUMIFS(Funded!$B$4:$B$57,Funded!$A$4:$A$57,$A12)-B12)+ABS(SUMIFS(Funded!$C$4:$C$57,Funded!$A$4:$A$57,$A12)-C12)+ABS(SUMIFS(Funded!$D$4:$D$57,Funded!$A$4:$A$57,$A12)-D12)+ABS(SUMIFS(Funded!$E$4:$E$57,Funded!$A$4:$A$57,$A12)-E12),2) -> 0
A13: 46212 | B13: 481718.91 | C13: -61209.25 | D13: 0 | E13: 0 | F13: 0 | G13: 420509.66 | H13: =ROUND(SUM(B13:F13)-G13,2) -> 0 | I13: =ROUND(ABS(SUMIFS(Funded!$B$4:$B$57,Funded!$A$4:$A$57,$A13)-B13)+ABS(SUMIFS(Funded!$C$4:$C$57,Funded!$A$4:$A$57,$A13)-C13)+ABS(SUMIFS(Funded!$D$4:$D$57,Funded!$A$4:$A$57,$A13)-D13)+ABS(SUMIFS(Funded!$E$4:$E$57,Funded!$A$4:$A$57,$A13)-E13),2) -> 0
A14: 46213 | B14: 465171.68 | C14: -71684.68 | D14: 0 | E14: 0 | F14: 0 | G14: 393487 | H14: =ROUND(SUM(B14:F14)-G14,2) -> 0 | I14: =ROUND(ABS(SUMIFS(Funded!$B$4:$B$57,Funded!$A$4:$A$57,$A14)-B14)+ABS(SUMIFS(Funded!$C$4:$C$57,Funded!$A$4:$A$57,$A14)-C14)+ABS(SUMIFS(Funded!$D$4:$D$57,Funded!$A$4:$A$57,$A14)-D14)+ABS(SUMIFS(Funded!$E$4:$E$57,Funded!$A$4:$A$57,$A14)-E14),2) -> 0
A15: 46214 | B15: 17460.37 | C15: -1472.36 | D15: 0 | E15: 0 | F15: 0 | G15: 15988.01 | H15: =ROUND(SUM(B15:F15)-G15,2) -> 0 | I15: =ROUND(ABS(SUMIFS(Funded!$B$4:$B$57,Funded!$A$4:$A$57,$A15)-B15)+ABS(SUMIFS(Funded!$C$4:$C$57,Funded!$A$4:$A$57,$A15)-C15)+ABS(SUMIFS(Funded!$D$4:$D$57,Funded!$A$4:$A$57,$A15)-D15)+ABS(SUMIFS(Funded!$E$4:$E$57,Funded!$A$4:$A$57,$A15)-E15),2) -> 0
... A34: 46234 | B34: 6679.24 | C34: -2466.5 | D34: 0 | E34: 0 | F34: 0 | G34: 4212.74 | H34: =ROUND(SUM(B34:F34)-G34,2) -> 0 | I34: =ROUND(ABS(SUMIFS(Funded!$B$4:$B$57,Funded!$A$4:$A$57,$A34)-B34)+ABS(SUMIFS(Funded!$C$4:$C$57,Funded!$A$4:$A$57,$A34)-C34)+ABS(SUMIFS(Funded!$D$4:$D$57,Funded!$A$4:$A$57,$A34)-D34)+ABS(SUMIFS(Funded!$E$4:$E$57,Funded!$A$4:$A$57,$A34)-E34),2) -> 0
A35: Month End Charge | B35: 0 | C35: 0 | D35: 0 | E35: 0 | F35: -170258.04 | G35: -170258.04 | H35: =ROUND(SUM(B35:F35)-G35,2) -> 0
A36: Total (statement) | B36: 8980209.2 | C36: -1678631.3 | D36: -1213.82 | E36: 0 | F36: -170258.04 | G36: 7130106
A37: Total (computed) | B37: =SUM(B4:B35) -> 8980209.2 | C37: =SUM(C4:C35) -> -1678631.3 | D37: =SUM(D4:D35) -> -1213.82 | E37: =SUM(E4:E35) -> 0 | F37: =SUM(F4:F35) -> -170258.04 | G37: =SUM(G4:G35) -> 7130106
A38: Difference | B38: =ROUND(B37-B36,2) -> 0 | C38: =ROUND(C37-C36,2) -> 0 | D38: =ROUND(D37-D36,2) -> 0 | E38: =ROUND(E37-E36,2) -> 0 | F38: =ROUND(F37-F36,2) -> 0 | G38: =ROUND(G37-G36,2) -> 0

Sheet CardType
A1: Summary by Card Type
A2: Average ticket on the statement is net amount / net items (refund items count as items).
A3: Card Type | B3: Average Ticket (statement) | C3: Gross Items | D3: Gross Sales Amount | E3: Refund Items | F3: Refund Amount | G3: Total Items | H3: Total Amount Submitted | I3: Check: gross + refunds - net | J3: Check: items | K3: Avg ticket (computed) | L3: Avg ticket diff | M3: Share of net | N3: Share printed (pie chart, page 3) | O3: Printed vs recomputed (4 dp)
A4: MASTERCARD | B4: 786.14 | C4: 3093 | D4: 2664297.2 | E4: 190 | F4: -83403.24 | G4: 3283 | H4: 2580894 | I4: =ROUND(D4+F4-H4,2) -> 0 | J4: =C4+E4-G4 -> 0 | K4: =ROUND(H4/G4,2) -> 786.14 | L4: =ROUND(K4-B4,2) -> 0 | M4: =H4/$H$9 -> 0.28739798 | N4: 0.2874 | O4: =ROUND(M4,4)-N4 -> 0
A5: VISA | B5: 782.05 | C5: 5065 | D5: 4308663.3 | E5: 275 | F5: -132497.98 | G5: 5340 | H5: 4176165.4 | I5: =ROUND(D5+F5-H5,2) -> 0 | J5: =C5+E5-G5 -> 0 | K5: =ROUND(H5/G5,2) -> 782.05 | L5: =ROUND(K5-B5,2) -> 0 | M5: =H5/$H$9 -> 0.46504099 | N5: 0.465 | O5: =ROUND(M5,4)-N5 -> 0
A6: DISCOVER | B6: 751.08 | C6: 192 | D6: 154076.77 | E6: 10 | F6: -2358.6 | G6: 202 | H6: 151718.17 | I6: =ROUND(D6+F6-H6,2) -> 0 | J6: =C6+E6-G6 -> 0 | K6: =ROUND(H6/G6,2) -> 751.08 | L6: =ROUND(K6-B6,2) -> 0 | M6: =H6/$H$9 -> 0.016894726 | N6: 0.0169 | O6: =ROUND(M6,4)-N6 -> 0
A7: AMERICAN EXPRESS | B7: 1026.69 | C7: 1568 | D7: 1708240.5 | E7: 67 | F7: -29609.18 | G7: 1635 | H7: 1678631.3 | I7: =ROUND(D7+F7-H7,2) -> 0 | J7: =C7+E7-G7 -> 0 | K7: =ROUND(H7/G7,2) -> 1026.69 | L7: =ROUND(K7-B7,2) -> 0 | M7: =H7/$H$9 -> 0.18692564 | N7: 0.1869 | O7: =ROUND(M7,4)-N7 -> 0
A8: DEBIT CARD | B8: 601.53 | C8: 653 | D8: 392800.35 | E8: 0 | F8: 0 | G8: 653 | H8: 392800.35 | I8: =ROUND(D8+F8-H8,2) -> 0 | J8: =C8+E8-G8 -> 0 | K8: =ROUND(H8/G8,2) -> 601.53 | L8: =ROUND(K8-B8,2) -> 0 | M8: =H8/$H$9 -> 0.043740668 | N8: 0.0437 | O8: =ROUND(M8,4)-N8 -> 0
A9: Total (statement) | C9: 10571 | D9: 9228078.2 | E9: 542 | F9: -247869 | G9: 11113 | H9: 8980209.2
A10: Total (computed) | C10: =SUM(C4:C8) -> 10571 | D10: =SUM(D4:D8) -> 9228078.2 | E10: =SUM(E4:E8) -> 542 | F10: =SUM(F4:F8) -> -247869 | G10: =SUM(G4:G8) -> 11113 | H10: =SUM(H4:H8) -> 8980209.2 | K10: =ROUND(H10/G10,2) -> 808.08
A11: Difference | C11: =ROUND(C10-C9,2) -> 0 | D11: =ROUND(D10-D9,2) -> 0 | E11: =ROUND(E10-E9,2) -> 0 | F11: =ROUND(F10-F9,2) -> 0 | G11: =ROUND(G10-G9,2) -> 0 | H11: =ROUND(H10-H9,2) -> 0

Sheet Locations
A1: Summary By Location (23 locations)
A3: Location ID | B3: Amount Submitted | C3: Paid by Others | D3: Disputes | E3: Adjustments | F3: Fees | G3: Processed Amount | H3: Row check | I3: Paid by Others per list | J3: PBO diff
A4: 496115385882 | B4: 663551.51 | C4: -112170.62 | D4: 0 | E4: 0 | F4: -16503.2 | G4: 534877.69 | H4: =ROUND(SUM(B4:F4)-G4,2) -> 0 | I4: =SUMPRODUCT((PaidByOthers!$A$4:$A$25=A4)*PaidByOthers!$C$4:$C$25) -> -112170.62 | J4: =ROUND(I4-C4,2) -> 0
A5: 496116308883 | B5: 450527.16 | C5: -72683.76 | D5: 0 | E5: 0 | F5: -8658.04 | G5: 369185.36 | H5: =ROUND(SUM(B5:F5)-G5,2) -> 0 | I5: =SUMPRODUCT((PaidByOthers!$A$4:$A$25=A5)*PaidByOthers!$C$4:$C$25) -> -72683.76 | J5: =ROUND(I5-C5,2) -> 0
A6: 496116313883 | B6: 278189.09 | C6: -21775.01 | D6: 0 | E6: 0 | F6: -6788.13 | G6: 249625.95 | H6: =ROUND(SUM(B6:F6)-G6,2) -> 0 | I6: =SUMPRODUCT((PaidByOthers!$A$4:$A$25=A6)*PaidByOthers!$C$4:$C$25) -> -21775.01 | J6: =ROUND(I6-C6,2) -> 0
A7: 496116314881 | B7: 278226.06 | C7: -40102.29 | D7: 0 | E7: 0 | F7: -6054.24 | G7: 232069.53 | H7: =ROUND(SUM(B7:F7)-G7,2) -> 0 | I7: =SUMPRODUCT((PaidByOthers!$A$4:$A$25=A7)*PaidByOthers!$C$4:$C$25) -> -40102.29 | J7: =ROUND(I7-C7,2) -> 0
A8: 496116316886 | B8: 1251729.6 | C8: -305584.22 | D8: 0 | E8: 0 | F8: -20760.07 | G8: 925385.29 | H8: =ROUND(SUM(B8:F8)-G8,2) -> 0 | I8: =SUMPRODUCT((PaidByOthers!$A$4:$A$25=A8)*PaidByOthers!$C$4:$C$25) -> -305584.22 | J8: =ROUND(I8-C8,2) -> 0
A9: 496116317884 | B9: 421779.8 | C9: -43230.27 | D9: 0 | E9: 0 | F9: -7325.32 | G9: 371224.21 | H9: =ROUND(SUM(B9:F9)-G9,2) -> 0 | I9: =SUMPRODUCT((PaidByOthers!$A$4:$A$25=A9)*PaidByOthers!$C$4:$C$25) -> -43230.27 | J9: =ROUND(I9-C9,2) -> 0
A10: 496116318882 | B10: 423642.31 | C10: -36882.61 | D10: 0 | E10: 0 | F10: -12149.34 | G10: 374610.36 | H10: =ROUND(SUM(B10:F10)-G10,2) -> 0 | I10: =SUMPRODUCT((PaidByOthers!$A$4:$A$25=A10)*PaidByOthers!$C$4:$C$25) -> -36882.61 | J10: =ROUND(I10-C10,2) -> 0
A11: 496116319880 | B11: 449308.19 | C11: -60986.13 | D11: 0 | E11: 0 | F11: -7364.64 | G11: 380957.42 | H11: =ROUND(SUM(B11:F11)-G11,2) -> 0 | I11: =SUMPRODUCT((PaidByOthers!$A$4:$A$25=A11)*PaidByOthers!$C$4:$C$25) -> -60986.13 | J11: =ROUND(I11-C11,2) -> 0
A12: 496116321886 | B12: 131235.71 | C12: -18657.54 | D12: 0 | E12: 0 | F12: -2954.97 | G12: 109623.2 | H12: =ROUND(SUM(B12:F12)-G12,2) -> 0 | I12: =SUMPRODUCT((PaidByOthers!$A$4:$A$25=A12)*PaidByOthers!$C$4:$C$25) -> -18657.54 | J12: =ROUND(I12-C12,2) -> 0
A13: 496116322884 | B13: 649816.1 | C13: -330284.41 | D13: 0 | E13: 0 | F13: -6627.81 | G13: 312903.88 | H13: =ROUND(SUM(B13:F13)-G13,2) -> 0 | I13: =SUMPRODUCT((PaidByOthers!$A$4:$A$25=A13)*PaidByOthers!$C$4:$C$25) -> -330284.41 | J13: =ROUND(I13-C13,2) -> 0
A14: 496116323882 | B14: 335103.31 | C14: -20629.27 | D14: 0 | E14: 0 | F14: -7790.56 | G14: 306683.48 | H14: =ROUND(SUM(B14:F14)-G14,2) -> 0 | I14: =SUMPRODUCT((PaidByOthers!$A$4:$A$25=A14)*PaidByOthers!$C$4:$C$25) -> -20629.27 | J14: =ROUND(I14-C14,2) -> 0
A15: 496116325887 | B15: 159370.32 | C15: -11748.84 | D15: 0 | E15: 0 | F15: -2644.64 | G15: 144976.84 | H15: =ROUND(SUM(B15:F15)-G15,2) -> 0 | I15: =SUMPRODUCT((PaidByOthers!$A$4:$A$25=A15)*PaidByOthers!$C$4:$C$25) -> -11748.84 | J15: =ROUND(I15-C15,2) -> 0
... A26: 496613745884 | B26: 9086.15 | C26: -1559.3 | D26: 0 | E26: 0 | F26: -509.25 | G26: 7017.6 | H26: =ROUND(SUM(B26:F26)-G26,2) -> 0 | I26: =SUMPRODUCT((PaidByOthers!$A$4:$A$25=A26)*PaidByOthers!$C$4:$C$25) -> -1559.3 | J26: =ROUND(I26-C26,2) -> 0
A27: Total (statement) | B27: 8980209.2 | C27: -1678631.3 | D27: -1213.82 | E27: 0 | F27: -170258.04 | G27: 7130106
A28: Total (computed) | B28: =SUM(B4:B26) -> 8980209.2 | C28: =SUM(C4:C26) -> -1678631.3 | D28: =SUM(D4:D26) -> -1213.82 | E28: =SUM(E4:E26) -> 0 | F28: =SUM(F4:F26) -> -170258.04 | G28: =SUM(G4:G26) -> 7130106
A29: Difference | B29: =ROUND(B28-B27,2) -> 0 | C29: =ROUND(C28-C27,2) -> 0 | D29: =ROUND(D28-D27,2) -> 0 | E29: =ROUND(E28-E27,2) -> 0 | F29: =ROUND(F28-F27,2) -> 0 | G29: =ROUND(G28-G27,2) -> 0

Sheet PaidByOthers
A1: Paid by Others
A2: Transactions passed directly to the card association for processing and funding (American Express).
A3: Location ID | B3: Description | C3: Amount
A4: 496115385882 | B4: Transactions submitted to American Express | C4: -112170.62
A5: 496116308883 | B5: Transactions submitted to American Express | C5: -72683.76
A6: 496116313883 | B6: Transactions submitted to American Express | C6: -21775.01
A7: 496116314881 | B7: Transactions submitted to American Express | C7: -40102.29
A8: 496116316886 | B8: Transactions submitted to American Express | C8: -305584.22
A9: 496116317884 | B9: Transactions submitted to American Express | C9: -43230.27
A10: 496116318882 | B10: Transactions submitted to American Express | C10: -36882.61
A11: 496116319880 | B11: Transactions submitted to American Express | C11: -60986.13
A12: 496116321886 | B12: Transactions submitted to American Express | C12: -18657.54
A13: 496116322884 | B13: Transactions submitted to American Express | C13: -330284.41
A14: 496116323882 | B14: Transactions submitted to American Express | C14: -20629.27
A15: 496116325887 | B15: Transactions submitted to American Express | C15: -11748.84
... A25: 496613745884 | B25: Transactions submitted to American Express | C25: -1559.3
A26: Total (statement) | C26: -1678631.3
A27: Total (computed) | C27: =SUM(C4:C25) -> -1678631.3

Sheet Disputes
A1: Disputes
A3: Location ID | B3: Date | C3: Reference No. | D3: Description | E3: Card number (last 4) | F3: Amount
A4: 496116335886 | B4: 46204 | C4: 861813362701 | D4: Cardholder disputing service/merchandise | E4: 9127 | F4: -1213.82
A5: Total Credits | F5: 0
A6: Total Debits | F6: =SUM(F4:F4) -> -1213.82
A7: Net disputes | F7: =F5+F6 -> -1213.82

Sheet FeeSummary
A1: Fee summary and reconciliations
A3: Fee matrix as printed (page 4)
B4: Visa | C4: Mastercard | D4: Amex | E4: Discover | F4: Debit | G4: Others | H4: Total
A5: Fees | B5: -1759.72 | C5: -966.12 | D5: -170 | E5: -25.61 | F5: -2.74 | G5: -9209.44 | H5: -12133.63
A6: Interchange Charges | B6: -77822.77 | C6: -61395.78 | D6: 0 | E6: -3351.3 | F6: -3863.23 | G6: -3.72 | H6: -146436.8
A7: Service Charges | B7: -6462.97 | C7: -4125.83 | D7: 0 | E7: -231.66 | F7: -32.13 | G7: -835.02 | H7: -11687.61
A8: Total | B8: -86045.46 | C8: -66487.73 | D8: -170 | E8: -3608.57 | F8: -3898.1 | G8: -10048.18 | H8: -170258.04
A10: Recomputed from FeeDetail (Others = Miscellaneous)
A11: Type / Product | B11: Visa | C11: Mastercard | D11: Amex | E11: Discover | F11: Debit | G11: Miscellaneous | H11: Total
A12: Fees | B12: =SUMIFS(FeeDetail!$F$4:$F$360,FeeDetail!$E$4:$E$360,$A12,FeeDetail!$C$4:$C$360,B$11) -> -1759.72 | C12: =SUMIFS(FeeDetail!$F$4:$F$360,FeeDetail!$E$4:$E$360,$A12,FeeDetail!$C$4:$C$360,C$11) -> -966.12 | D12: =SUMIFS(FeeDetail!$F$4:$F$360,FeeDetail!$E$4:$E$360,$A12,FeeDetail!$C$4:$C$360,D$11) -> -170 | E12: =SUMIFS(FeeDetail!$F$4:$F$360,FeeDetail!$E$4:$E$360,$A12,FeeDetail!$C$4:$C$360,E$11) -> -25.61 | F12: =SUMIFS(FeeDetail!$F$4:$F$360,FeeDetail!$E$4:$E$360,$A12,FeeDetail!$C$4:$C$360,F$11) -> -2.74 | G12: =SUMIFS(FeeDetail!$F$4:$F$360,FeeDetail!$E$4:$E$360,$A12,FeeDetail!$C$4:$C$360,G$11) -> -9209.44 | H12: =SUM(B12:G12) -> -12133.63
A13: Interchange Charges | B13: =SUMIFS(FeeDetail!$F$4:$F$360,FeeDetail!$E$4:$E$360,$A13,FeeDetail!$C$4:$C$360,B$11) -> -77822.77 | C13: =SUMIFS(FeeDetail!$F$4:$F$360,FeeDetail!$E$4:$E$360,$A13,FeeDetail!$C$4:$C$360,C$11) -> -61395.78 | D13: =SUMIFS(FeeDetail!$F$4:$F$360,FeeDetail!$E$4:$E$360,$A13,FeeDetail!$C$4:$C$360,D$11) -> 0 | E13: =SUMIFS(FeeDetail!$F$4:$F$360,FeeDetail!$E$4:$E$360,$A13,FeeDetail!$C$4:$C$360,E$11) -> -3351.3 | F13: =SUMIFS(FeeDetail!$F$4:$F$360,FeeDetail!$E$4:$E$360,$A13,FeeDetail!$C$4:$C$360,F$11) -> -3863.23 | G13: =SUMIFS(FeeDetail!$F$4:$F$360,FeeDetail!$E$4:$E$360,$A13,FeeDetail!$C$4:$C$360,G$11) -> -3.72 | H13: =SUM(B13:G13) -> -146436.8
A14: Service Charges | B14: =SUMIFS(FeeDetail!$F$4:$F$360,FeeDetail!$E$4:$E$360,$A14,FeeDetail!$C$4:$C$360,B$11) -> -6462.97 | C14: =SUMIFS(FeeDetail!$F$4:$F$360,FeeDetail!$E$4:$E$360,$A14,FeeDetail!$C$4:$C$360,C$11) -> -4125.83 | D14: =SUMIFS(FeeDetail!$F$4:$F$360,FeeDetail!$E$4:$E$360,$A14,FeeDetail!$C$4:$C$360,D$11) -> 0 | E14: =SUMIFS(FeeDetail!$F$4:$F$360,FeeDetail!$E$4:$E$360,$A14,FeeDetail!$C$4:$C$360,E$11) -> -231.66 | F14: =SUMIFS(FeeDetail!$F$4:$F$360,FeeDetail!$E$4:$E$360,$A14,FeeDetail!$C$4:$C$360,F$11) -> -32.13 | G14: =SUMIFS(FeeDetail!$F$4:$F$360,FeeDetail!$E$4:$E$360,$A14,FeeDetail!$C$4:$C$360,G$11) -> -835.02 | H14: =SUM(B14:G14) -> -11687.61
A15: Total | B15: =SUM(B12:B14) -> -86045.46 | C15: =SUM(C12:C14) -> -66487.73 | D15: =SUM(D12:D14) -> -170 | E15: =SUM(E12:E14) -> -3608.57 | F15: =SUM(F12:F14) -> -3898.1 | G15: =SUM(G12:G14) -> -10048.18 | H15: =SUM(H12:H14) -> -170258.04
A17: Difference (computed - printed)
A18: Fees | B18: =ROUND(B12-B5,2) -> 0 | C18: =ROUND(C12-C5,2) -> 0 | D18: =ROUND(D12-D5,2) -> 0 | E18: =ROUND(E12-E5,2) -> 0 | F18: =ROUND(F12-F5,2) -> 0 | G18: =ROUND(G12-G5,2) -> 0 | H18: =ROUND(H12-H5,2) -> 0
A19: Interchange Charges | B19: =ROUND(B13-B6,2) -> 0 | C19: =ROUND(C13-C6,2) -> 0 | D19: =ROUND(D13-D6,2) -> 0 | E19: =ROUND(E13-E6,2) -> 0 | F19: =ROUND(F13-F6,2) -> 0 | G19: =ROUND(G13-G6,2) -> 0 | H19: =ROUND(H13-H6,2) -> 0
A20: Service Charges | B20: =ROUND(B14-B7,2) -> 0 | C20: =ROUND(C14-C7,2) -> 0 | D20: =ROUND(D14-D7,2) -> 0 | E20: =ROUND(E14-E7,2) -> 0 | F20: =ROUND(F14-F7,2) -> 0 | G20: =ROUND(G14-G7,2) -> 0 | H20: =ROUND(H14-H7,2) -> 0
A21: Total | B21: =ROUND(B15-B8,2) -> 0 | C21: =ROUND(C15-C8,2) -> 0 | D21: =ROUND(D15-D8,2) -> 0 | E21: =ROUND(E15-E8,2) -> 0 | F21: =ROUND(F15-F8,2) -> 0 | G21: =ROUND(G15-G8,2) -> 0 | H21: =ROUND(H15-H8,2) -> 0
A23: Category subtotals
A24: Category | B24: Statement subtotal | C24: Computed | D24: Difference
A25: Account Fees | B25: -9375.7 | C25: =SUMIFS(FeeDetail!$F$4:$F$360,FeeDetail!$B$4:$B$360,A25) -> -9375.7 | D25: =ROUND(C25-B25,2) -> 0
A26: Debit Fees | B26: -3863.23 | C26: =SUMIFS(FeeDetail!$F$4:$F$360,FeeDetail!$B$4:$B$360,A26) -> -3863.23 | D26: =ROUND(C26-B26,2) -> 0
A27: Debit Network Fees | B27: -4.9 | C27: =SUMIFS(FeeDetail!$F$4:$F$360,FeeDetail!$B$4:$B$360,A27) -> -4.9 | D27: =ROUND(C27-B27,2) -> 0
A28: Transaction Fees | B28: -157014.21 | C28: =SUMIFS(FeeDetail!$F$4:$F$360,FeeDetail!$B$4:$B$360,A28) -> -157014.21 | D28: =ROUND(C28-B28,2) -> 0
A29: Total | B29: =SUM(B25:B28) -> -170258.04 | C29: =SUM(C25:C28) -> -170258.04 | D29: =ROUND(C29-B29,2) -> 0
A31: Fee Summary (page 4)
A32: Component | B32: Statement | C32: Computed from FeeDetail | D32: Difference
A33: Fees | B33: -12133.63 | C33: =SUMIFS(FeeDetail!$F$4:$F$360,FeeDetail!$E$4:$E$360,"Fees") -> -12133.63 | D33: =ROUND(C33-B33,2) -> 0
A34: IC/PF (interchange / program fees) | B34: -146436.8 | C34: =SUMIFS(FeeDetail!$F$4:$F$360,FeeDetail!$E$4:$E$360,"Interchange Charges") -> -146436.8 | D34: =ROUND(C34-B34,2) -> 0
A35: Service Charges | B35: -11687.61 | C35: =SUMIFS(FeeDetail!$F$4:$F$360,FeeDetail!$E$4:$E$360,"Service Charges") -> -11687.61 | D35: =ROUND(C35-B35,2) -> 0
A36: Total fees | B36: -170258.04 | C36: =SUM(C33:C35) -> -170258.04 | D36: =ROUND(C36-B36,2) -> 0
A38: Why IC/PF (page 4) differs from the interchange table total
A39: Interchange table grand total (Interchange sheet) | B39: =Interchange!D152 -> -132608.12
A40: + Assessments and network fees typed "Interchange Charges" | B40: =SUMIFS(FeeDetail!$F$4:$F$360,FeeDetail!$M$4:$M$360,"Y") -> -9965.45
A41: + Debit interchange (fee list only; the interchange table shows $0.00 for all debit networks) | B41: =SUMIFS(FeeDetail!$F$4:$F$360,FeeDetail!$B$4:$B$360,"Debit Fees") -> -3863.23
A42: Reconstructed IC/PF (sum of the three lines) | B42: =SUM(B39:B41) -> -146436.8
A43: IC/PF printed on the Fee Summary | B43: =B34 -> -146436.8
A44: Difference | B44: =ROUND(B42-B43,2) -> 0
A46: Per brand: interchange table + assessments = fee matrix Interchange row
A47: Brand | B47: Interchange table | C47: Assessments in fee list | D47: Reconstructed | E47: Fee matrix (printed) | F47: Difference
A48: Mastercard | B48: =Interchange!D147 -> -57499.26 | C48: =SUMIFS(FeeDetail!$F$4:$F$360,FeeDetail!$M$4:$M$360,"Y",FeeDetail!$C$4:$C$360,A48) -> -3896.52 | D48: =B48+C48 -> -61395.78 | E48: =C6 -> -61395.78 | F48: =ROUND(D48-E48,2) -> 0
A49: Visa | B49: =Interchange!D148 -> -71973.26 | C49: =SUMIFS(FeeDetail!$F$4:$F$360,FeeDetail!$M$4:$M$360,"Y",FeeDetail!$C$4:$C$360,A49) -> -5849.51 | D49: =B49+C49 -> -77822.77 | E49: =B6 -> -77822.77 | F49: =ROUND(D49-E49,2) -> 0
A50: Discover | B50: =Interchange!D149 -> -3135.6 | C50: =SUMIFS(FeeDetail!$F$4:$F$360,FeeDetail!$M$4:$M$360,"Y",FeeDetail!$C$4:$C$360,A50) -> -215.7 | D50: =B50+C50 -> -3351.3 | E50: =E6 -> -3351.3 | F50: =ROUND(D50-E50,2) -> 0
A52: Fee mix printed (pie chart, page 4) vs recomputed
A53: Component | B53: Printed | C53: Recomputed | D53: Printed - recomputed (4 dp)
A54: Fees | B54: 0.0713 | C54: =B33/$B$36 -> 0.071266121 | D54: =ROUND(ROUND(C54,4)-B54,4) -> 0
A55: Interchange Charges (IC/PF) | B55: 0.8601 | C55: =B34/$B$36 -> 0.86008743 | D55: =ROUND(ROUND(C55,4)-B55,4) -> 0
A56: Service Charges | B56: 0.0686 | C56: =B35/$B$36 -> 0.06864645 | D56: =ROUND(ROUND(C56,4)-B56,4) -> 0

Sheet FeeDetail
A1: Fee detail (all 357 lines)
A2: Category and Product are printed only on the first row of each group; they are forward-filled here. Recomputed = -(basis x rate) where the description states both.
A3: # | B3: Category | C3: Product | D3: Description | E3: Type | F3: Amount | G3: Basis type | H3: Basis value | I3: Rate | J3: Recomputed | K3: Variance | L3: Note | M3: Typed as Interchange but is an assessment / network fee
A4: 1 | B4: Account Fees | C4: Miscellaneous | D4: MC MONTHLY LOCATION FEE | E4: Fees | F4: -27.5
A5: 2 | B5: Account Fees | C5: Miscellaneous | D5: VISA INTL SERVICE FEE - BASE 0 TRANS TOTALING $7.15 | E5: Fees | F5: -0.07
A6: 3 | B6: Account Fees | C6: Miscellaneous | D6: ILK-COMMERCIAL SOLUTIONS FEE $411.57 AT .000100 | E6: Fees | F6: -0.04 | G6: Sales base | H6: 411.57 | I6: 0.0001 | J6: =-ROUND(H6*I6,2) -> -0.04 | K6: =ROUND(J6-F6,2) -> 0 | L6: =IF(ABS(K6)<0.005,"OK",IF(ABS(K6)<=0.11,"Rounding / minimum fee","REVIEW")) -> OK
A7: 4 | B7: Account Fees | C7: Miscellaneous | D7: ILK-COMMERCIAL SOLUTIONS FEE $410.67 AT .000100 | E7: Fees | F7: -0.04 | G7: Sales base | H7: 410.67 | I7: 0.0001 | J7: =-ROUND(H7*I7,2) -> -0.04 | K7: =ROUND(J7-F7,2) -> 0 | L7: =IF(ABS(K7)<0.005,"OK",IF(ABS(K7)<=0.11,"Rounding / minimum fee","REVIEW")) -> OK
A8: 5 | B8: Account Fees | C8: Miscellaneous | D8: REGULATORY PRODUCT FEE | E8: Fees | F8: -343.85
A9: 6 | B9: Account Fees | C9: Miscellaneous | D9: ILK-COMMERCIAL SOLUTIONS FEE $1,240.97 AT .000100 | E9: Fees | F9: -0.12 | G9: Sales base | H9: 1240.97 | I9: 0.0001 | J9: =-ROUND(H9*I9,2) -> -0.12 | K9: =ROUND(J9-F9,2) -> 0 | L9: =IF(ABS(K9)<0.005,"OK",IF(ABS(K9)<=0.11,"Rounding / minimum fee","REVIEW")) -> OK
A10: 7 | B10: Account Fees | C10: Miscellaneous | D10: ANNUAL COMPLIANCE SVC FEE | E10: Fees | F10: -6899.77
A11: 8 | B11: Account Fees | C11: Miscellaneous | D11: VS INTL ACQUIRER FEE 0 TRANS TOTALING $7.15 | E11: Fees | F11: -0.03
A12: 9 | B12: Account Fees | C12: Miscellaneous | D12: MC GLOBAL ACQUIRER FEE 0 TRANS TOTALING $985.40 | E12: Fees | F12: -8.38
A13: 10 | B13: Account Fees | C13: Miscellaneous | D13: INCOMING CHARGEBACKS ALL 1 TRANSACTIONS AT 35 | E13: Fees | F13: -35 | G13: Transactions | H13: 1 | I13: 35 | J13: =-ROUND(H13*I13,2) -> -35 | K13: =ROUND(J13-F13,2) -> 0 | L13: =IF(ABS(K13)<0.005,"OK",IF(ABS(K13)<=0.11,"Rounding / minimum fee","REVIEW")) -> OK
A14: 11 | B14: Account Fees | C14: Miscellaneous | D14: ACCOUNT MINIMUM FEE 25.00 MINIMUM LEVEL LESS 0.00 | E14: Fees | F14: -25
A15: 12 | B15: Account Fees | C15: Miscellaneous | D15: ILK-COMMERCIAL SOLUTIONS FEE $209.79 AT .000100 | E15: Fees | F15: -0.02 | G15: Sales base | H15: 209.79 | I15: 0.0001 | J15: =-ROUND(H15*I15,2) -> -0.02 | K15: =ROUND(J15-F15,2) -> 0 | L15: =IF(ABS(K15)<0.005,"OK",IF(ABS(K15)<=0.11,"Rounding / minimum fee","REVIEW")) -> OK
A16: 13 | B16: Account Fees | C16: Miscellaneous | D16: ILK-COMMERCIAL SOLUTIONS FEE $1,108.95 AT .000100 | E16: Fees | F16: -0.11 | G16: Sales base | H16: 1108.95 | I16: 0.0001 | J16: =-ROUND(H16*I16,2) -> -0.11 | K16: =ROUND(J16-F16,2) -> 0 | L16: =IF(ABS(K16)<0.005,"OK",IF(ABS(K16)<=0.11,"Rounding / minimum fee","REVIEW")) -> OK
A17: 14 | B17: Account Fees | C17: Miscellaneous | D17: US CROSS BORDER FEE 0 TRANS TOTALING $985.40 | E17: Fees | F17: -5.91
A18: 15 | B18: Account Fees | C18: Miscellaneous | D18: VISA NETWORK FEE CP 1B-08 | E18: Fees | F18: -88
A19: 16 | B19: Account Fees | C19: Miscellaneous | D19: ILK-COMMERCIAL SOLUTIONS FEE $483.68 AT .000100 | E19: Fees | F19: -0.05 | G19: Sales base | H19: 483.68 | I19: 0.0001 | J19: =-ROUND(H19*I19,2) -> -0.05 | K19: =ROUND(J19-F19,2) -> 0 | L19: =IF(ABS(K19)<0.005,"OK",IF(ABS(K19)<=0.11,"Rounding / minimum fee","REVIEW")) -> OK
A20: 17 | B20: Account Fees | C20: Miscellaneous | D20: VISA CB/EXCPT PACKAGE MAIL 1 TRANSACTIONS AT 0.78 | E20: Fees | F20: -0.78 | G20: Transactions | H20: 1 | I20: 0.78 | J20: =-ROUND(H20*I20,2) -> -0.78 | K20: =ROUND(J20-F20,2) -> 0 | L20: =IF(ABS(K20)<0.005,"OK",IF(ABS(K20)<=0.11,"Rounding / minimum fee","REVIEW")) -> OK
A21: 18 | B21: Account Fees | C21: Miscellaneous | D21: VISA NETWORK FEE CNP 2-09 | E21: Fees | F21: -1000.01
A22: 19 | B22: Account Fees | C22: Mastercard | D22: MC-MOTO DOMESTIC FEE $25,506.68 AT .000150 | E22: Fees | F22: -3.83 | G22: Sales base | H22: 25506.68 | I22: 0.00015 | J22: =-ROUND(H22*I22,2) -> -3.83 | K22: =ROUND(J22-F22,2) -> 0 | L22: =IF(ABS(K22)<0.005,"OK",IF(ABS(K22)<=0.11,"Rounding / minimum fee","REVIEW")) -> OK
A23: 20 | B23: Account Fees | C23: Mastercard | D23: MC-MOTO DOMESTIC FEE $66,812.23 AT .000150 | E23: Fees | F23: -10.02 | G23: Sales base | H23: 66812.23 | I23: 0.00015 | J23: =-ROUND(H23*I23,2) -> -10.02 | K23: =ROUND(J23-F23,2) -> 0 | L23: =IF(ABS(K23)<0.005,"OK",IF(ABS(K23)<=0.11,"Rounding / minimum fee","REVIEW")) -> OK
A24: 21 | B24: Account Fees | C24: Mastercard | D24: MC-MOTO DOMESTIC FEE $86,963.63 AT .000150 | E24: Fees | F24: -13.04 | G24: Sales base | H24: 86963.63 | I24: 0.00015 | J24: =-ROUND(H24*I24,2) -> -13.04 | K24: =ROUND(J24-F24,2) -> 0 | L24: =IF(ABS(K24)<0.005,"OK",IF(ABS(K24)<=0.11,"Rounding / minimum fee","REVIEW")) -> OK
A25: 22 | B25: Account Fees | C25: Mastercard | D25: MC-MOTO DOMESTIC FEE $49,052.79 AT .000150 | E25: Fees | F25: -7.36 | G25: Sales base | H25: 49052.79 | I25: 0.00015 | J25: =-ROUND(H25*I25,2) -> -7.36 | K25: =ROUND(J25-F25,2) -> 0 | L25: =IF(ABS(K25)<0.005,"OK",IF(ABS(K25)<=0.11,"Rounding / minimum fee","REVIEW")) -> OK
A26: 23 | B26: Account Fees | C26: Mastercard | D26: MC-MOTO DOMESTIC FEE DECLINE $26,812.10 AT .000150 | E26: Fees | F26: -4.02 | G26: Sales base | H26: 26812.1 | I26: 0.00015 | J26: =-ROUND(H26*I26,2) -> -4.02 | K26: =ROUND(J26-F26,2) -> 0 | L26: =IF(ABS(K26)<0.005,"OK",IF(ABS(K26)<=0.11,"Rounding / minimum fee","REVIEW")) -> OK
A27: 24 | B27: Account Fees | C27: Mastercard | D27: MC-MOTO DOMESTIC FEE DECLINE $36,156.88 AT .000150 | E27: Fees | F27: -5.42 | G27: Sales base | H27: 36156.88 | I27: 0.00015 | J27: =-ROUND(H27*I27,2) -> -5.42 | K27: =ROUND(J27-F27,2) -> 0 | L27: =IF(ABS(K27)<0.005,"OK",IF(ABS(K27)<=0.11,"Rounding / minimum fee","REVIEW")) -> OK
A28: 25 | B28: Account Fees | C28: Mastercard | D28: MC-MOTO DOMESTIC FEE $732.81 AT .000150 | E28: Fees | F28: -0.11 | G28: Sales base | H28: 732.81 | I28: 0.00015 | J28: =-ROUND(H28*I28,2) -> -0.11 | K28: =ROUND(J28-F28,2) -> 0 | L28: =IF(ABS(K28)<0.005,"OK",IF(ABS(K28)<=0.11,"Rounding / minimum fee","REVIEW")) -> OK
A29: 26 | B29: Account Fees | C29: Mastercard | D29: MC-MOTO DOMESTIC FEE $68,502.34 AT .000150 | E29: Fees | F29: -10.28 | G29: Sales base | H29: 68502.34 | I29: 0.00015 | J29: =-ROUND(H29*I29,2) -> -10.28 | K29: =ROUND(J29-F29,2) -> 0 | L29: =IF(ABS(K29)<0.005,"OK",IF(ABS(K29)<=0.11,"Rounding / minimum fee","REVIEW")) -> OK
A30: 27 | B30: Account Fees | C30: Mastercard | D30: MC-MOTO DOMESTIC FEE DECLINE $23,576.48 AT .000150 | E30: Fees | F30: -3.54 | G30: Sales base | H30: 23576.48 | I30: 0.00015 | J30: =-ROUND(H30*I30,2) -> -3.54 | K30: =ROUND(J30-F30,2) -> 0 | L30: =IF(ABS(K30)<0.005,"OK",IF(ABS(K30)<=0.11,"Rounding / minimum fee","REVIEW")) -> OK
A31: 28 | B31: Account Fees | C31: Mastercard | D31: MC-MOTO DOMESTIC FEE DECLINE $29,498.87 AT .000150 | E31: Fees | F31: -4.42 | G31: Sales base | H31: 29498.87 | I31: 0.00015 | J31: =-ROUND(H31*I31,2) -> -4.42 | K31: =ROUND(J31-F31,2) -> 0 | L31: =IF(ABS(K31)<0.005,"OK",IF(ABS(K31)<=0.11,"Rounding / minimum fee","REVIEW")) -> OK
A32: 29 | B32: Account Fees | C32: Mastercard | D32: MC-MOTO DOMESTIC FEE DECLINE $13,171.15 AT .000150 | E32: Fees | F32: -1.98 | G32: Sales base | H32: 13171.15 | I32: 0.00015 | J32: =-ROUND(H32*I32,2) -> -1.98 | K32: =ROUND(J32-F32,2) -> 0 | L32: =IF(ABS(K32)<0.005,"OK",IF(ABS(K32)<=0.11,"Rounding / minimum fee","REVIEW")) -> OK
A33: 30 | B33: Account Fees | C33: Mastercard | D33: MC-MOTO DOMESTIC FEE DECLINE $9,287.32 AT .000150 | E33: Fees | F33: -1.39 | G33: Sales base | H33: 9287.32 | I33: 0.00015 | J33: =-ROUND(H33*I33,2) -> -1.39 | K33: =ROUND(J33-F33,2) -> 0 | L33: =IF(ABS(K33)<0.005,"OK",IF(ABS(K33)<=0.11,"Rounding / minimum fee","REVIEW")) -> OK
... A99: 96 | B99: Account Fees | C99: Visa | D99: VI-COMMERCIAL SOLUTIONS FEE .000100 TIMES $83,808.24 | E99: Fees | F99: -8.38 | G99: Sales base | H99: 83808.24 | I99: 0.0001 | J99: =-ROUND(H99*I99,2) -> -8.38 | K99: =ROUND(J99-F99,2) -> 0 | L99: =IF(ABS(K99)<0.005,"OK",IF(ABS(K99)<=0.11,"Rounding / minimum fee","REVIEW")) -> OK
A100: 97 | B100: Debit Fees | C100: Debit | D100: MAESTRO | E100: Interchange Charges | F100: -588.32
A101: 98 | B101: Debit Fees | C101: Debit | D101: ACCEL ADVANTAGE REG | E101: Interchange Charges | F101: -1340.12
A102: 99 | B102: Debit Fees | C102: Debit | D102: MAESTRO REG DECLINE | E102: Interchange Charges | F102: -0.16
A103: 100 | B103: Debit Fees | C103: Debit | D103: MAESTRO DECLINE | E103: Interchange Charges | F103: -0.03
A104: 101 | B104: Debit Fees | C104: Debit | D104: ACCEL DECLINE | E104: Interchange Charges | F104: -0.1
A105: 102 | B105: Debit Fees | C105: Debit | D105: PAVD DECLINE | E105: Interchange Charges | F105: -0.11
A106: 103 | B106: Debit Fees | C106: Debit | D106: PAVD | E106: Interchange Charges | F106: -70.68
A107: 104 | B107: Debit Fees | C107: Debit | D107: ACCEL ADVANTAGE REG DECLINE | E107: Interchange Charges | F107: -0.4
A108: 105 | B108: Debit Fees | C108: Debit | D108: STAR NE PREFER REG | E108: Interchange Charges | F108: -373.77
A109: 106 | B109: Debit Fees | C109: Debit | D109: ACCEL | E109: Interchange Charges | F109: -57.87
A110: 107 | B110: Debit Fees | C110: Debit | D110: PAVD REG | E110: Interchange Charges | F110: -5.01
A111: 108 | B111: Debit Fees | C111: Debit | D111: ACCEL ADVANTAGE DECLINE | E111: Interchange Charges | F111: -0.5
... A119: 116 | B119: Debit Fees | C119: Debit | D119: PULSE PAY LIMITED/PREPAID | E119: Interchange Charges | F119: -128.66
A120: 117 | B120: Debit Network Fees | C120: Debit | D120: DEBIT/ATM CARD TRANSACTION FEE 49 TRANSACTIONS AT 0.1 | E120: Service Charges | F120: -4.9 | G120: Transactions | H120: 49 | I120: 0.1 | J120: =-ROUND(H120*I120,2) -> -4.9 | K120: =ROUND(J120-F120,2) -> 0 | L120: =IF(ABS(K120)<0.005,"OK",IF(ABS(K120)<=0.11,"Rounding / minimum fee","REVIEW")) -> OK
A121: 118 | B121: Transaction Fees | C121: Miscellaneous | D121: MC PROC INTEG FINAL AUTH 0 TRANS TOTALING $12105.66 | E121: Fees | F121: -30.26
A122: 119 | B122: Transaction Fees | C122: Miscellaneous | D122: CARDPOINTE PLATFORM FEE | E122: Service Charges | F122: -803.85
A123: 120 | B123: Transaction Fees | C123: Miscellaneous | D123: DIGITAL INVESTMENT FEE $70311.30 AT0.0001 | E123: Service Charges | F123: -7.03 | G123: Sales base | H123: 70311.3 | I123: 0.0001 | J123: =-ROUND(H123*I123,2) -> -7.03 | K123: =ROUND(J123-F123,2) -> 0 | L123: =IF(ABS(K123)<0.005,"OK",IF(ABS(K123)<=0.11,"Rounding / minimum fee","REVIEW")) -> OK
A124: 121 | B124: Transaction Fees | C124: Miscellaneous | D124: VI BASE II SYSTEM FILE FEE 5340 TRANSACTIONS AT 0.0025 | E124: Service Charges | F124: -13.4 | G124: Transactions | H124: 5340 | I124: 0.0025 | J124: =-ROUND(H124*I124,2) -> -13.35 | K124: =ROUND(J124-F124,2) -> 0.05 | L124: =IF(ABS(K124)<0.005,"OK",IF(ABS(K124)<=0.11,"Rounding / minimum fee","REVIEW")) -> Rounding / minimum fee
A125: 122 | B125: Transaction Fees | C125: Miscellaneous | D125: AVS WATS AUTHORIZATION FEE 10826 TRANSACTIONS AT 0.05 | E125: Fees | F125: -541.3 | G125: Transactions | H125: 10826 | I125: 0.05 | J125: =-ROUND(H125*I125,2) -> -541.3 | K125: =ROUND(J125-F125,2) -> 0 | L125: =IF(ABS(K125)<0.005,"OK",IF(ABS(K125)<=0.11,"Rounding / minimum fee","REVIEW")) -> OK
A126: 123 | B126: Transaction Fees | C126: Miscellaneous | D126: MC-AUTH DIGITAL ENABLEMENT FEE $491630.15 AT0.00025 | E126: Fees | F126: -122.9 | G126: Sales base | H126: 491630.15 | I126: 0.00025 | J126: =-ROUND(H126*I126,2) -> -122.91 | K126: =ROUND(J126-F126,2) -> -0.01 | L126: =IF(ABS(K126)<0.005,"OK",IF(ABS(K126)<=0.11,"Rounding / minimum fee","REVIEW")) -> Rounding / minimum fee
A127: 124 | B127: Transaction Fees | C127: Miscellaneous | D127: MC CLEARING CONNECTIVITY FEE 2581 KILOBYTES AT 0.002294 | E127: Service Charges | F127: -5.91 | G127: Kilobytes | H127: 2581 | I127: 0.002294 | J127: =-ROUND(H127*I127,2) -> -5.92 | K127: =ROUND(J127-F127,2) -> -0.01 | L127: =IF(ABS(K127)<0.005,"OK",IF(ABS(K127)<=0.11,"Rounding / minimum fee","REVIEW")) -> Rounding / minimum fee
A128: 125 | B128: Transaction Fees | C128: Miscellaneous | D128: VI BASE II CR VCHER FEE US CR 132 TRANSACTIONS AT 0.0195 | E128: Service Charges | F128: -2.6 | G128: Transactions | H128: 132 | I128: 0.0195 | J128: =-ROUND(H128*I128,2) -> -2.57 | K128: =ROUND(J128-F128,2) -> 0.03 | L128: =IF(ABS(K128)<0.005,"OK",IF(ABS(K128)<=0.11,"Rounding / minimum fee","REVIEW")) -> Rounding / minimum fee
A129: 126 | B129: Transaction Fees | C129: Miscellaneous | D129: BATCH SETTLEMENT FEE 803 TRANSACTIONS AT 0.1 | E129: Fees | F129: -80.3 | G129: Transactions | H129: 803 | I129: 0.1 | J129: =-ROUND(H129*I129,2) -> -80.3 | K129: =ROUND(J129-F129,2) -> 0 | L129: =IF(ABS(K129)<0.005,"OK",IF(ABS(K129)<=0.11,"Rounding / minimum fee","REVIEW")) -> OK
A130: 127 | B130: Transaction Fees | C130: Miscellaneous | D130: VI BASE II CR VCHER FEE US D/P 143 TRANSACTIONS AT 0.0155 | E130: Service Charges | F130: -2.23 | G130: Transactions | H130: 143 | I130: 0.0155 | J130: =-ROUND(H130*I130,2) -> -2.22 | K130: =ROUND(J130-F130,2) -> 0.01 | L130: =IF(ABS(K130)<0.005,"OK",IF(ABS(K130)<=0.11,"Rounding / minimum fee","REVIEW")) -> Rounding / minimum fee
A131: 128 | B131: Transaction Fees | C131: Miscellaneous | D131: MC NTWRK ACCESS SETTLEMENT FEE 190 TRANSACTIONS AT 0.0195 | E131: Interchange Charges | F131: -3.72 | G131: Transactions | H131: 190 | I131: 0.0195 | J131: =-ROUND(H131*I131,2) -> -3.71 | K131: =ROUND(J131-F131,2) -> 0.01 | L131: =IF(ABS(K131)<0.005,"OK",IF(ABS(K131)<=0.11,"Rounding / minimum fee","REVIEW")) -> Rounding / minimum fee | M131: Y
A132: 129 | B132: Transaction Fees | C132: Mastercard | D132: MC LICENSE VOLUME FEE 0.000046 DISC RATE TIMES $2664297.23 | E132: Service Charges | F132: -122.58 | G132: Sales base | H132: 2664297.2 | I132: 4.6e-05 | J132: =-ROUND(H132*I132,2) -> -122.56 | K132: =ROUND(J132-F132,2) -> 0.02 | L132: =IF(ABS(K132)<0.005,"OK",IF(ABS(K132)<=0.11,"Rounding / minimum fee","REVIEW")) -> Rounding / minimum fee
A133: 130 | B133: Transaction Fees | C133: Mastercard | D133: MC ACQUIRER AVS BILLING 1860 TRANSACTIONS AT 0.01 | E133: Fees | F133: -18.6 | G133: Transactions | H133: 1860 | I133: 0.01 | J133: =-ROUND(H133*I133,2) -> -18.6 | K133: =ROUND(J133-F133,2) -> 0 | L133: =IF(ABS(K133)<0.005,"OK",IF(ABS(K133)<=0.11,"Rounding / minimum fee","REVIEW")) -> OK
A134: 131 | B134: Transaction Fees | C134: Mastercard | D134: MC-AUTH DIGITAL ENABLEMENT MIN 434 TRANSACTIONS AT 0.025 | E134: Fees | F134: -10.92 | G134: Transactions | H134: 434 | I134: 0.025 | J134: =-ROUND(H134*I134,2) -> -10.85 | K134: =ROUND(J134-F134,2) -> 0.07 | L134: =IF(ABS(K134)<0.005,"OK",IF(ABS(K134)<=0.11,"Rounding / minimum fee","REVIEW")) -> Rounding / minimum fee
A135: 132 | B135: Transaction Fees | C135: Mastercard | D135: MC NETWORK ACCESS AUTH FEE 3347 TRANSACTIONS AT 0.0195 | E135: Fees | F135: -65.26 | G135: Transactions | H135: 3347 | I135: 0.0195 | J135: =-ROUND(H135*I135,2) -> -65.27 | K135: =ROUND(J135-F135,2) -> -0.01 | L135: =IF(ABS(K135)<0.005,"OK",IF(ABS(K135)<=0.11,"Rounding / minimum fee","REVIEW")) -> Rounding / minimum fee
A136: 133 | B136: Transaction Fees | C136: Mastercard | D136: MC PIF DETAIL REPORT 7 TRANSACTIONS AT 0.02 | E136: Fees | F136: -0.14 | G136: Transactions | H136: 7 | I136: 0.02 | J136: =-ROUND(H136*I136,2) -> -0.14 | K136: =ROUND(J136-F136,2) -> 0 | L136: =IF(ABS(K136)<0.005,"OK",IF(ABS(K136)<=0.11,"Rounding / minimum fee","REVIEW")) -> OK
A137: 134 | B137: Transaction Fees | C137: Mastercard | D137: MC ASSESSMNT TRAN AMT >=$1K 0 X TRNS $1665458.91 | E137: Interchange Charges | F137: -166.51 | M137: Y
A138: 135 | B138: Transaction Fees | C138: Mastercard | D138: MASTERCARD SALES DISCOUNT 0.0015 DISC RATE TIMES $2051547.43 | E138: Service Charges | F138: -3077.31 | G138: Sales base | H138: 2051547.4 | I138: 0.0015 | J138: =-ROUND(H138*I138,2) -> -3077.32 | K138: =ROUND(J138-F138,2) -> -0.01 | L138: =IF(ABS(K138)<0.005,"OK",IF(ABS(K138)<=0.11,"Rounding / minimum fee","REVIEW")) -> Rounding / minimum fee
A139: 136 | B139: Transaction Fees | C139: Mastercard | D139: MC-NTWK ACCESS AUTH FEE NONUS 1 TRANSACTIONS AT .029500 | E139: Fees | F139: -0.09 | G139: Transactions | H139: 1 | I139: 0.0295 | J139: =-ROUND(H139*I139,2) -> -0.03 | K139: =ROUND(J139-F139,2) -> 0.06 | L139: =IF(ABS(K139)<0.005,"OK",IF(ABS(K139)<=0.11,"Rounding / minimum fee","REVIEW")) -> Rounding / minimum fee
A140: 137 | B140: Transaction Fees | C140: Mastercard | D140: MASTERCARD AUTH FEE 3559 TRANSACTIONS AT 0.1 | E140: Fees | F140: -355.9 | G140: Transactions | H140: 3559 | I140: 0.1 | J140: =-ROUND(H140*I140,2) -> -355.9 | K140: =ROUND(J140-F140,2) -> 0 | L140: =IF(ABS(K140)<0.005,"OK",IF(ABS(K140)<=0.11,"Rounding / minimum fee","REVIEW")) -> OK
A141: 138 | B141: Transaction Fees | C141: Mastercard | D141: MC-AUTH DIGITAL ENABLEMENT MAX 302 TRANSACTIONS AT 0.5 | E141: Fees | F141: -151 | G141: Transactions | H141: 302 | I141: 0.5 | J141: =-ROUND(H141*I141,2) -> -151 | K141: =ROUND(J141-F141,2) -> 0 | L141: =IF(ABS(K141)<0.005,"OK",IF(ABS(K141)<=0.11,"Rounding / minimum fee","REVIEW")) -> OK
A142: 139 | B142: Transaction Fees | C142: Mastercard | D142: MC TPE EXCESSIVE AUTH 7 TRANSACTIONS AT 0.5 | E142: Fees | F142: -3.5 | G142: Transactions | H142: 7 | I142: 0.5 | J142: =-ROUND(H142*I142,2) -> -3.5 | K142: =ROUND(J142-F142,2) -> 0 | L142: =IF(ABS(K142)<0.005,"OK",IF(ABS(K142)<=0.11,"Rounding / minimum fee","REVIEW")) -> OK
A143: 140 | B143: Transaction Fees | C143: Mastercard | D143: MC AUTH CONNECTIVITY FEE 2983 KILOBYTES AT 0.002294 | E143: Service Charges | F143: -6.83 | G143: Kilobytes | H143: 2983 | I143: 0.002294 | J143: =-ROUND(H143*I143,2) -> -6.84 | K143: =ROUND(J143-F143,2) -> -0.01 | L143: =IF(ABS(K143)<0.005,"OK",IF(ABS(K143)<=0.11,"Rounding / minimum fee","REVIEW")) -> Rounding / minimum fee
A144: 141 | B144: Transaction Fees | C144: Mastercard | D144: MC-DECLINE REASON CODE SVC FEE 1 TRANSACTIONS AT 0.02 | E144: Fees | F144: -0.02 | G144: Transactions | H144: 1 | I144: 0.02 | J144: =-ROUND(H144*I144,2) -> -0.02 | K144: =ROUND(J144-F144,2) -> 0 | L144: =IF(ABS(K144)<0.005,"OK",IF(ABS(K144)<=0.11,"Rounding / minimum fee","REVIEW")) -> OK
A145: 142 | B145: Transaction Fees | C145: Mastercard | D145: MASTERCARD ASSESSMENT FEE 0.0014 TIMES $2664297.23 | E145: Interchange Charges | F145: -3730.01 | G145: Sales base | H145: 2664297.2 | I145: 0.0014 | J145: =-ROUND(H145*I145,2) -> -3730.02 | K145: =ROUND(J145-F145,2) -> -0.01 | L145: =IF(ABS(K145)<0.005,"OK",IF(ABS(K145)<=0.11,"Rounding / minimum fee","REVIEW")) -> Rounding / minimum fee | M145: Y
A146: 143 | B146: Transaction Fees | C146: Mastercard | D146: MASTERCARD DEBIT SALES DISC 0.0015 DISC RATE TIMES $612749.80 | E146: Service Charges | F146: -919.11 | G146: Sales base | H146: 612749.8 | I146: 0.0015 | J146: =-ROUND(H146*I146,2) -> -919.12 | K146: =ROUND(J146-F146,2) -> -0.01 | L146: =IF(ABS(K146)<0.005,"OK",IF(ABS(K146)<=0.11,"Rounding / minimum fee","REVIEW")) -> Rounding / minimum fee
A147: 144 | B147: Transaction Fees | C147: Mastercard | D147: CNP AVS FEE 1490 TRANSACTIONS AT 0.01 | E147: Fees | F147: -14.9 | G147: Transactions | H147: 1490 | I147: 0.01 | J147: =-ROUND(H147*I147,2) -> -14.9 | K147: =ROUND(J147-F147,2) -> 0 | L147: =IF(ABS(K147)<0.005,"OK",IF(ABS(K147)<=0.11,"Rounding / minimum fee","REVIEW")) -> OK
A148: 145 | B148: Transaction Fees | C148: Mastercard | D148: MC-WORLD HV SMALL TICKET CP | E148: Interchange Charges | F148: -0.1
A149: 146 | B149: Transaction Fees | C149: Mastercard | D149: MC-REG INCENT FRF ADJ POS (DB) | E149: Interchange Charges | F149: -40.37
A150: 147 | B150: Transaction Fees | C150: Mastercard | D150: MC-CORP DATA RATE I (US) PUR | E150: Interchange Charges | F150: -3134.14
A151: 148 | B151: Transaction Fees | C151: Mastercard | D151: MC-CORP DATA RATE II (US) BUS | E151: Interchange Charges | F151: -518.75
A152: 149 | B152: Transaction Fees | C152: Mastercard | D152: MC-US STP B2B VIP 7 | E152: Interchange Charges | F152: -5425.67
A153: 150 | B153: Transaction Fees | C153: Mastercard | D153: MC-COM DATA RATE I FLT NFUEL | E153: Interchange Charges | F153: -993.8
A154: 151 | B154: Transaction Fees | C154: Mastercard | D154: MC-WORLD ELITE MERIT I | E154: Interchange Charges | F154: -7097.09
A155: 152 | B155: Transaction Fees | C155: Mastercard | D155: MC-DOMESTIC MERIT I (DB) | E155: Interchange Charges | F155: -777.91
A156: 153 | B156: Transaction Fees | C156: Mastercard | D156: MC-WRLD ELITE SMALL TICKET CP | E156: Interchange Charges | F156: -0.11
A157: 154 | B157: Transaction Fees | C157: Mastercard | D157: MC-COMM DATA RATE II BUS (DB) | E157: Interchange Charges | F157: -3928.98
A158: 155 | B158: Transaction Fees | C158: Mastercard | D158: MC-WORLDCARD MERIT I | E158: Interchange Charges | F158: -219.63
A159: 156 | B159: Transaction Fees | C159: Mastercard | D159: MC-INT CON RTE 2 CP PREM | E159: Interchange Charges | F159: -2.2
... A187: 184 | B187: Transaction Fees | C187: Mastercard | D187: MC-DOMESTIC MERIT I | E187: Interchange Charges | F187: -129.93
A188: 185 | B188: Transaction Fees | C188: Visa | D188: VI DIGITAL COMM CP SVCS FEE $6,979.27 AT .000100 | E188: Fees | F188: -0.7 | G188: Sales base | H188: 6979.27 | I188: 0.0001 | J188: =-ROUND(H188*I188,2) -> -0.7 | K188: =ROUND(J188-F188,2) -> 0 | L188: =IF(ABS(K188)<0.005,"OK",IF(ABS(K188)<=0.11,"Rounding / minimum fee","REVIEW")) -> OK
A189: 186 | B189: Transaction Fees | C189: Visa | D189: VI DIGTL COM US CNP SVC FEE MN 5 TRANSACTIONS AT .010000 | E189: Fees | F189: -0.1 | G189: Transactions | H189: 5 | I189: 0.01 | J189: =-ROUND(H189*I189,2) -> -0.05 | K189: =ROUND(J189-F189,2) -> 0.05 | L189: =IF(ABS(K189)<0.005,"OK",IF(ABS(K189)<=0.11,"Rounding / minimum fee","REVIEW")) -> Rounding / minimum fee
A190: 187 | B190: Transaction Fees | C190: Visa | D190: VISA DEBIT SALES DISCOUNT 0.0015 DISC RATE TIMES $1826627.84 | E190: Service Charges | F190: -2739.93 | G190: Sales base | H190: 1826627.8 | I190: 0.0015 | J190: =-ROUND(H190*I190,2) -> -2739.94 | K190: =ROUND(J190-F190,2) -> -0.01 | L190: =IF(ABS(K190)<0.005,"OK",IF(ABS(K190)<=0.11,"Rounding / minimum fee","REVIEW")) -> Rounding / minimum fee
A191: 188 | B191: Transaction Fees | C191: Visa | D191: VI DIGTL COM US CNP SVC FEE MN 15 TRANSACTIONS AT .010000 | E191: Fees | F191: -0.15 | G191: Transactions | H191: 15 | I191: 0.01 | J191: =-ROUND(H191*I191,2) -> -0.15 | K191: =ROUND(J191-F191,2) -> 0 | L191: =IF(ABS(K191)<0.005,"OK",IF(ABS(K191)<=0.11,"Rounding / minimum fee","REVIEW")) -> OK
A192: 189 | B192: Transaction Fees | C192: Visa | D192: VI DIGITAL COMM CP SVCS FEE $2,392.35 AT .000100 | E192: Fees | F192: -0.24 | G192: Sales base | H192: 2392.35 | I192: 0.0001 | J192: =-ROUND(H192*I192,2) -> -0.24 | K192: =ROUND(J192-F192,2) -> 0 | L192: =IF(ABS(K192)<0.005,"OK",IF(ABS(K192)<=0.11,"Rounding / minimum fee","REVIEW")) -> OK
A193: 190 | B193: Transaction Fees | C193: Visa | D193: VISA ASSESSMENT FEE CR 0.0014 TIMES $2482035.50 | E193: Interchange Charges | F193: -3474.85 | G193: Sales base | H193: 2482035.5 | I193: 0.0014 | J193: =-ROUND(H193*I193,2) -> -3474.85 | K193: =ROUND(J193-F193,2) -> 0 | L193: =IF(ABS(K193)<0.005,"OK",IF(ABS(K193)<=0.11,"Rounding / minimum fee","REVIEW")) -> OK | M193: Y
A194: 191 | B194: Transaction Fees | C194: Visa | D194: VI DIGTL COMRC US CNP SVCS FEE $136,815.29 AT .000150 | E194: Fees | F194: -20.52 | G194: Sales base | H194: 136815.29 | I194: 0.00015 | J194: =-ROUND(H194*I194,2) -> -20.52 | K194: =ROUND(J194-F194,2) -> 0 | L194: =IF(ABS(K194)<0.005,"OK",IF(ABS(K194)<=0.11,"Rounding / minimum fee","REVIEW")) -> OK
A195: 192 | B195: Transaction Fees | C195: Visa | D195: VISA SALES DISCOUNT 0.0015 DISC RATE TIMES $2482035.50 | E195: Service Charges | F195: -3723.04 | G195: Sales base | H195: 2482035.5 | I195: 0.0015 | J195: =-ROUND(H195*I195,2) -> -3723.05 | K195: =ROUND(J195-F195,2) -> -0.01 | L195: =IF(ABS(K195)<0.005,"OK",IF(ABS(K195)<=0.11,"Rounding / minimum fee","REVIEW")) -> Rounding / minimum fee
A196: 193 | B196: Transaction Fees | C196: Visa | D196: VI DIGITAL COMM CP SVCS FEE $61.34 AT .000100 | E196: Fees | F196: -0.01 | G196: Sales base | H196: 61.34 | I196: 0.0001 | J196: =-ROUND(H196*I196,2) -> -0.01 | K196: =ROUND(J196-F196,2) -> 0 | L196: =IF(ABS(K196)<0.005,"OK",IF(ABS(K196)<=0.11,"Rounding / minimum fee","REVIEW")) -> OK
A197: 194 | B197: Transaction Fees | C197: Visa | D197: VI DIGITAL COMM CP SVCS FEE $9,822.15 AT .000100 | E197: Fees | F197: -0.98 | G197: Sales base | H197: 9822.15 | I197: 0.0001 | J197: =-ROUND(H197*I197,2) -> -0.98 | K197: =ROUND(J197-F197,2) -> 0 | L197: =IF(ABS(K197)<0.005,"OK",IF(ABS(K197)<=0.11,"Rounding / minimum fee","REVIEW")) -> OK
A198: 195 | B198: Transaction Fees | C198: Visa | D198: VI NTWK ACQ PROC FEE INTL CR 1 TRANSACTIONS AT 0.0395 | E198: Fees | F198: -0.04 | G198: Transactions | H198: 1 | I198: 0.0395 | J198: =-ROUND(H198*I198,2) -> -0.04 | K198: =ROUND(J198-F198,2) -> 0 | L198: =IF(ABS(K198)<0.005,"OK",IF(ABS(K198)<=0.11,"Rounding / minimum fee","REVIEW")) -> OK
A199: 196 | B199: Transaction Fees | C199: Visa | D199: VI DIGTL COM US CNP SVC FEE MN 20 TRANSACTIONS AT .010000 | E199: Fees | F199: -0.2 | G199: Transactions | H199: 20 | I199: 0.01 | J199: =-ROUND(H199*I199,2) -> -0.2 | K199: =ROUND(J199-F199,2) -> 0 | L199: =IF(ABS(K199)<0.005,"OK",IF(ABS(K199)<=0.11,"Rounding / minimum fee","REVIEW")) -> OK
...

Sheet Interchange
A1: Interchange Charges / Program Fees
A2: Recomputed = -(sales x rate + transactions x per-transaction fee). The printed rate is rounded to 4 decimals, so differences up to $0.05 are rounding.
A3: Brand | B3: Product Description | C3: Sales Total | D3: % of Sales | E3: Total No. of Transactions | F3: % of Transactions | G3: Transaction Rate | H3: Per-transaction fee | I3: Interchange / Program Charges | J3: Recomputed | K3: Variance | L3: Flag | M3: % of sales recomputed (absolute basis) | N3: % of transactions recomputed | O3: % columns check
A4: MASTERCARD | B4: MC-INT CON RTE 2 CP PREM | C4: 118.73 | D4: 0 | E4: 1 | F4: 0 | G4: 0.0185 | H4: 0 | I4: -2.2 | J4: =-ROUND(C4*G4+E4*H4,2) -> -2.2 | K4: =ROUND(J4-I4,2) -> 0 | L4: =IF(ABS(K4)<0.005,"OK",IF(ABS(K4)<=0.05,"Rounding","REVIEW")) -> OK | M4: =ABS(C4)/SUMPRODUCT(($A$4:$A$143=A4)*ABS($C$4:$C$143)) -> 4.3210678e-05 | N4: =E4/SUMIFS($E$4:$E$143,$A$4:$A$143,A4) -> 0.00030459945 | O4: =IF(AND(ABS(ROUND(M4,2)-D4)<0.0051,ABS(ROUND(N4,2)-F4)<0.0051),"OK","REVIEW") -> OK
A5: MASTERCARD | B5: MC-BUS LEVEL 5 DATA RATE II | C5: 444995.75 | D5: 0.16 | E5: 566 | F5: 0.17 | G5: 0.0225 | H5: 0.1 | I5: -10069.01 | J5: =-ROUND(C5*G5+E5*H5,2) -> -10069 | K5: =ROUND(J5-I5,2) -> 0.01 | L5: =IF(ABS(K5)<0.005,"OK",IF(ABS(K5)<=0.05,"Rounding","REVIEW")) -> Rounding | M5: =ABS(C5)/SUMPRODUCT(($A$4:$A$143=A5)*ABS($C$4:$C$143)) -> 0.16195206 | N5: =E5/SUMIFS($E$4:$E$143,$A$4:$A$143,A5) -> 0.17240329 | O5: =IF(AND(ABS(ROUND(M5,2)-D5)<0.0051,ABS(ROUND(N5,2)-F5)<0.0051),"OK","REVIEW") -> OK
A6: MASTERCARD | B6: MC-CONSUMER REFUND 1 (DB) | C6: -2363.25 | D6: 0 | E6: 14 | F6: 0 | G6: 0 | H6: 0 | I6: 0 | J6: 0 | K6: =ROUND(J6-I6,2) -> 0 | L6: =IF(ABS(K6)<0.005,"OK",IF(ABS(K6)<=0.05,"Rounding","REVIEW")) -> OK | M6: =ABS(C6)/SUMPRODUCT(($A$4:$A$143=A6)*ABS($C$4:$C$143)) -> 0.00086008283 | N6: =E6/SUMIFS($E$4:$E$143,$A$4:$A$143,A6) -> 0.0042643923 | O6: =IF(AND(ABS(ROUND(M6,2)-D6)<0.0051,ABS(ROUND(N6,2)-F6)<0.0051),"OK","REVIEW") -> OK
A7: MASTERCARD | B7: MC-US STP B2B VIP 9 | C7: 31954.35 | D7: 0.01 | E7: 14 | F7: 0 | G7: 0.0295 | H7: 0.1 | I7: -944.05 | J7: =-ROUND(C7*G7+E7*H7,2) -> -944.05 | K7: =ROUND(J7-I7,2) -> 0 | L7: =IF(ABS(K7)<0.005,"OK",IF(ABS(K7)<=0.05,"Rounding","REVIEW")) -> OK | M7: =ABS(C7)/SUMPRODUCT(($A$4:$A$143=A7)*ABS($C$4:$C$143)) -> 0.011629488 | N7: =E7/SUMIFS($E$4:$E$143,$A$4:$A$143,A7) -> 0.0042643923 | O7: =IF(AND(ABS(ROUND(M7,2)-D7)<0.0051,ABS(ROUND(N7,2)-F7)<0.0051),"OK","REVIEW") -> OK
A8: MASTERCARD | B8: MC-WRLD ELITE SMALL TICKET CP | C8: 3.99 | D8: 0 | E8: 1 | F8: 0 | G8: 0.023 | H8: 0.02 | I8: -0.11 | J8: =-ROUND(C8*G8+E8*H8,2) -> -0.11 | K8: =ROUND(J8-I8,2) -> 0 | L8: =IF(ABS(K8)<0.005,"OK",IF(ABS(K8)<=0.05,"Rounding","REVIEW")) -> OK | M8: =ABS(C8)/SUMPRODUCT(($A$4:$A$143=A8)*ABS($C$4:$C$143)) -> 1.4521233e-06 | N8: =E8/SUMIFS($E$4:$E$143,$A$4:$A$143,A8) -> 0.00030459945 | O8: =IF(AND(ABS(ROUND(M8,2)-D8)<0.0051,ABS(ROUND(N8,2)-F8)<0.0051),"OK","REVIEW") -> OK
A9: MASTERCARD | B9: MC-CORP DATA RATE I (US) BUS | C9: 67263.59 | D9: 0.02 | E9: 48 | F9: 0.01 | G9: 0.0265 | H9: 0.1 | I9: -1787.29 | J9: =-ROUND(C9*G9+E9*H9,2) -> -1787.29 | K9: =ROUND(J9-I9,2) -> 0 | L9: =IF(ABS(K9)<0.005,"OK",IF(ABS(K9)<=0.05,"Rounding","REVIEW")) -> OK | M9: =ABS(C9)/SUMPRODUCT(($A$4:$A$143=A9)*ABS($C$4:$C$143)) -> 0.024479957 | N9: =E9/SUMIFS($E$4:$E$143,$A$4:$A$143,A9) -> 0.014620774 | O9: =IF(AND(ABS(ROUND(M9,2)-D9)<0.0051,ABS(ROUND(N9,2)-F9)<0.0051),"OK","REVIEW") -> OK
A10: MASTERCARD | B10: MC-BUS LEVEL 5 DATA RATE I | C10: 237202.26 | D10: 0.09 | E10: 89 | F10: 0.03 | G10: 0.03 | H10: 0.1 | I10: -7124.97 | J10: =-ROUND(C10*G10+E10*H10,2) -> -7124.97 | K10: =ROUND(J10-I10,2) -> 0 | L10: =IF(ABS(K10)<0.005,"OK",IF(ABS(K10)<=0.05,"Rounding","REVIEW")) -> OK | M10: =ABS(C10)/SUMPRODUCT(($A$4:$A$143=A10)*ABS($C$4:$C$143)) -> 0.086327554 | N10: =E10/SUMIFS($E$4:$E$143,$A$4:$A$143,A10) -> 0.027109351 | O10: =IF(AND(ABS(ROUND(M10,2)-D10)<0.0051,ABS(ROUND(N10,2)-F10)<0.0051),"OK","REVIEW") -> OK
A11: MASTERCARD | B11: MC-CORPORATE CREDIT REFUND 3 | C11: -33828.89 | D11: 0.01 | E11: 68 | F11: 0.02 | G11: 0 | H11: 0 | I11: 0 | J11: 0 | K11: =ROUND(J11-I11,2) -> 0 | L11: =IF(ABS(K11)<0.005,"OK",IF(ABS(K11)<=0.05,"Rounding","REVIEW")) -> OK | M11: =ABS(C11)/SUMPRODUCT(($A$4:$A$143=A11)*ABS($C$4:$C$143)) -> 0.01231171 | N11: =E11/SUMIFS($E$4:$E$143,$A$4:$A$143,A11) -> 0.020712763 | O11: =IF(AND(ABS(ROUND(M11,2)-D11)<0.0051,ABS(ROUND(N11,2)-F11)<0.0051),"OK","REVIEW") -> OK
A12: MASTERCARD | B12: MC-CORPORATE CREDIT REFUND 4 | C12: -380.95 | D12: 0 | E12: 1 | F12: 0 | G12: 0 | H12: 0 | I12: 0 | J12: 0 | K12: =ROUND(J12-I12,2) -> 0 | L12: =IF(ABS(K12)<0.005,"OK",IF(ABS(K12)<=0.05,"Rounding","REVIEW")) -> OK | M12: =ABS(C12)/SUMPRODUCT(($A$4:$A$143=A12)*ABS($C$4:$C$143)) -> 0.00013864321 | N12: =E12/SUMIFS($E$4:$E$143,$A$4:$A$143,A12) -> 0.00030459945 | O12: =IF(AND(ABS(ROUND(M12,2)-D12)<0.0051,ABS(ROUND(N12,2)-F12)<0.0051),"OK","REVIEW") -> OK
A13: MASTERCARD | B13: MC-BUS LEVEL 2 DATA RATE I | C13: 1451.01 | D13: 0 | E13: 5 | F13: 0 | G13: 0.028 | H13: 0.1 | I13: -41.13 | J13: =-ROUND(C13*G13+E13*H13,2) -> -41.13 | K13: =ROUND(J13-I13,2) -> 0 | L13: =IF(ABS(K13)<0.005,"OK",IF(ABS(K13)<=0.05,"Rounding","REVIEW")) -> OK | M13: =ABS(C13)/SUMPRODUCT(($A$4:$A$143=A13)*ABS($C$4:$C$143)) -> 0.00052808158 | N13: =E13/SUMIFS($E$4:$E$143,$A$4:$A$143,A13) -> 0.0015229973 | O13: =IF(AND(ABS(ROUND(M13,2)-D13)<0.0051,ABS(ROUND(N13,2)-F13)<0.0051),"OK","REVIEW") -> OK
A14: MASTERCARD | B14: MC-CORP BUSINESS INTL FLT | C14: 866.67 | D14: 0 | E14: 1 | F14: 0 | G14: 0.02 | H14: 0 | I14: -17.33 | J14: =-ROUND(C14*G14+E14*H14,2) -> -17.33 | K14: =ROUND(J14-I14,2) -> 0 | L14: =IF(ABS(K14)<0.005,"OK",IF(ABS(K14)<=0.05,"Rounding","REVIEW")) -> OK | M14: =ABS(C14)/SUMPRODUCT(($A$4:$A$143=A14)*ABS($C$4:$C$143)) -> 0.00031541648 | N14: =E14/SUMIFS($E$4:$E$143,$A$4:$A$143,A14) -> 0.00030459945 | O14: =IF(AND(ABS(ROUND(M14,2)-D14)<0.0051,ABS(ROUND(N14,2)-F14)<0.0051),"OK","REVIEW") -> OK
A15: MASTERCARD | B15: MC-CORP DATA RATE II (US) PUR | C15: 12743.93 | D15: 0 | E15: 18 | F15: 0.01 | G15: 0.025 | H15: 0.1 | I15: -320.41 | J15: =-ROUND(C15*G15+E15*H15,2) -> -320.4 | K15: =ROUND(J15-I15,2) -> 0.01 | L15: =IF(ABS(K15)<0.005,"OK",IF(ABS(K15)<=0.05,"Rounding","REVIEW")) -> Rounding | M15: =ABS(C15)/SUMPRODUCT(($A$4:$A$143=A15)*ABS($C$4:$C$143)) -> 0.0046380347 | N15: =E15/SUMIFS($E$4:$E$143,$A$4:$A$143,A15) -> 0.0054827901 | O15: =IF(AND(ABS(ROUND(M15,2)-D15)<0.0051,ABS(ROUND(N15,2)-F15)<0.0051),"OK","REVIEW") -> OK
A16: MASTERCARD | B16: MC-BUS LEVEL 4 DATA RATE I | C16: 27424.38 | D16: 0.01 | E16: 16 | F16: 0 | G16: 0.0295 | H16: 0.1 | I16: -810.63 | J16: =-ROUND(C16*G16+E16*H16,2) -> -810.62 | K16: =ROUND(J16-I16,2) -> 0.01 | L16: =IF(ABS(K16)<0.005,"OK",IF(ABS(K16)<=0.05,"Rounding","REVIEW")) -> Rounding | M16: =ABS(C16)/SUMPRODUCT(($A$4:$A$143=A16)*ABS($C$4:$C$143)) -> 0.0099808477 | N16: =E16/SUMIFS($E$4:$E$143,$A$4:$A$143,A16) -> 0.0048735912 | O16: =IF(AND(ABS(ROUND(M16,2)-D16)<0.0051,ABS(ROUND(N16,2)-F16)<0.0051),"OK","REVIEW") -> OK
A17: MASTERCARD | B17: MC-WORLDCARD MERIT III | C17: 18690.81 | D17: 0.01 | E17: 55 | F17: 0.02 | G17: 0.019 | H17: 0.1 | I17: -360.62 | J17: =-ROUND(C17*G17+E17*H17,2) -> -360.63 | K17: =ROUND(J17-I17,2) -> -0.01 | L17: =IF(ABS(K17)<0.005,"OK",IF(ABS(K17)<=0.05,"Rounding","REVIEW")) -> Rounding | M17: =ABS(C17)/SUMPRODUCT(($A$4:$A$143=A17)*ABS($C$4:$C$143)) -> 0.0068023463 | N17: =E17/SUMIFS($E$4:$E$143,$A$4:$A$143,A17) -> 0.01675297 | O17: =IF(AND(ABS(ROUND(M17,2)-D17)<0.0051,ABS(ROUND(N17,2)-F17)<0.0051),"OK","REVIEW") -> OK
A18: MASTERCARD | B18: MC-CONSUMER CREDIT REFUND 5 | C18: -258.08 | D18: 0 | E18: 5 | F18: 0 | G18: 0 | H18: 0 | I18: 0 | J18: 0 | K18: =ROUND(J18-I18,2) -> 0 | L18: =IF(ABS(K18)<0.005,"OK",IF(ABS(K18)<=0.05,"Rounding","REVIEW")) -> OK | M18: =ABS(C18)/SUMPRODUCT(($A$4:$A$143=A18)*ABS($C$4:$C$143)) -> 9.3925813e-05 | N18: =E18/SUMIFS($E$4:$E$143,$A$4:$A$143,A18) -> 0.0015229973 | O18: =IF(AND(ABS(ROUND(M18,2)-D18)<0.0051,ABS(ROUND(N18,2)-F18)<0.0051),"OK","REVIEW") -> OK
A19: MASTERCARD | B19: MC-DOMESTIC MERIT III (DB) | C19: 38236.77 | D19: 0.01 | E19: 163 | F19: 0.05 | G19: 0.0105 | H19: 0.15 | I19: -425.96 | J19: =-ROUND(C19*G19+E19*H19,2) -> -425.94 | K19: =ROUND(J19-I19,2) -> 0.02 | L19: =IF(ABS(K19)<0.005,"OK",IF(ABS(K19)<=0.05,"Rounding","REVIEW")) -> Rounding | M19: =ABS(C19)/SUMPRODUCT(($A$4:$A$143=A19)*ABS($C$4:$C$143)) -> 0.013915916 | N19: =E19/SUMIFS($E$4:$E$143,$A$4:$A$143,A19) -> 0.049649711 | O19: =IF(AND(ABS(ROUND(M19,2)-D19)<0.0051,ABS(ROUND(N19,2)-F19)<0.0051),"OK","REVIEW") -> OK
A20: MASTERCARD | B20: MC-BUS LEVEL 3 DATA RATE I | C20: 29838.89 | D20: 0.01 | E20: 5 | F20: 0 | G20: 0.0285 | H20: 0.1 | I20: -850.91 | J20: =-ROUND(C20*G20+E20*H20,2) -> -850.91 | K20: =ROUND(J20-I20,2) -> 0 | L20: =IF(ABS(K20)<0.005,"OK",IF(ABS(K20)<=0.05,"Rounding","REVIEW")) -> OK | M20: =ABS(C20)/SUMPRODUCT(($A$4:$A$143=A20)*ABS($C$4:$C$143)) -> 0.010859586 | N20: =E20/SUMIFS($E$4:$E$143,$A$4:$A$143,A20) -> 0.0015229973 | O20: =IF(AND(ABS(ROUND(M20,2)-D20)<0.0051,ABS(ROUND(N20,2)-F20)<0.0051),"OK","REVIEW") -> OK
A21: MASTERCARD | B21: MC-COMM DATA RATE II BUS (DB) | C21: 185741.8 | D21: 0.07 | E21: 284 | F21: 0.09 | G21: 0.021 | H21: 0.1 | I21: -3928.98 | J21: =-ROUND(C21*G21+E21*H21,2) -> -3928.98 | K21: =ROUND(J21-I21,2) -> 0 | L21: =IF(ABS(K21)<0.005,"OK",IF(ABS(K21)<=0.05,"Rounding","REVIEW")) -> OK | M21: =ABS(C21)/SUMPRODUCT(($A$4:$A$143=A21)*ABS($C$4:$C$143)) -> 0.067598999 | N21: =E21/SUMIFS($E$4:$E$143,$A$4:$A$143,A21) -> 0.086506244 | O21: =IF(AND(ABS(ROUND(M21,2)-D21)<0.0051,ABS(ROUND(N21,2)-F21)<0.0051),"OK","REVIEW") -> OK
A22: MASTERCARD | B22: MC-WRLD ELITE SMALL TICKET CNP | C22: 2.42 | D22: 0 | E22: 1 | F22: 0 | G22: 0.026 | H22: 0.02 | I22: -0.08 | J22: =-ROUND(C22*G22+E22*H22,2) -> -0.08 | K22: =ROUND(J22-I22,2) -> 0 | L22: =IF(ABS(K22)<0.005,"OK",IF(ABS(K22)<=0.05,"Rounding","REVIEW")) -> OK | M22: =ABS(C22)/SUMPRODUCT(($A$4:$A$143=A22)*ABS($C$4:$C$143)) -> 8.8073647e-07 | N22: =E22/SUMIFS($E$4:$E$143,$A$4:$A$143,A22) -> 0.00030459945 | O22: =IF(AND(ABS(ROUND(M22,2)-D22)<0.0051,ABS(ROUND(N22,2)-F22)<0.0051),"OK","REVIEW") -> OK
A23: MASTERCARD | B23: MC-REGULATED W FRD REFUNDS | C23: -14989.23 | D23: 0.01 | E23: 43 | F23: 0.01 | G23: 0 | H23: 0 | I23: 0 | J23: 0 | K23: =ROUND(J23-I23,2) -> 0 | L23: =IF(ABS(K23)<0.005,"OK",IF(ABS(K23)<=0.05,"Rounding","REVIEW")) -> OK | M23: =ABS(C23)/SUMPRODUCT(($A$4:$A$143=A23)*ABS($C$4:$C$143)) -> 0.0054551907 | N23: =E23/SUMIFS($E$4:$E$143,$A$4:$A$143,A23) -> 0.013097776 | O23: =IF(AND(ABS(ROUND(M23,2)-D23)<0.0051,ABS(ROUND(N23,2)-F23)<0.0051),"OK","REVIEW") -> OK
A24: MASTERCARD | B24: MC-CORP DATA RATE I (US) PUR | C24: 115871.6 | D24: 0.04 | E24: 56 | F24: 0.02 | G24: 0.027 | H24: 0.1 | I24: -3134.14 | J24: =-ROUND(C24*G24+E24*H24,2) -> -3134.13 | K24: =ROUND(J24-I24,2) -> 0.01 | L24: =IF(ABS(K24)<0.005,"OK",IF(ABS(K24)<=0.05,"Rounding","REVIEW")) -> Rounding | M24: =ABS(C24)/SUMPRODUCT(($A$4:$A$143=A24)*ABS($C$4:$C$143)) -> 0.04217039 | N24: =E24/SUMIFS($E$4:$E$143,$A$4:$A$143,A24) -> 0.017057569 | O24: =IF(AND(ABS(ROUND(M24,2)-D24)<0.0051,ABS(ROUND(N24,2)-F24)<0.0051),"OK","REVIEW") -> OK
A25: MASTERCARD | B25: MC-DOMESTIC MERIT I | C25: 6647.78 | D25: 0 | E25: 3 | F25: 0 | G25: 0.0195 | H25: 0.1 | I25: -129.93 | J25: =-ROUND(C25*G25+E25*H25,2) -> -129.93 | K25: =ROUND(J25-I25,2) -> 0 | L25: =IF(ABS(K25)<0.005,"OK",IF(ABS(K25)<=0.05,"Rounding","REVIEW")) -> OK | M25: =ABS(C25)/SUMPRODUCT(($A$4:$A$143=A25)*ABS($C$4:$C$143)) -> 0.0024193976 | N25: =E25/SUMIFS($E$4:$E$143,$A$4:$A$143,A25) -> 0.00091379836 | O25: =IF(AND(ABS(ROUND(M25,2)-D25)<0.0051,ABS(ROUND(N25,2)-F25)<0.0051),"OK","REVIEW") -> OK
A26: MASTERCARD | B26: MC-BUS LEVEL 2 DATA RATE II | C26: 8882.1 | D26: 0 | E26: 15 | F26: 0 | G26: 0.0205 | H26: 0.1 | I26: -183.58 | J26: =-ROUND(C26*G26+E26*H26,2) -> -183.58 | K26: =ROUND(J26-I26,2) -> 0 | L26: =IF(ABS(K26)<0.005,"OK",IF(ABS(K26)<=0.05,"Rounding","REVIEW")) -> OK | M26: =ABS(C26)/SUMPRODUCT(($A$4:$A$143=A26)*ABS($C$4:$C$143)) -> 0.0032325576 | N26: =E26/SUMIFS($E$4:$E$143,$A$4:$A$143,A26) -> 0.0045689918 | O26: =IF(AND(ABS(ROUND(M26,2)-D26)<0.0051,ABS(ROUND(N26,2)-F26)<0.0051),"OK","REVIEW") -> OK
A27: MASTERCARD | B27: MC-HIGH VAL MERIT III BASE | C27: 42221.25 | D27: 0.02 | E27: 85 | F27: 0.03 | G27: 0.023 | H27: 0.1 | I27: -979.6 | J27: =-ROUND(C27*G27+E27*H27,2) -> -979.59 | K27: =ROUND(J27-I27,2) -> 0.01 | L27: =IF(ABS(K27)<0.005,"OK",IF(ABS(K27)<=0.05,"Rounding","REVIEW")) -> Rounding | M27: =ABS(C27)/SUMPRODUCT(($A$4:$A$143=A27)*ABS($C$4:$C$143)) -> 0.015366031 | N27: =E27/SUMIFS($E$4:$E$143,$A$4:$A$143,A27) -> 0.025890953 | O27: =IF(AND(ABS(ROUND(M27,2)-D27)<0.0051,ABS(ROUND(N27,2)-F27)<0.0051),"OK","REVIEW") -> OK
A28: MASTERCARD | B28: MC-WORLD ELITE MERIT III | C28: 206345.15 | D28: 0.08 | E28: 347 | F28: 0.11 | G28: 0.023 | H28: 0.1 | I28: -4780.63 | J28: =-ROUND(C28*G28+E28*H28,2) -> -4780.64 | K28: =ROUND(J28-I28,2) -> -0.01 | L28: =IF(ABS(K28)<0.005,"OK",IF(ABS(K28)<=0.05,"Rounding","REVIEW")) -> Rounding | M28: =ABS(C28)/SUMPRODUCT(($A$4:$A$143=A28)*ABS($C$4:$C$143)) -> 0.075097396 | N28: =E28/SUMIFS($E$4:$E$143,$A$4:$A$143,A28) -> 0.10569601 | O28: =IF(AND(ABS(ROUND(M28,2)-D28)<0.0051,ABS(ROUND(N28,2)-F28)<0.0051),"OK","REVIEW") -> OK
A29: MASTERCARD | B29: MC-WORLDCARD MERIT I | C29: 9937.56 | D29: 0 | E29: 10 | F29: 0 | G29: 0.022 | H29: 0.1 | I29: -219.63 | J29: =-ROUND(C29*G29+E29*H29,2) -> -219.63 | K29: =ROUND(J29-I29,2) -> 0 | L29: =IF(ABS(K29)<0.005,"OK",IF(ABS(K29)<=0.05,"Rounding","REVIEW")) -> OK | M29: =ABS(C29)/SUMPRODUCT(($A$4:$A$143=A29)*ABS($C$4:$C$143)) -> 0.0036166824 | N29: =E29/SUMIFS($E$4:$E$143,$A$4:$A$143,A29) -> 0.0030459945 | O29: =IF(AND(ABS(ROUND(M29,2)-D29)<0.0051,ABS(ROUND(N29,2)-F29)<0.0051),"OK","REVIEW") -> OK
A30: MASTERCARD | B30: MC-DOMESTIC MERIT I (DB) | C30: 46790.84 | D30: 0.02 | E30: 39 | F30: 0.01 | G30: 0.0165 | H30: 0.15 | I30: -777.91 | J30: =-ROUND(C30*G30+E30*H30,2) -> -777.9 | K30: =ROUND(J30-I30,2) -> 0.01 | L30: =IF(ABS(K30)<0.005,"OK",IF(ABS(K30)<=0.05,"Rounding","REVIEW")) -> Rounding | M30: =ABS(C30)/SUMPRODUCT(($A$4:$A$143=A30)*ABS($C$4:$C$143)) -> 0.017029091 | N30: =E30/SUMIFS($E$4:$E$143,$A$4:$A$143,A30) -> 0.011879379 | O30: =IF(AND(ABS(ROUND(M30,2)-D30)<0.0051,ABS(ROUND(N30,2)-F30)<0.0051),"OK","REVIEW") -> OK
A31: MASTERCARD | B31: MC-REG CONSM WFRAUD ADJ MC(DB) | C31: 27797.82 | D31: 0.01 | E31: 48 | F31: 0.01 | G31: 0.0005 | H31: 0.22 | I31: -24.45 | J31: =-ROUND(C31*G31+E31*H31,2) -> -24.46 | K31: =ROUND(J31-I31,2) -> -0.01 | L31: =IF(ABS(K31)<0.005,"OK",IF(ABS(K31)<=0.05,"Rounding","REVIEW")) -> Rounding | M31: =ABS(C31)/SUMPRODUCT(($A$4:$A$143=A31)*ABS($C$4:$C$143)) -> 0.010116758 | N31: =E31/SUMIFS($E$4:$E$143,$A$4:$A$143,A31) -> 0.014620774 | O31: =IF(AND(ABS(ROUND(M31,2)-D31)<0.0051,ABS(ROUND(N31,2)-F31)<0.0051),"OK","REVIEW") -> OK
A32: MASTERCARD | B32: MC-CORP DATA RATE II (US) BUS | C32: 27060.19 | D32: 0.01 | E32: 46 | F32: 0.01 | G32: 0.019 | H32: 0.1 | I32: -518.75 | J32: =-ROUND(C32*G32+E32*H32,2) -> -518.74 | K32: =ROUND(J32-I32,2) -> 0.01 | L32: =IF(ABS(K32)<0.005,"OK",IF(ABS(K32)<=0.05,"Rounding","REVIEW")) -> Rounding | M32: =ABS(C32)/SUMPRODUCT(($A$4:$A$143=A32)*ABS($C$4:$C$143)) -> 0.0098483042 | N32: =E32/SUMIFS($E$4:$E$143,$A$4:$A$143,A32) -> 0.014011575 | O32: =IF(AND(ABS(ROUND(M32,2)-D32)<0.0051,ABS(ROUND(N32,2)-F32)<0.0051),"OK","REVIEW") -> OK
A33: MASTERCARD | B33: MC-COM DATA RATE I FLT NFUEL | C33: 36756.24 | D33: 0.01 | E33: 14 | F33: 0 | G33: 0.027 | H33: 0.1 | I33: -993.8 | J33: =-ROUND(C33*G33+E33*H33,2) -> -993.82 | K33: =ROUND(J33-I33,2) -> -0.02 | L33: =IF(ABS(K33)<0.005,"OK",IF(ABS(K33)<=0.05,"Rounding","REVIEW")) -> Rounding | M33: =ABS(C33)/SUMPRODUCT(($A$4:$A$143=A33)*ABS($C$4:$C$143)) -> 0.013377091 | N33: =E33/SUMIFS($E$4:$E$143,$A$4:$A$143,A33) -> 0.0042643923 | O33: =IF(AND(ABS(ROUND(M33,2)-D33)<0.0051,ABS(ROUND(N33,2)-F33)<0.0051),"OK","REVIEW") -> OK
A34: MASTERCARD | B34: MC-BUS LEVEL 4 DATA RATE II | C34: 127286.64 | D34: 0.05 | E34: 120 | F34: 0.04 | G34: 0.022 | H34: 0.1 | I34: -2812.33 | J34: =-ROUND(C34*G34+E34*H34,2) -> -2812.31 | K34: =ROUND(J34-I34,2) -> 0.02 | L34: =IF(ABS(K34)<0.005,"OK",IF(ABS(K34)<=0.05,"Rounding","REVIEW")) -> Rounding | M34: =ABS(C34)/SUMPRODUCT(($A$4:$A$143=A34)*ABS($C$4:$C$143)) -> 0.046324787 | N34: =E34/SUMIFS($E$4:$E$143,$A$4:$A$143,A34) -> 0.036551934 | O34: =IF(AND(ABS(ROUND(M34,2)-D34)<0.0051,ABS(ROUND(N34,2)-F34)<0.0051),"OK","REVIEW") -> OK
A35: MASTERCARD | B35: MC-CORP DATA RATE II (US) CORP | C35: 14.43 | D35: 0 | E35: 1 | F35: 0 | G35: 0.025 | H35: 0.1 | I35: -0.46 | J35: =-ROUND(C35*G35+E35*H35,2) -> -0.46 | K35: =ROUND(J35-I35,2) -> 0 | L35: =IF(ABS(K35)<0.005,"OK",IF(ABS(K35)<=0.05,"Rounding","REVIEW")) -> OK | M35: =ABS(C35)/SUMPRODUCT(($A$4:$A$143=A35)*ABS($C$4:$C$143)) -> 5.2516641e-06 | N35: =E35/SUMIFS($E$4:$E$143,$A$4:$A$143,A35) -> 0.00030459945 | O35: =IF(AND(ABS(ROUND(M35,2)-D35)<0.0051,ABS(ROUND(N35,2)-F35)<0.0051),"OK","REVIEW") -> OK
... A39: MASTERCARD | B39: MC-MERIT III (PP) | C39: 185.6 | D39: 0 | E39: 1 | F39: 0 | G39: 0.0115 | H39: 0.15 | I39: -2.28 | J39: =-ROUND(C39*G39+E39*H39,2) -> -2.28 | K39: =ROUND(J39-I39,2) -> 0 | L39: =IF(ABS(K39)<0.005,"OK",IF(ABS(K39)<=0.05,"Rounding","REVIEW")) -> OK | M39: =ABS(C39)/SUMPRODUCT(($A$4:$A$143=A39)*ABS($C$4:$C$143)) -> 6.7547392e-05 | N39: =E39/SUMIFS($E$4:$E$143,$A$4:$A$143,A39) -> 0.00030459945 | O39: =IF(AND(ABS(ROUND(M39,2)-D39)<0.0051,ABS(ROUND(N39,2)-F39)<0.0051),"OK","REVIEW") -> OK
A40: MASTERCARD | B40: MC-CONSUMER CREDIT REFUND 3 | C40: -31582.84 | D40: 0.01 | E40: 59 | F40: 0.02 | G40: 0 | H40: 0 | I40: 0 | J40: 0 | K40: =ROUND(J40-I40,2) -> 0 | L40: =IF(ABS(K40)<0.005,"OK",IF(ABS(K40)<=0.05,"Rounding","REVIEW")) -> OK | M40: =ABS(C40)/SUMPRODUCT(($A$4:$A$143=A40)*ABS($C$4:$C$143)) -> 0.011494281 | N40: =E40/SUMIFS($E$4:$E$143,$A$4:$A$143,A40) -> 0.017971368 | O40: =IF(AND(ABS(ROUND(M40,2)-D40)<0.0051,ABS(ROUND(N40,2)-F40)<0.0051),"OK","REVIEW") -> OK
A41: MASTERCARD | B41: MC-COMML DATA RT II FLT NONFL | C41: 48256.91 | D41: 0.02 | E41: 37 | F41: 0.01 | G41: 0.025 | H41: 0.1 | I41: -1210.13 | J41: =-ROUND(C41*G41+E41*H41,2) -> -1210.12 | K41: =ROUND(J41-I41,2) -> 0.01 | L41: =IF(ABS(K41)<0.005,"OK",IF(ABS(K41)<=0.05,"Rounding","REVIEW")) -> Rounding | M41: =ABS(C41)/SUMPRODUCT(($A$4:$A$143=A41)*ABS($C$4:$C$143)) -> 0.017562653 | N41: =E41/SUMIFS($E$4:$E$143,$A$4:$A$143,A41) -> 0.01127018 | O41: =IF(AND(ABS(ROUND(M41,2)-D41)<0.0051,ABS(ROUND(N41,2)-F41)<0.0051),"OK","REVIEW") -> OK
A42: MASTERCARD | B42: MC-WORLD SMALL TICKET CP | C42: 3.51 | D42: 0 | E42: 1 | F42: 0 | G42: 0.019 | H42: 0.02 | I42: -0.09 | J42: =-ROUND(C42*G42+E42*H42,2) -> -0.09 | K42: =ROUND(J42-I42,2) -> 0 | L42: =IF(ABS(K42)<0.005,"OK",IF(ABS(K42)<=0.05,"Rounding","REVIEW")) -> OK | M42: =ABS(C42)/SUMPRODUCT(($A$4:$A$143=A42)*ABS($C$4:$C$143)) -> 1.2774318e-06 | N42: =E42/SUMIFS($E$4:$E$143,$A$4:$A$143,A42) -> 0.00030459945 | O42: =IF(AND(ABS(ROUND(M42,2)-D42)<0.0051,ABS(ROUND(N42,2)-F42)<0.0051),"OK","REVIEW") -> OK
A43: MASTERCARD | B43: MC-WORLD ELITE MERIT I | C43: 272399.09 | D43: 0.1 | E43: 147 | F43: 0.04 | G43: 0.026 | H43: 0.1 | I43: -7097.09 | J43: =-ROUND(C43*G43+E43*H43,2) -> -7097.08 | K43: =ROUND(J43-I43,2) -> 0.01 | L43: =IF(ABS(K43)<0.005,"OK",IF(ABS(K43)<=0.05,"Rounding","REVIEW")) -> Rounding | M43: =ABS(C43)/SUMPRODUCT(($A$4:$A$143=A43)*ABS($C$4:$C$143)) -> 0.099137112 | N43: =E43/SUMIFS($E$4:$E$143,$A$4:$A$143,A43) -> 0.044776119 | O43: =IF(AND(ABS(ROUND(M43,2)-D43)<0.0051,ABS(ROUND(N43,2)-F43)<0.0051),"OK","REVIEW") -> OK
A44: MASTERCARD | B44: MC-HIGH VAL MERIT I | C44: 47275.18 | D44: 0.02 | E44: 22 | F44: 0.01 | G44: 0.026 | H44: 0.1 | I44: -1231.37 | J44: =-ROUND(C44*G44+E44*H44,2) -> -1231.35 | K44: =ROUND(J44-I44,2) -> 0.02 | L44: =IF(ABS(K44)<0.005,"OK",IF(ABS(K44)<=0.05,"Rounding","REVIEW")) -> Rounding | M44: =ABS(C44)/SUMPRODUCT(($A$4:$A$143=A44)*ABS($C$4:$C$143)) -> 0.017205362 | N44: =E44/SUMIFS($E$4:$E$143,$A$4:$A$143,A44) -> 0.0067011879 | O44: =IF(AND(ABS(ROUND(M44,2)-D44)<0.0051,ABS(ROUND(N44,2)-F44)<0.0051),"OK","REVIEW") -> OK
A45: MASTERCARD | B45: MC-DOMESTIC MERIT III | C45: 9460.5 | D45: 0 | E45: 31 | F45: 0.01 | G45: 0.0165 | H45: 0.1 | I45: -159.19 | J45: =-ROUND(C45*G45+E45*H45,2) -> -159.2 | K45: =ROUND(J45-I45,2) -> -0.01 | L45: =IF(ABS(K45)<0.005,"OK",IF(ABS(K45)<=0.05,"Rounding","REVIEW")) -> Rounding | M45: =ABS(C45)/SUMPRODUCT(($A$4:$A$143=A45)*ABS($C$4:$C$143)) -> 0.0034430609 | N45: =E45/SUMIFS($E$4:$E$143,$A$4:$A$143,A45) -> 0.009442583 | O45: =IF(AND(ABS(ROUND(M45,2)-D45)<0.0051,ABS(ROUND(N45,2)-F45)<0.0051),"OK","REVIEW") -> OK
A46: MASTERCARD | B46: MC-WORLD HV SMALL TICKET CP | C46: 3.35 | D46: 0 | E46: 1 | F46: 0 | G46: 0.023 | H46: 0.02 | I46: -0.1 | J46: =-ROUND(C46*G46+E46*H46,2) -> -0.1 | K46: =ROUND(J46-I46,2) -> 0 | L46: =IF(ABS(K46)<0.005,"OK",IF(ABS(K46)<=0.05,"Rounding","REVIEW")) -> OK | M46: =ABS(C46)/SUMPRODUCT(($A$4:$A$143=A46)*ABS($C$4:$C$143)) -> 1.2192013e-06 | N46: =E46/SUMIFS($E$4:$E$143,$A$4:$A$143,A46) -> 0.00030459945 | O46: =IF(AND(ABS(ROUND(M46,2)-D46)<0.0051,ABS(ROUND(N46,2)-F46)<0.0051),"OK","REVIEW") -> OK
A47: MASTERCARD | B47: MC-ENHANCED MERIT I | C47: 3042.74 | D47: 0 | E47: 4 | F47: 0 | G47: 0.021 | H47: 0.1 | I47: -64.29 | J47: =-ROUND(C47*G47+E47*H47,2) -> -64.3 | K47: =ROUND(J47-I47,2) -> -0.01 | L47: =IF(ABS(K47)<0.005,"OK",IF(ABS(K47)<=0.05,"Rounding","REVIEW")) -> Rounding | M47: =ABS(C47)/SUMPRODUCT(($A$4:$A$143=A47)*ABS($C$4:$C$143)) -> 0.0011073769 | N47: =E47/SUMIFS($E$4:$E$143,$A$4:$A$143,A47) -> 0.0012183978 | O47: =IF(AND(ABS(ROUND(M47,2)-D47)<0.0051,ABS(ROUND(N47,2)-F47)<0.0051),"OK","REVIEW") -> OK
A48: MASTERCARD | B48: MC-REG INCENT FRF ADJ POS (DB) | C48: 24861 | D48: 0.01 | E48: 127 | F48: 0.04 | G48: 0.0005 | H48: 0.22 | I48: -40.37 | J48: =-ROUND(C48*G48+E48*H48,2) -> -40.37 | K48: =ROUND(J48-I48,2) -> 0 | L48: =IF(ABS(K48)<0.005,"OK",IF(ABS(K48)<=0.05,"Rounding","REVIEW")) -> OK | M48: =ABS(C48)/SUMPRODUCT(($A$4:$A$143=A48)*ABS($C$4:$C$143)) -> 0.0090479294 | N48: =E48/SUMIFS($E$4:$E$143,$A$4:$A$143,A48) -> 0.03868413 | O48: =IF(AND(ABS(ROUND(M48,2)-D48)<0.0051,ABS(ROUND(N48,2)-F48)<0.0051),"OK","REVIEW") -> OK
A49: MASTERCARD | B49: MC-BUS LEVEL 3 DATA RATE II | C49: 33156.09 | D49: 0.01 | E49: 50 | F49: 0.02 | G49: 0.021 | H49: 0.1 | I49: -701.28 | J49: =-ROUND(C49*G49+E49*H49,2) -> -701.28 | K49: =ROUND(J49-I49,2) -> 0 | L49: =IF(ABS(K49)<0.005,"OK",IF(ABS(K49)<=0.05,"Rounding","REVIEW")) -> OK | M49: =ABS(C49)/SUMPRODUCT(($A$4:$A$143=A49)*ABS($C$4:$C$143)) -> 0.01206685 | N49: =E49/SUMIFS($E$4:$E$143,$A$4:$A$143,A49) -> 0.015229973 | O49: =IF(AND(ABS(ROUND(M49,2)-D49)<0.0051,ABS(ROUND(N49,2)-F49)<0.0051),"OK","REVIEW") -> OK
A50: VISA | B50: VI-CPS CNP (DB) | C50: 35840.95 | D50: 0.01 | E50: 44 | F50: 0.01 | G50: 0.0165 | H50: 0.15 | I50: -597.98 | J50: =-ROUND(C50*G50+E50*H50,2) -> -597.98 | K50: =ROUND(J50-I50,2) -> 0 | L50: =IF(ABS(K50)<0.005,"OK",IF(ABS(K50)<=0.05,"Rounding","REVIEW")) -> OK | M50: =ABS(C50)/SUMPRODUCT(($A$4:$A$143=A50)*ABS($C$4:$C$143)) -> 0.0080701752 | N50: =E50/SUMIFS($E$4:$E$143,$A$4:$A$143,A50) -> 0.0082397004 | O50: =IF(AND(ABS(ROUND(M50,2)-D50)<0.0051,ABS(ROUND(N50,2)-F50)<0.0051),"OK","REVIEW") -> OK
A51: VISA | B51: VI-RETAIL P2 TRAD REWARD | C51: 5615.35 | D51: 0 | E51: 16 | F51: 0 | G51: 0.0165 | H51: 0.1 | I51: -94.26 | J51: =-ROUND(C51*G51+E51*H51,2) -> -94.25 | K51: =ROUND(J51-I51,2) -> 0.01 | L51: =IF(ABS(K51)<0.005,"OK",IF(ABS(K51)<=0.05,"Rounding","REVIEW")) -> Rounding | M51: =ABS(C51)/SUMPRODUCT(($A$4:$A$143=A51)*ABS($C$4:$C$143)) -> 0.0012643878 | N51: =E51/SUMIFS($E$4:$E$143,$A$4:$A$143,A51) -> 0.0029962547 | O51: =IF(AND(ABS(ROUND(M51,2)-D51)<0.0051,ABS(ROUND(N51,2)-F51)<0.0051),"OK","REVIEW") -> OK
A52: VISA | B52: VI-US REGULATED COMM (DB) | C52: 1085708.1 | D52: 0.24 | E52: 1369 | F52: 0.26 | G52: 0.0005 | H52: 0.22 | I52: -844.05 | J52: =-ROUND(C52*G52+E52*H52,2) -> -844.03 | K52: =ROUND(J52-I52,2) -> 0.02 | L52: =IF(ABS(K52)<0.005,"OK",IF(ABS(K52)<=0.05,"Rounding","REVIEW")) -> Rounding | M52: =ABS(C52)/SUMPRODUCT(($A$4:$A$143=A52)*ABS($C$4:$C$143)) -> 0.2444649 | N52: =E52/SUMIFS($E$4:$E$143,$A$4:$A$143,A52) -> 0.25636704 | O52: =IF(AND(ABS(ROUND(M52,2)-D52)<0.0051,ABS(ROUND(N52,2)-F52)<0.0051),"OK","REVIEW") -> OK
... A80: VISA | B80: VI-CORPORATE CREDIT PRODUCT 1 | C80: 1903.87 | D80: 0 | E80: 4 | F80: 0 | G80: 0.027 | H80: 0.1 | I80: -51.81 | J80: =-ROUND(C80*G80+E80*H80,2) -> -51.8 | K80: =ROUND(J80-I80,2) -> 0.01 | L80: =IF(ABS(K80)<0.005,"OK",IF(ABS(K80)<=0.05,"Rounding","REVIEW")) -> Rounding | M80: =ABS(C80)/SUMPRODUCT(($A$4:$A$143=A80)*ABS($C$4:$C$143)) -> 0.00042868742 | N80: =E80/SUMIFS($E$4:$E$143,$A$4:$A$143,A80) -> 0.00074906367 | O80: =IF(AND(ABS(ROUND(M80,2)-D80)<0.0051,ABS(ROUND(N80,2)-F80)<0.0051),"OK","REVIEW") -> OK
A81: VISA | B81: VI-CR VOUCH NGSA PURCH NON PT1 | C81: -2630.07 | D81: 0 | E81: 6 | F81: 0 | G81: 0 | H81: 0 | I81: 0 | J81: 0 | K81: =ROUND(J81-I81,2) -> 0 | L81: =IF(ABS(K81)<0.005,"OK",IF(ABS(K81)<=0.05,"Rounding","REVIEW")) -> OK | M81: =ABS(C81)/SUMPRODUCT(($A$4:$A$143=A81)*ABS($C$4:$C$143)) -> 0.00059220321 | N81: =E81/SUMIFS($E$4:$E$143,$A$4:$A$143,A81) -> 0.0011235955 | O81: =IF(AND(ABS(ROUND(M81,2)-D81)<0.0051,ABS(ROUND(N81,2)-F81)<0.0051),"OK","REVIEW") -> OK
A82: VISA | B82: VI-SERVICES INFINITE SQ | C82: 36459.17 | D82: 0.01 | E82: 28 | F82: 0.01 | G82: 0.023 | H82: 0.1 | I82: -841.36 | J82: =-ROUND(C82*G82+E82*H82,2) -> -841.36 | K82: =ROUND(J82-I82,2) -> 0 | L82: =IF(ABS(K82)<0.005,"OK",IF(ABS(K82)<=0.05,"Rounding","REVIEW")) -> OK | M82: =ABS(C82)/SUMPRODUCT(($A$4:$A$143=A82)*ABS($C$4:$C$143)) -> 0.0082093775 | N82: =E82/SUMIFS($E$4:$E$143,$A$4:$A$143,A82) -> 0.0052434457 | O82: =IF(AND(ABS(ROUND(M82,2)-D82)<0.0051,ABS(ROUND(N82,2)-F82)<0.0051),"OK","REVIEW") -> OK
A83: VISA | B83: VI-US BUS TR5 PRD 3 | C83: 28572.86 | D83: 0.01 | E83: 36 | F83: 0.01 | G83: 0.0275 | H83: 0.1 | I83: -789.36 | J83: =-ROUND(C83*G83+E83*H83,2) -> -789.35 | K83: =ROUND(J83-I83,2) -> 0.01 | L83: =IF(ABS(K83)<0.005,"OK",IF(ABS(K83)<=0.05,"Rounding","REVIEW")) -> Rounding | M83: =ABS(C83)/SUMPRODUCT(($A$4:$A$143=A83)*ABS($C$4:$C$143)) -> 0.0064336461 | N83: =E83/SUMIFS($E$4:$E$143,$A$4:$A$143,A83) -> 0.006741573 | O83: =IF(AND(ABS(ROUND(M83,2)-D83)<0.0051,ABS(ROUND(N83,2)-F83)<0.0051),"OK","REVIEW") -> OK
A84: VISA | B84: VI-US BUS TR4 PRD 2 | C84: 129611.32 | D84: 0.03 | E84: 245 | F84: 0.05 | G84: 0.022 | H84: 0.1 | I84: -2875.94 | J84: =-ROUND(C84*G84+E84*H84,2) -> -2875.95 | K84: =ROUND(J84-I84,2) -> -0.01 | L84: =IF(ABS(K84)<0.005,"OK",IF(ABS(K84)<=0.05,"Rounding","REVIEW")) -> Rounding | M84: =ABS(C84)/SUMPRODUCT(($A$4:$A$143=A84)*ABS($C$4:$C$143)) -> 0.029184105 | N84: =E84/SUMIFS($E$4:$E$143,$A$4:$A$143,A84) -> 0.04588015 | O84: =IF(AND(ABS(ROUND(M84,2)-D84)<0.0051,ABS(ROUND(N84,2)-F84)<0.0051),"OK","REVIEW") -> OK
A85: VISA | B85: VI-US BUS TIER 4 PRD 2 CEDP | C85: 23790.45 | D85: 0.01 | E85: 24 | F85: 0 | G85: 0.022 | H85: 0.1 | I85: -525.78 | J85: =-ROUND(C85*G85+E85*H85,2) -> -525.79 | K85: =ROUND(J85-I85,2) -> -0.01 | L85: =IF(ABS(K85)<0.005,"OK",IF(ABS(K85)<=0.05,"Rounding","REVIEW")) -> Rounding | M85: =ABS(C85)/SUMPRODUCT(($A$4:$A$143=A85)*ABS($C$4:$C$143)) -> 0.0053568083 | N85: =E85/SUMIFS($E$4:$E$143,$A$4:$A$143,A85) -> 0.004494382 | O85: =IF(AND(ABS(ROUND(M85,2)-D85)<0.0051,ABS(ROUND(N85,2)-F85)<0.0051),"OK","REVIEW") -> OK
A86: VISA | B86: VI-PURCH CREDIT PRD 2 CEDP | C86: 6501.82 | D86: 0 | E86: 18 | F86: 0 | G86: 0.025 | H86: 0.1 | I86: -164.34 | J86: =-ROUND(C86*G86+E86*H86,2) -> -164.35 | K86: =ROUND(J86-I86,2) -> -0.01 | L86: =IF(ABS(K86)<0.005,"OK",IF(ABS(K86)<=0.05,"Rounding","REVIEW")) -> Rounding | M86: =ABS(C86)/SUMPRODUCT(($A$4:$A$143=A86)*ABS($C$4:$C$143)) -> 0.001463991 | N86: =E86/SUMIFS($E$4:$E$143,$A$4:$A$143,A86) -> 0.0033707865 | O86: =IF(AND(ABS(ROUND(M86,2)-D86)<0.0051,ABS(ROUND(N86,2)-F86)<0.0051),"OK","REVIEW") -> OK
A87: VISA | B87: VI-US BUS TIER 5 PRD 1 CEDP | C87: 22095.2 | D87: 0 | E87: 44 | F87: 0.01 | G87: 0.0225 | H87: 0.1 | I87: -501.53 | J87: =-ROUND(C87*G87+E87*H87,2) -> -501.54 | K87: =ROUND(J87-I87,2) -> -0.01 | L87: =IF(ABS(K87)<0.005,"OK",IF(ABS(K87)<=0.05,"Rounding","REVIEW")) -> Rounding | M87: =ABS(C87)/SUMPRODUCT(($A$4:$A$143=A87)*ABS($C$4:$C$143)) -> 0.0049750951 | N87: =E87/SUMIFS($E$4:$E$143,$A$4:$A$143,A87) -> 0.0082397004 | O87: =IF(AND(ABS(ROUND(M87,2)-D87)<0.0051,ABS(ROUND(N87,2)-F87)<0.0051),"OK","REVIEW") -> OK
A88: VISA | B88: VI-US BUS TIER 3 PRD 2 CEDP | C88: 7143.77 | D88: 0 | E88: 16 | F88: 0 | G88: 0.021 | H88: 0.1 | I88: -151.61 | J88: =-ROUND(C88*G88+E88*H88,2) -> -151.62 | K88: =ROUND(J88-I88,2) -> -0.01 | L88: =IF(ABS(K88)<0.005,"OK",IF(ABS(K88)<=0.05,"Rounding","REVIEW")) -> Rounding | M88: =ABS(C88)/SUMPRODUCT(($A$4:$A$143=A88)*ABS($C$4:$C$143)) -> 0.0016085365 | N88: =E88/SUMIFS($E$4:$E$143,$A$4:$A$143,A88) -> 0.0029962547 | O88: =IF(AND(ABS(ROUND(M88,2)-D88)<0.0051,ABS(ROUND(N88,2)-F88)<0.0051),"OK","REVIEW") -> OK
A89: VISA | B89: VI-US BUS TIER 2 PRD 1 CEDP | C89: 10442.8 | D89: 0 | E89: 6 | F89: 0 | G89: 0.028 | H89: 0.1 | I89: -293 | J89: =-ROUND(C89*G89+E89*H89,2) -> -293 | K89: =ROUND(J89-I89,2) -> 0 | L89: =IF(ABS(K89)<0.005,"OK",IF(ABS(K89)<=0.05,"Rounding","REVIEW")) -> OK | M89: =ABS(C89)/SUMPRODUCT(($A$4:$A$143=A89)*ABS($C$4:$C$143)) -> 0.002351367 | N89: =E89/SUMIFS($E$4:$E$143,$A$4:$A$143,A89) -> 0.0011235955 | O89: =IF(AND(ABS(ROUND(M89,2)-D89)<0.0051,ABS(ROUND(N89,2)-F89)<0.0051),"OK","REVIEW") -> OK
A90: VISA | B90: VI-PURCHASING CREDIT PRODUCT 2 | C90: 23240.66 | D90: 0.01 | E90: 84 | F90: 0.02 | G90: 0.025 | H90: 0.1 | I90: -589.42 | J90: =-ROUND(C90*G90+E90*H90,2) -> -589.42 | K90: =ROUND(J90-I90,2) -> 0 | L90: =IF(ABS(K90)<0.005,"OK",IF(ABS(K90)<=0.05,"Rounding","REVIEW")) -> OK | M90: =ABS(C90)/SUMPRODUCT(($A$4:$A$143=A90)*ABS($C$4:$C$143)) -> 0.0052330141 | N90: =E90/SUMIFS($E$4:$E$143,$A$4:$A$143,A90) -> 0.015730337 | O90: =IF(AND(ABS(ROUND(M90,2)-D90)<0.0051,ABS(ROUND(N90,2)-F90)<0.0051),"OK","REVIEW") -> OK
A91: VISA | B91: VI-US BUS TR3 PRD 3 | C91: 6332.3 | D91: 0 | E91: 1 | F91: 0 | G91: 0.026 | H91: 0.1 | I91: -164.74 | J91: =-ROUND(C91*G91+E91*H91,2) -> -164.74 | K91: =ROUND(J91-I91,2) -> 0 | L91: =IF(ABS(K91)<0.005,"OK",IF(ABS(K91)<=0.05,"Rounding","REVIEW")) -> OK | M91: =ABS(C91)/SUMPRODUCT(($A$4:$A$143=A91)*ABS($C$4:$C$143)) -> 0.0014258208 | N91: =E91/SUMIFS($E$4:$E$143,$A$4:$A$143,A91) -> 0.00018726592 | O91: =IF(AND(ABS(ROUND(M91,2)-D91)<0.0051,ABS(ROUND(N91,2)-F91)<0.0051),"OK","REVIEW") -> OK
A92: VISA | B92: VI-CONS NON-PASS TRANS CREDIT | C92: -25967.38 | D92: 0.01 | E92: 51 | F92: 0.01 | G92: 0 | H92: 0 | I92: 0 | J92: 0 | K92: =ROUND(J92-I92,2) -> 0 | L92: =IF(ABS(K92)<0.005,"OK",IF(ABS(K92)<=0.05,"Rounding","REVIEW")) -> OK | M92: =ABS(C92)/SUMPRODUCT(($A$4:$A$143=A92)*ABS($C$4:$C$143)) -> 0.0058469797 | N92: =E92/SUMIFS($E$4:$E$143,$A$4:$A$143,A92) -> 0.0095505618 | O92: =IF(AND(ABS(ROUND(M92,2)-D92)<0.0051,ABS(ROUND(N92,2)-F92)<0.0051),"OK","REVIEW") -> OK
A93: VISA | B93: VI-CPS SMALL TICKET (PP) | C93: 17.49 | D93: 0 | E93: 2 | F93: 0 | G93: 0.016 | H93: 0.05 | I93: -0.38 | J93: =-ROUND(C93*G93+E93*H93,2) -> -0.38 | K93: =ROUND(J93-I93,2) -> 0 | L93: =IF(ABS(K93)<0.005,"OK",IF(ABS(K93)<=0.05,"Rounding","REVIEW")) -> OK | M93: =ABS(C93)/SUMPRODUCT(($A$4:$A$143=A93)*ABS($C$4:$C$143)) -> 3.9381591e-06 | N93: =E93/SUMIFS($E$4:$E$143,$A$4:$A$143,A93) -> 0.00037453184 | O93: =IF(AND(ABS(ROUND(M93,2)-D93)<0.0051,ABS(ROUND(N93,2)-F93)<0.0051),"OK","REVIEW") -> OK
A94: VISA | B94: VI-CNP P1 SIGNATURE | C94: 326.95 | D94: 0 | E94: 5 | F94: 0 | G94: 0.0205 | H94: 0.1 | I94: -7.2 | J94: =-ROUND(C94*G94+E94*H94,2) -> -7.2 | K94: =ROUND(J94-I94,2) -> 0 | L94: =IF(ABS(K94)<0.005,"OK",IF(ABS(K94)<=0.05,"Rounding","REVIEW")) -> OK | M94: =ABS(C94)/SUMPRODUCT(($A$4:$A$143=A94)*ABS($C$4:$C$143)) -> 7.3618132e-05 | N94: =E94/SUMIFS($E$4:$E$143,$A$4:$A$143,A94) -> 0.00093632959 | O94: =IF(AND(ABS(ROUND(M94,2)-D94)<0.0051,ABS(ROUND(N94,2)-F94)<0.0051),"OK","REVIEW") -> OK
A95: VISA | B95: VI-SERVICES SIGN PREF NTKN | C95: 233461.45 | D95: 0.05 | E95: 99 | F95: 0.02 | G95: 0.024 | H95: 0.1 | I95: -5612.99 | J95: =-ROUND(C95*G95+E95*H95,2) -> -5612.97 | K95: =ROUND(J95-I95,2) -> 0.02 | L95: =IF(ABS(K95)<0.005,"OK",IF(ABS(K95)<=0.05,"Rounding","REVIEW")) -> Rounding | M95: =ABS(C95)/SUMPRODUCT(($A$4:$A$143=A95)*ABS($C$4:$C$143)) -> 0.052567658 | N95: =E95/SUMIFS($E$4:$E$143,$A$4:$A$143,A95) -> 0.018539326 | O95: =IF(AND(ABS(ROUND(M95,2)-D95)<0.0051,ABS(ROUND(N95,2)-F95)<0.0051),"OK","REVIEW") -> OK
A96: VISA | B96: VI-SERVICES INFINITE SQ NTKN | C96: 37463.35 | D96: 0.01 | E96: 15 | F96: 0 | G96: 0.024 | H96: 0.1 | I96: -900.64 | J96: =-ROUND(C96*G96+E96*H96,2) -> -900.62 | K96: =ROUND(J96-I96,2) -> 0.02 | L96: =IF(ABS(K96)<0.005,"OK",IF(ABS(K96)<=0.05,"Rounding","REVIEW")) -> Rounding | M96: =ABS(C96)/SUMPRODUCT(($A$4:$A$143=A96)*ABS($C$4:$C$143)) -> 0.0084354851 | N96: =E96/SUMIFS($E$4:$E$143,$A$4:$A$143,A96) -> 0.0028089888 | O96: =IF(AND(ABS(ROUND(M96,2)-D96)<0.0051,ABS(ROUND(N96,2)-F96)<0.0051),"OK","REVIEW") -> OK
A97: VISA | B97: VI-US BUS TIER 5 PRD 1 CEDP | C97: 228931.31 | D97: 0.05 | E97: 50 | F97: 0.01 | G97: 0.03 | H97: 0.1 | I97: -6880.79 | J97: =-ROUND(C97*G97+E97*H97,2) -> -6872.94 | K97: =ROUND(J97-I97,2) -> 7.85 | L97: =IF(ABS(K97)<0.005,"OK",IF(ABS(K97)<=0.05,"Rounding","REVIEW")) -> REVIEW | M97: =ABS(C97)/SUMPRODUCT(($A$4:$A$143=A97)*ABS($C$4:$C$143)) -> 0.051547623 | N97: =E97/SUMIFS($E$4:$E$143,$A$4:$A$143,A97) -> 0.0093632959 | O97: =IF(AND(ABS(ROUND(M97,2)-D97)<0.0051,ABS(ROUND(N97,2)-F97)<0.0051),"OK","REVIEW") -> OK
A98: VISA | B98: VI-REG CONSUMER MQ (DB) | C98: 201096.92 | D98: 0.05 | E98: 158 | F98: 0.03 | G98: 0.0005 | H98: 0.22 | I98: -135.31 | J98: =-ROUND(C98*G98+E98*H98,2) -> -135.31 | K98: =ROUND(J98-I98,2) -> 0 | L98: =IF(ABS(K98)<0.005,"OK",IF(ABS(K98)<=0.05,"Rounding","REVIEW")) -> OK | M98: =ABS(C98)/SUMPRODUCT(($A$4:$A$143=A98)*ABS($C$4:$C$143)) -> 0.045280256 | N98: =E98/SUMIFS($E$4:$E$143,$A$4:$A$143,A98) -> 0.029588015 | O98: =IF(AND(ABS(ROUND(M98,2)-D98)<0.0051,ABS(ROUND(N98,2)-F98)<0.0051),"OK","REVIEW") -> OK
A99: VISA | B99: VI-US BUS TR2 PRD 1 | C99: 24951.9 | D99: 0.01 | E99: 8 | F99: 0 | G99: 0.028 | H99: 0.1 | I99: -699.45 | J99: =-ROUND(C99*G99+E99*H99,2) -> -699.45 | K99: =ROUND(J99-I99,2) -> 0 | L99: =IF(ABS(K99)<0.005,"OK",IF(ABS(K99)<=0.05,"Rounding","REVIEW")) -> OK | M99: =ABS(C99)/SUMPRODUCT(($A$4:$A$143=A99)*ABS($C$4:$C$143)) -> 0.0056183278 | N99: =E99/SUMIFS($E$4:$E$143,$A$4:$A$143,A99) -> 0.0014981273 | O99: =IF(AND(ABS(ROUND(M99,2)-D99)<0.0051,ABS(ROUND(N99,2)-F99)<0.0051),"OK","REVIEW") -> OK
A100: VISA | B100: VI-SERVICES SIGNATURE | C100: 31453.78 | D100: 0.01 | E100: 41 | F100: 0.01 | G100: 0.0185 | H100: 0.1 | I100: -586 | J100: =-ROUND(C100*G100+E100*H100,2) -> -585.99 | K100: =ROUND(J100-I100,2) -> 0.01 | L100: =IF(ABS(K100)<0.005,"OK",IF(ABS(K100)<=0.05,"Rounding","REVIEW")) -> Rounding | M100: =ABS(C100)/SUMPRODUCT(($A$4:$A$143=A100)*ABS($C$4:$C$143)) -> 0.0070823322 | N100: =E100/SUMIFS($E$4:$E$143,$A$4:$A$143,A100) -> 0.0076779026 | O100: =IF(AND(ABS(ROUND(M100,2)-D100)<0.0051,ABS(ROUND(N100,2)-F100)<0.0051),"OK","REVIEW") -> OK
A101: VISA | B101: VI-US REGULATED (DB) | C101: 195253.9 | D101: 0.04 | E101: 424 | F101: 0.08 | G101: 0.0005 | H101: 0.22 | I101: -190.92 | J101: =-ROUND(C101*G101+E101*H101,2) -> -190.91 | K101: =ROUND(J101-I101,2) -> 0.01 | L101: =IF(ABS(K101)<0.005,"OK",IF(ABS(K101)<=0.05,"Rounding","REVIEW")) -> Rounding | M101: =ABS(C101)/SUMPRODUCT(($A$4:$A$143=A101)*ABS($C$4:$C$143)) -> 0.043964604 | N101: =E101/SUMIFS($E$4:$E$143,$A$4:$A$143,A101) -> 0.079400749 | O101: =IF(AND(ABS(ROUND(M101,2)-D101)<0.0051,ABS(ROUND(N101,2)-F101)<0.0051),"OK","REVIEW") -> OK
A102: VISA | B102: VI-GSA LARGE TICKET | C102: 7284.52 | D102: 0 | E102: 1 | F102: 0 | G102: 0.012 | H102: 39 | I102: -126.41 | J102: =-ROUND(C102*G102+E102*H102,2) -> -126.41 | K102: =ROUND(J102-I102,2) -> 0 | L102: =IF(ABS(K102)<0.005,"OK",IF(ABS(K102)<=0.05,"Rounding","REVIEW")) -> OK | M102: =ABS(C102)/SUMPRODUCT(($A$4:$A$143=A102)*ABS($C$4:$C$143)) -> 0.0016402286 | N102: =E102/SUMIFS($E$4:$E$143,$A$4:$A$143,A102) -> 0.00018726592 | O102: =IF(AND(ABS(ROUND(M102,2)-D102)<0.0051,ABS(ROUND(N102,2)-F102)<0.0051),"OK","REVIEW") -> OK
A103: VISA | B103: VI-RETAIL P2 INFINITE SQ | C103: 1205.07 | D103: 0 | E103: 26 | F103: 0 | G103: 0.023 | H103: 0.1 | I103: -30.31 | J103: =-ROUND(C103*G103+E103*H103,2) -> -30.32 | K103: =ROUND(J103-I103,2) -> -0.01 | L103: =IF(ABS(K103)<0.005,"OK",IF(ABS(K103)<=0.05,"Rounding","REVIEW")) -> Rounding | M103: =ABS(C103)/SUMPRODUCT(($A$4:$A$143=A103)*ABS($C$4:$C$143)) -> 0.00027134119 | N103: =E103/SUMIFS($E$4:$E$143,$A$4:$A$143,A103) -> 0.0048689139 | O103: =IF(AND(ABS(ROUND(M103,2)-D103)<0.0051,ABS(ROUND(N103,2)-F103)<0.0051),"OK","REVIEW") -> OK
A104: VISA | B104: VI-CORPORATE CREDIT PRODUCT 2 | C104: 5539.86 | D104: 0 | E104: 9 | F104: 0 | G104: 0.025 | H104: 0.1 | I104: -139.39 | J104: =-ROUND(C104*G104+E104*H104,2) -> -139.4 | K104: =ROUND(J104-I104,2) -> -0.01 | L104: =IF(ABS(K104)<0.005,"OK",IF(ABS(K104)<=0.05,"Rounding","REVIEW")) -> Rounding | M104: =ABS(C104)/SUMPRODUCT(($A$4:$A$143=A104)*ABS($C$4:$C$143)) -> 0.00124739 | N104: =E104/SUMIFS($E$4:$E$143,$A$4:$A$143,A104) -> 0.0016853933 | O104: =IF(AND(ABS(ROUND(M104,2)-D104)<0.0051,ABS(ROUND(N104,2)-F104)<0.0051),"OK","REVIEW") -> OK
... A106: VISA | B106: VI-RETAIL P2 SIGN PREFERRED | C106: 10360.71 | D106: 0 | E106: 186 | F106: 0.03 | G106: 0.021 | H106: 0.1 | I106: -236.16 | J106: =-ROUND(C106*G106+E106*H106,2) -> -236.17 | K106: =ROUND(J106-I106,2) -> -0.01 | L106: =IF(ABS(K106)<0.005,"OK",IF(ABS(K106)<=0.05,"Rounding","REVIEW")) -> Rounding | M106: =ABS(C106)/SUMPRODUCT(($A$4:$A$143=A106)*ABS($C$4:$C$143)) -> 0.0023328831 | N106: =E106/SUMIFS($E$4:$E$143,$A$4:$A$143,A106) -> 0.034831461 | O106: =IF(AND(ABS(ROUND(M106,2)-D106)<0.0051,ABS(ROUND(N106,2)-F106)<0.0051),"OK","REVIEW") -> OK
A107: VISA | B107: VI-CRVCHR DEBIT CARD (DB) | C107: -62577.22 | D107: 0.01 | E107: 143 | F107: 0.03 | G107: 0 | H107: 0 | I107: 0 | J107: 0 | K107: =ROUND(J107-I107,2) -> 0 | L107: =IF(ABS(K107)<0.005,"OK",IF(ABS(K107)<=0.05,"Rounding","REVIEW")) -> OK | M107: =ABS(C107)/SUMPRODUCT(($A$4:$A$143=A107)*ABS($C$4:$C$143)) -> 0.014090283 | N107: =E107/SUMIFS($E$4:$E$143,$A$4:$A$143,A107) -> 0.026779026 | O107: =IF(AND(ABS(ROUND(M107,2)-D107)<0.0051,ABS(ROUND(N107,2)-F107)<0.0051),"OK","REVIEW") -> OK
A108: VISA | B108: VI-CPS/RETAIL ALL OTHER (DB) | C108: 48717.21 | D108: 0.01 | E108: 162 | F108: 0.03 | G108: 0.008 | H108: 0.15 | I108: -414 | J108: =-ROUND(C108*G108+E108*H108,2) -> -414.04 | K108: =ROUND(J108-I108,2) -> -0.04 | L108: =IF(ABS(K108)<0.005,"OK",IF(ABS(K108)<=0.05,"Rounding","REVIEW")) -> Rounding | M108: =ABS(C108)/SUMPRODUCT(($A$4:$A$143=A108)*ABS($C$4:$C$143)) -> 0.010969475 | N108: =E108/SUMIFS($E$4:$E$143,$A$4:$A$143,A108) -> 0.030337079 | O108: =IF(AND(ABS(ROUND(M108,2)-D108)<0.0051,ABS(ROUND(N108,2)-F108)<0.0051),"OK","REVIEW") -> OK
A109: VISA | B109: VI-US BUS TR4 PRD 1 | C109: 179297.41 | D109: 0.04 | E109: 137 | F109: 0.03 | G109: 0.0295 | H109: 0.1 | I109: -5302.98 | J109: =-ROUND(C109*G109+E109*H109,2) -> -5302.97 | K109: =ROUND(J109-I109,2) -> 0.01 | L109: =IF(ABS(K109)<0.005,"OK",IF(ABS(K109)<=0.05,"Rounding","REVIEW")) -> Rounding | M109: =ABS(C109)/SUMPRODUCT(($A$4:$A$143=A109)*ABS($C$4:$C$143)) -> 0.04037174 | N109: =E109/SUMIFS($E$4:$E$143,$A$4:$A$143,A109) -> 0.025655431 | O109: =IF(AND(ABS(ROUND(M109,2)-D109)<0.0051,ABS(ROUND(N109,2)-F109)<0.0051),"OK","REVIEW") -> OK
A110: VISA | B110: VI-CPS SMALL TICKET (DB) | C110: 215.7 | D110: 0 | E110: 20 | F110: 0 | G110: 0.0155 | H110: 0.04 | I110: -4.15 | J110: =-ROUND(C110*G110+E110*H110,2) -> -4.14 | K110: =ROUND(J110-I110,2) -> 0.01 | L110: =IF(ABS(K110)<0.005,"OK",IF(ABS(K110)<=0.05,"Rounding","REVIEW")) -> Rounding | M110: =ABS(C110)/SUMPRODUCT(($A$4:$A$143=A110)*ABS($C$4:$C$143)) -> 4.8568378e-05 | N110: =E110/SUMIFS($E$4:$E$143,$A$4:$A$143,A110) -> 0.0037453184 | O110: =IF(AND(ABS(ROUND(M110,2)-D110)<0.0051,ABS(ROUND(N110,2)-F110)<0.0051),"OK","REVIEW") -> OK
A111: VISA | B111: VI-US CPS/SMALL TCKT REG (DB) | C111: 513.16 | D111: 0 | E111: 52 | F111: 0.01 | G111: 0.0005 | H111: 0.22 | I111: -11.69 | J111: =-ROUND(C111*G111+E111*H111,2) -> -11.7 | K111: =ROUND(J111-I111,2) -> -0.01 | L111: =IF(ABS(K111)<0.005,"OK",IF(ABS(K111)<=0.05,"Rounding","REVIEW")) -> Rounding | M111: =ABS(C111)/SUMPRODUCT(($A$4:$A$143=A111)*ABS($C$4:$C$143)) -> 0.00011554635 | N111: =E111/SUMIFS($E$4:$E$143,$A$4:$A$143,A111) -> 0.0097378277 | O111: =IF(AND(ABS(ROUND(M111,2)-D111)<0.0051,ABS(ROUND(N111,2)-F111)<0.0051),"OK","REVIEW") -> OK
A112: VISA | B112: VI-CNP P1 INFINITE SQ | C112: 139.48 | D112: 0 | E112: 4 | F112: 0 | G112: 0.026 | H112: 0.1 | I112: -4.02 | J112: =-ROUND(C112*G112+E112*H112,2) -> -4.03 | K112: =ROUND(J112-I112,2) -> -0.01 | L112: =IF(ABS(K112)<0.005,"OK",IF(ABS(K112)<=0.05,"Rounding","REVIEW")) -> Rounding | M112: =ABS(C112)/SUMPRODUCT(($A$4:$A$143=A112)*ABS($C$4:$C$143)) -> 3.14062e-05 | N112: =E112/SUMIFS($E$4:$E$143,$A$4:$A$143,A112) -> 0.00074906367 | O112: =IF(AND(ABS(ROUND(M112,2)-D112)<0.0051,ABS(ROUND(N112,2)-F112)<0.0051),"OK","REVIEW") -> OK
A113: VISA | B113: VI-COMM NON-PASS TRANS CREDIT | C113: -41323.31 | D113: 0.01 | E113: 75 | F113: 0.01 | G113: 0 | H113: 0 | I113: 0 | J113: 0 | K113: =ROUND(J113-I113,2) -> 0 | L113: =IF(ABS(K113)<0.005,"OK",IF(ABS(K113)<=0.05,"Rounding","REVIEW")) -> OK | M113: =ABS(C113)/SUMPRODUCT(($A$4:$A$143=A113)*ABS($C$4:$C$143)) -> 0.0093046181 | N113: =E113/SUMIFS($E$4:$E$143,$A$4:$A$143,A113) -> 0.014044944 | O113: =IF(AND(ABS(ROUND(M113,2)-D113)<0.0051,ABS(ROUND(N113,2)-F113)<0.0051),"OK","REVIEW") -> OK
A114: VISA | B114: VI-US BUS TIER 3 PRD 1 CEDP | C114: 40191.67 | D114: 0.01 | E114: 11 | F114: 0 | G114: 0.0285 | H114: 0.1 | I114: -1146.56 | J114: =-ROUND(C114*G114+E114*H114,2) -> -1146.56 | K114: =ROUND(J114-I114,2) -> 0 | L114: =IF(ABS(K114)<0.005,"OK",IF(ABS(K114)<=0.05,"Rounding","REVIEW")) -> OK | M114: =ABS(C114)/SUMPRODUCT(($A$4:$A$143=A114)*ABS($C$4:$C$143)) -> 0.0090498109 | N114: =E114/SUMIFS($E$4:$E$143,$A$4:$A$143,A114) -> 0.0020599251 | O114: =IF(AND(ABS(ROUND(M114,2)-D114)<0.0051,ABS(ROUND(N114,2)-F114)<0.0051),"OK","REVIEW") -> OK
A115: VISA | B115: VI-BUS PURCH RTL (PP) | C115: 81.83 | D115: 0 | E115: 2 | F115: 0 | G115: 0.0215 | H115: 0.1 | I115: -1.96 | J115: =-ROUND(C115*G115+E115*H115,2) -> -1.96 | K115: =ROUND(J115-I115,2) -> 0 | L115: =IF(ABS(K115)<0.005,"OK",IF(ABS(K115)<=0.05,"Rounding","REVIEW")) -> OK | M115: =ABS(C115)/SUMPRODUCT(($A$4:$A$143=A115)*ABS($C$4:$C$143)) -> 1.8425361e-05 | N115: =E115/SUMIFS($E$4:$E$143,$A$4:$A$143,A115) -> 0.00037453184 | O115: =IF(AND(ABS(ROUND(M115,2)-D115)<0.0051,ABS(ROUND(N115,2)-F115)<0.0051),"OK","REVIEW") -> OK
A116: VISA | B116: VI-SERVICES TRAD RWDS NTKN | C116: 9842.57 | D116: 0 | E116: 6 | F116: 0 | G116: 0.018 | H116: 0.1 | I116: -177.76 | J116: =-ROUND(C116*G116+E116*H116,2) -> -177.77 | K116: =ROUND(J116-I116,2) -> -0.01 | L116: =IF(ABS(K116)<0.005,"OK",IF(ABS(K116)<=0.05,"Rounding","REVIEW")) -> Rounding | M116: =ABS(C116)/SUMPRODUCT(($A$4:$A$143=A116)*ABS($C$4:$C$143)) -> 0.0022162154 | N116: =E116/SUMIFS($E$4:$E$143,$A$4:$A$143,A116) -> 0.0011235955 | O116: =IF(AND(ABS(ROUND(M116,2)-D116)<0.0051,ABS(ROUND(N116,2)-F116)<0.0051),"OK","REVIEW") -> OK
A117: VISA | B117: VI-CNP P1 SIGN PREFERRED | C117: 11290.93 | D117: 0 | E117: 37 | F117: 0.01 | G117: 0.025 | H117: 0.1 | I117: -285.96 | J117: =-ROUND(C117*G117+E117*H117,2) -> -285.97 | K117: =ROUND(J117-I117,2) -> -0.01 | L117: =IF(ABS(K117)<0.005,"OK",IF(ABS(K117)<=0.05,"Rounding","REVIEW")) -> Rounding | M117: =ABS(C117)/SUMPRODUCT(($A$4:$A$143=A117)*ABS($C$4:$C$143)) -> 0.0025423373 | N117: =E117/SUMIFS($E$4:$E$143,$A$4:$A$143,A117) -> 0.006928839 | O117: =IF(AND(ABS(ROUND(M117,2)-D117)<0.0051,ABS(ROUND(N117,2)-F117)<0.0051),"OK","REVIEW") -> OK
A118: DISCOVER | B118: DSCVR CNSMR ADJ VCHR PGM 3 PP | C118: -910.71 | D118: 0.01 | E118: 2 | F118: 0.01 | G118: 0 | H118: 0 | I118: 0 | J118: 0 | K118: =ROUND(J118-I118,2) -> 0 | L118: =IF(ABS(K118)<0.005,"OK",IF(ABS(K118)<=0.05,"Rounding","REVIEW")) -> OK | M118: =ABS(C118)/SUMPRODUCT(($A$4:$A$143=A118)*ABS($C$4:$C$143)) -> 0.0058216374 | N118: =E118/SUMIFS($E$4:$E$143,$A$4:$A$143,A118) -> 0.0099009901 | O118: =IF(AND(ABS(ROUND(M118,2)-D118)<0.0051,ABS(ROUND(N118,2)-F118)<0.0051),"OK","REVIEW") -> OK
A119: DISCOVER | B119: DSCVR PSLCARDNOTPRESENT(CP) | C119: 13791.62 | D119: 0.09 | E119: 7 | F119: 0.03 | G119: 0.0203 | H119: 0.1 | I119: -280.68 | J119: =-ROUND(C119*G119+E119*H119,2) -> -280.67 | K119: =ROUND(J119-I119,2) -> 0.01 | L119: =IF(ABS(K119)<0.005,"OK",IF(ABS(K119)<=0.05,"Rounding","REVIEW")) -> Rounding | M119: =ABS(C119)/SUMPRODUCT(($A$4:$A$143=A119)*ABS($C$4:$C$143)) -> 0.088161776 | N119: =E119/SUMIFS($E$4:$E$143,$A$4:$A$143,A119) -> 0.034653465 | O119: =IF(AND(ABS(ROUND(M119,2)-D119)<0.0051,ABS(ROUND(N119,2)-F119)<0.0051),"OK","REVIEW") -> OK
A120: DISCOVER | B120: DSCVR CNSMR ADJ VCHR PGM 3 DB | C120: -613.18 | D120: 0 | E120: 3 | F120: 0.01 | G120: 0 | H120: 0 | I120: 0 | J120: 0 | K120: =ROUND(J120-I120,2) -> 0 | L120: =IF(ABS(K120)<0.005,"OK",IF(ABS(K120)<=0.05,"Rounding","REVIEW")) -> OK | M120: =ABS(C120)/SUMPRODUCT(($A$4:$A$143=A120)*ABS($C$4:$C$143)) -> 0.0039197018 | N120: =E120/SUMIFS($E$4:$E$143,$A$4:$A$143,A120) -> 0.014851485 | O120: =IF(AND(ABS(ROUND(M120,2)-D120)<0.0051,ABS(ROUND(N120,2)-F120)<0.0051),"OK","REVIEW") -> OK
A121: DISCOVER | B121: DSCVR PSLCARDNOTPRESENT(DB) | C121: 3459.91 | D121: 0.02 | E121: 6 | F121: 0.03 | G121: 0.0175 | H121: 0.2 | I121: -61.75 | J121: =-ROUND(C121*G121+E121*H121,2) -> -61.75 | K121: =ROUND(J121-I121,2) -> 0 | L121: =IF(ABS(K121)<0.005,"OK",IF(ABS(K121)<=0.05,"Rounding","REVIEW")) -> OK | M121: =ABS(C121)/SUMPRODUCT(($A$4:$A$143=A121)*ABS($C$4:$C$143)) -> 0.022117185 | N121: =E121/SUMIFS($E$4:$E$143,$A$4:$A$143,A121) -> 0.02970297 | O121: =IF(AND(ABS(ROUND(M121,2)-D121)<0.0051,ABS(ROUND(N121,2)-F121)<0.0051),"OK","REVIEW") -> OK
A122: DISCOVER | B122: DSCVR CNSMR ADJ VCHR PGM 3 PR | C122: -784.99 | D122: 0.01 | E122: 3 | F122: 0.01 | G122: 0 | H122: 0 | I122: 0 | J122: 0 | K122: =ROUND(J122-I122,2) -> 0 | L122: =IF(ABS(K122)<0.005,"OK",IF(ABS(K122)<=0.05,"Rounding","REVIEW")) -> OK | M122: =ABS(C122)/SUMPRODUCT(($A$4:$A$143=A122)*ABS($C$4:$C$143)) -> 0.0050179828 | N122: =E122/SUMIFS($E$4:$E$143,$A$4:$A$143,A122) -> 0.014851485 | O122: =IF(AND(ABS(ROUND(M122,2)-D122)<0.0051,ABS(ROUND(N122,2)-F122)<0.0051),"OK","REVIEW") -> OK
A123: DISCOVER | B123: DSCVR CNSMR ADJ VCHR PGM 3 CP | C123: -49.72 | D123: 0 | E123: 2 | F123: 0.01 | G123: 0 | H123: 0 | I123: 0 | J123: 0 | K123: =ROUND(J123-I123,2) -> 0 | L123: =IF(ABS(K123)<0.005,"OK",IF(ABS(K123)<=0.05,"Rounding","REVIEW")) -> OK | M123: =ABS(C123)/SUMPRODUCT(($A$4:$A$143=A123)*ABS($C$4:$C$143)) -> 0.00031783094 | N123: =E123/SUMIFS($E$4:$E$143,$A$4:$A$143,A123) -> 0.0099009901 | O123: =IF(AND(ABS(ROUND(M123,2)-D123)<0.0051,ABS(ROUND(N123,2)-F123)<0.0051),"OK","REVIEW") -> OK
A124: DISCOVER | B124: DSCVR PSL RTL PP | C124: 9984.71 | D124: 0.06 | E124: 39 | F124: 0.19 | G124: 0.0225 | H124: 0.1 | I124: -228.55 | J124: =-ROUND(C124*G124+E124*H124,2) -> -228.56 | K124: =ROUND(J124-I124,2) -> -0.01 | L124: =IF(ABS(K124)<0.005,"OK",IF(ABS(K124)<=0.05,"Rounding","REVIEW")) -> Rounding | M124: =ABS(C124)/SUMPRODUCT(($A$4:$A$143=A124)*ABS($C$4:$C$143)) -> 0.063826422 | N124: =E124/SUMIFS($E$4:$E$143,$A$4:$A$143,A124) -> 0.19306931 | O124: =IF(AND(ABS(ROUND(M124,2)-D124)<0.0051,ABS(ROUND(N124,2)-F124)<0.0051),"OK","REVIEW") -> OK
A125: DISCOVER | B125: DSCVR-COMMELECALLOTHERS(DB) | C125: 2157.65 | D125: 0.01 | E125: 8 | F125: 0.04 | G125: 0.0245 | H125: 0.15 | I125: -54.06 | J125: =-ROUND(C125*G125+E125*H125,2) -> -54.06 | K125: =ROUND(J125-I125,2) -> 0 | L125: =IF(ABS(K125)<0.005,"OK",IF(ABS(K125)<=0.05,"Rounding","REVIEW")) -> OK | M125: =ABS(C125)/SUMPRODUCT(($A$4:$A$143=A125)*ABS($C$4:$C$143)) -> 0.013792597 | N125: =E125/SUMIFS($E$4:$E$143,$A$4:$A$143,A125) -> 0.03960396 | O125: =IF(AND(ABS(ROUND(M125,2)-D125)<0.0051,ABS(ROUND(N125,2)-F125)<0.0051),"OK","REVIEW") -> OK
A126: DISCOVER | B126: DSCVR PSL RTL CP | C126: 16342.61 | D126: 0.1 | E126: 34 | F126: 0.17 | G126: 0.0172 | H126: 0.1 | I126: -284.49 | J126: =-ROUND(C126*G126+E126*H126,2) -> -284.49 | K126: =ROUND(J126-I126,2) -> 0 | L126: =IF(ABS(K126)<0.005,"OK",IF(ABS(K126)<=0.05,"Rounding","REVIEW")) -> OK | M126: =ABS(C126)/SUMPRODUCT(($A$4:$A$143=A126)*ABS($C$4:$C$143)) -> 0.10446877 | N126: =E126/SUMIFS($E$4:$E$143,$A$4:$A$143,A126) -> 0.16831683 | O126: =IF(AND(ABS(ROUND(M126,2)-D126)<0.0051,ABS(ROUND(N126,2)-F126)<0.0051),"OK","REVIEW") -> OK
A127: DISCOVER | B127: DSCVR PSL RTL DB | C127: 3981.04 | D127: 0.03 | E127: 22 | F127: 0.11 | G127: 0.011 | H127: 0.16 | I127: -47.3 | J127: =-ROUND(C127*G127+E127*H127,2) -> -47.31 | K127: =ROUND(J127-I127,2) -> -0.01 | L127: =IF(ABS(K127)<0.005,"OK",IF(ABS(K127)<=0.05,"Rounding","REVIEW")) -> Rounding | M127: =ABS(C127)/SUMPRODUCT(($A$4:$A$143=A127)*ABS($C$4:$C$143)) -> 0.025448465 | N127: =E127/SUMIFS($E$4:$E$143,$A$4:$A$143,A127) -> 0.10891089 | O127: =IF(AND(ABS(ROUND(M127,2)-D127)<0.0051,ABS(ROUND(N127,2)-F127)<0.0051),"OK","REVIEW") -> OK
A128: DISCOVER | B128: DSCVR PSLCARDNOTPRESENT(PPLUS) | C128: 38607.67 | D128: 0.25 | E128: 10 | F128: 0.05 | G128: 0.0255 | H128: 0.1 | I128: -985.49 | J128: =-ROUND(C128*G128+E128*H128,2) -> -985.5 | K128: =ROUND(J128-I128,2) -> -0.01 | L128: =IF(ABS(K128)<0.005,"OK",IF(ABS(K128)<=0.05,"Rounding","REVIEW")) -> Rounding | M128: =ABS(C128)/SUMPRODUCT(($A$4:$A$143=A128)*ABS($C$4:$C$143)) -> 0.2467963 | N128: =E128/SUMIFS($E$4:$E$143,$A$4:$A$143,A128) -> 0.04950495 | O128: =IF(AND(ABS(ROUND(M128,2)-D128)<0.0051,ABS(ROUND(N128,2)-F128)<0.0051),"OK","REVIEW") -> OK
A129: DISCOVER | B129: DSCVR PSL RTL PR | C129: 52008.19 | D129: 0.33 | E129: 58 | F129: 0.29 | G129: 0.0174 | H129: 0.1 | I129: -910.75 | J129: =-ROUND(C129*G129+E129*H129,2) -> -910.74 | K129: =ROUND(J129-I129,2) -> 0.01 | L129: =IF(ABS(K129)<0.005,"OK",IF(ABS(K129)<=0.05,"Rounding","REVIEW")) -> Rounding | M129: =ABS(C129)/SUMPRODUCT(($A$4:$A$143=A129)*ABS($C$4:$C$143)) -> 0.332458 | N129: =E129/SUMIFS($E$4:$E$143,$A$4:$A$143,A129) -> 0.28712871 | O129: =IF(AND(ABS(ROUND(M129,2)-D129)<0.0051,ABS(ROUND(N129,2)-F129)<0.0051),"OK","REVIEW") -> OK
A130: DISCOVER | B130: DSCVR PSLCARDNOTPRESENT(PREM) | C130: 13743.37 | D130: 0.09 | E130: 8 | F130: 0.04 | G130: 0.0205 | H130: 0.1 | I130: -282.53 | J130: =-ROUND(C130*G130+E130*H130,2) -> -282.54 | K130: =ROUND(J130-I130,2) -> -0.01 | L130: =IF(ABS(K130)<0.005,"OK",IF(ABS(K130)<=0.05,"Rounding","REVIEW")) -> Rounding | M130: =ABS(C130)/SUMPRODUCT(($A$4:$A$143=A130)*ABS($C$4:$C$143)) -> 0.087853342 | N130: =E130/SUMIFS($E$4:$E$143,$A$4:$A$143,A130) -> 0.03960396 | O130: =IF(AND(ABS(ROUND(M130,2)-D130)<0.0051,ABS(ROUND(N130,2)-F130)<0.0051),"OK","REVIEW") -> OK
A131: AMERICAN EXPRESS | B131: AMEX PASS-THRU | C131: 1678631.3 | D131: 1 | E131: 1635 | F131: 1 | G131: 0 | H131: 0 | I131: 0 | J131: 0 | K131: =ROUND(J131-I131,2) -> 0 | L131: =IF(ABS(K131)<0.005,"OK",IF(ABS(K131)<=0.05,"Rounding","REVIEW")) -> OK | M131: =ABS(C131)/SUMPRODUCT(($A$4:$A$143=A131)*ABS($C$4:$C$143)) -> 1 | N131: =E131/SUMIFS($E$4:$E$143,$A$4:$A$143,A131) -> 1 | O131: =IF(AND(ABS(ROUND(M131,2)-D131)<0.0051,ABS(ROUND(N131,2)-F131)<0.0051),"OK","REVIEW") -> OK
...

Sheet Funded
A1: Amounts Funded
A2: Fees funded here belong to prior statements, so the Fees column differs from the Month End Charge (see Checks).
A3: Date Submitted | B3: Amount Submitted | C3: Paid by Others | D3: Disputes | E3: Adjustments | F3: Fees | G3: Date Funded | H3: Amount Funded | I3: Row check
A4: 46203 | B4: 509561.75 | C4: -118230.89 | D4: 0 | E4: 0 | F4: 0 | G4: 46204 | H4: 391330.86 | I4: =ROUND(SUM(B4:F4)-H4,2) -> 0
A5: 46203 | B5: 0 | C5: 0 | D5: 0 | E5: 0 | F5: -163012.13 | G5: 46205 | H5: -163012.13 | I5: =ROUND(SUM(B5:F5)-H5,2) -> 0
A6: 46204 | B6: 29047.87 | C6: 0 | D6: -1213.82 | E6: 0 | F6: 0 | G6: 46204 | H6: 27834.05 | I6: =ROUND(SUM(B6:F6)-H6,2) -> 0
A7: 46204 | B7: 391562.44 | C7: -55478.76 | D7: 0 | E7: 0 | F7: 0 | G7: 46205 | H7: 336083.68 | I7: =ROUND(SUM(B7:F7)-H7,2) -> 0
A8: 46205 | B8: 1739.76 | C8: 0 | D8: 0 | E8: 0 | F8: 0 | G8: 46205 | H8: 1739.76 | I8: =ROUND(SUM(B8:F8)-H8,2) -> 0
A9: 46205 | B9: 473942.28 | C9: -97077.08 | D9: 0 | E9: 0 | F9: 0 | G9: 46206 | H9: 376865.2 | I9: =ROUND(SUM(B9:F9)-H9,2) -> 0
A10: 46206 | B10: 12214.91 | C10: -544.42 | D10: 0 | E10: 0 | F10: 0 | G10: 46206 | H10: 11670.49 | I10: =ROUND(SUM(B10:F10)-H10,2) -> 0
A11: 46206 | B11: 124585.87 | C11: -20999.7 | D11: 0 | E11: 0 | F11: 0 | G11: 46207 | H11: 103586.17 | I11: =ROUND(SUM(B11:F11)-H11,2) -> 0
A12: 46207 | B12: -2360.77 | C12: 0 | D12: 0 | E12: 0 | F12: 0 | G12: 46207 | H12: -2360.77 | I12: =ROUND(SUM(B12:F12)-H12,2) -> 0
A13: 46207 | B13: 1965.52 | C13: -1965.52 | D13: 0 | E13: 0 | F13: 0 | G13: 46208 | H13: 0 | I13: =ROUND(SUM(B13:F13)-H13,2) -> 0
A14: 46208 | B14: 1818.92 | C14: 0 | D14: 0 | E14: 0 | F14: 0 | G14: 46209 | H14: 1818.92 | I14: =ROUND(SUM(B14:F14)-H14,2) -> 0
A15: 46209 | B15: 368117.09 | C15: -63882.42 | D15: 0 | E15: 0 | F15: 0 | G15: 46210 | H15: 304234.67 | I15: =ROUND(SUM(B15:F15)-H15,2) -> 0
... A57: 46234 | B57: 6679.24 | C57: -2466.5 | D57: 0 | E57: 0 | F57: 0 | G57: 46234 | H57: 4212.74 | I57: =ROUND(SUM(B57:F57)-H57,2) -> 0
A58: Total (statement) | B58: 8980209.2 | C58: -1678631.3 | D58: -1213.82 | E58: 0 | F58: -163012.13 | H58: 7137351.9
A59: Total (computed) | B59: =SUM(B4:B57) -> 8980209.2 | C59: =SUM(C4:C57) -> -1678631.3 | D59: =SUM(D4:D57) -> -1213.82 | E59: =SUM(E4:E57) -> 0 | F59: =SUM(F4:F57) -> -163012.13 | H59: =SUM(H4:H57) -> 7137351.9
A60: Difference | B60: =ROUND(B59-B58,2) -> 0 | C60: =ROUND(C59-C58,2) -> 0 | D60: =ROUND(D59-D58,2) -> 0 | E60: =ROUND(E59-E58,2) -> 0 | F60: =ROUND(F59-F58,2) -> 0 | H60: =ROUND(H59-H58,2) -> 0
